Workbook

Sheet Navigation
C6: TALENTS APARTMENT
C7: Accounting Information System
C8: ...home away from home
C11: DAILY INPUT
C12: Record Income | E12: All revenue transactions | H12: →
C13: Record Expenses | E13: Non-salary expense transactions | H13: →
C14: Staff Salaries | E14: Monthly company payroll totals | H14: →
C15: Budget & Targets | E15: Monthly budget vs actual variance | H15: →
C17: REPORTS & ANALYSIS
C18: Executive Dashboard | E18: KPIs + monthly P&L matrix | H18: →
C19: Charts & Analytics | E19: 6 interactive charts with location filter | H19: →
C20: General Ledger | E20: Double-entry records | H20: →
C21: Profit & Loss | E21: Annual income statement | H21: →
C22: Cash Flow | E22: Cash movements summary | H22: →
C23: Balance Sheet | E23: Financial position snapshot | H23: →
C24: Trial Balance | E24: Debit/credit verification | H24: →
C26: SYSTEM SETTINGS
C27: Chart of Accounts | E27: Account code structure | H27: →
C28: Dropdown Lists | E28: Master control for ALL dropdowns | H28: →
C29: Employee Records | E29: Staff info & payroll rates | H29: →

Sheet Revenue_Log
B2: Revenue Log
B3: Record all income transactions
A4: TOTAL: | H4: =SUBTOTAL(9,H6:H5000)
A5: Date | B5: Location | C5: Unit Name | D5: Account | E5: Description | F5: Txn ID | G5: Payment Method | H5: Amount
A6: 45299 | B6: Agbowo | C6: Anooore 1 | D6: Room Revenue | E6: Booking - Anooore 1 | F6: R0001 | G6: Bank Transfer | H6: 196558
A7: 45299 | B7: Agbowo | C7: Anooore 1 | D7: Extra Charges | E7: TV rental | F7: R0002 | G7: Cash | H7: 10000
A8: 45308 | B8: Agbowo | C8: Vine 1 | D8: Room Revenue | E8: Booking - Vine 1 | F8: R0003 | G8: Cash | H8: 176948
A9: 45310 | B9: Agbowo | C9: Vine 2 | D9: Room Revenue | E9: Booking - Vine 2 | F9: R0004 | G9: POS | H9: 354033
A10: 45310 | B10: Agbowo | C10: Vine 2 | D10: Form & Legal Fees | E10: Registration form fee | F10: R0005 | G10: Cash | H10: 5000
A11: 45298 | B11: Agbowo | C11: Provision Shop | D11: Room Revenue | E11: Booking - Provision Shop | F11: R0006 | G11: POS | H11: 298616
A12: 45298 | B12: Agbowo | C12: Provision Shop | D12: Extra Charges | E12: TV rental | F12: R0007 | G12: Cash | H12: 25000
A13: 45315 | B13: Agbowo | C13: Salon | D13: Room Revenue | E13: Booking - Salon | F13: R0008 | G13: Mobile Transfer | H13: 331695
A14: 45312 | B14: UI | C14: Anooore 2 | D14: Room Revenue | E14: Booking - Anooore 2 | F14: R0009 | G14: POS | H14: 479317
A15: 45294 | B15: UI | C15: Scholar | D15: Room Revenue | E15: Booking - Scholar | F15: R0010 | G15: Bank Transfer | H15: 263653
A16: 45303 | B16: UI | C16: Scholar 2 | D16: Room Revenue | E16: Booking - Scholar 2 | F16: R0011 | G16: Bank Transfer | H16: 291415
A17: 45297 | B17: UI | C17: Kollege | D17: Room Revenue | E17: Booking - Kollege | F17: R0012 | G17: Bank Transfer | H17: 191592

Sheet Expenses_Log
B2: Expenses Log
B3: Non-salary expenses (salaries tracked in Staff_Salaries sheet)
A4: TOTAL: | G4: =SUBTOTAL(9,G6:G5000)
A5: Date | B5: Location | C5: Category | D5: Vendor/Staff | E5: Department | F5: Description | G5: Amount | H5: Payment Method | I5: Acct Code
A6: 45292 | B6: Agbowo | C6: Loans & Advances | D6: Stanbic Bank | E6: Accounts | F6: Monthly loan repayment | G6: 200000 | H6: Bank Transfer
A7: 45294 | B7: Agbowo | C7: Maintenance | D7: Dayo Contractor | E7: Maintenance | F7: Paint touch-up | G7: 41000 | H7: Cash
A8: 45294 | B8: UI | C8: Utilities | D8: Waste Mgt Co | E8: Admin | F8: Water bill | G8: 41000 | H8: Bank Transfer
A9: 45295 | B9: UI | C9: Maintenance | D9: Plumber Bayo | E9: Maintenance | F9: Paint touch-up | G9: 24000 | H9: Cash
A10: 45300 | B10: Agbowo | C10: Construction | D10: Mr Taiwo | E10: Project | F10: Mason work | G10: 27000 | H10: Cash
A11: 45300 | B11: Agbowo | C11: Maintenance | D11: Plumber Bayo | E11: Maintenance | F11: Door/lock repair | G11: 10000 | H11: Cash
A12: 45302 | B12: UI | C12: Administrative | D12: Office Mart | E12: Admin | F12: Insurance premium | G12: 8000 | H12: Cash
A13: 45305 | B13: Agbowo | C13: Construction | D13: Engr Segun | E13: Project | F13: Tiling | G13: 48000 | H13: Cash

Sheet Staff_Salaries
B2: Staff Salaries
B3: Monthly company payroll — feeds into total expenses
A4: ANNUAL PAYROLL TOTAL: | E4: =SUMPRODUCT((Staff_Salaries!A6:A5000=Dashboard!$B$1)*(Staff_Salaries!E6:E5000)) | F4: Staff count: | G4: =COUNTA(Employee_Data!C6:C5000)
A5: Year | B5: Month | C5: Description | D5: Staff Count | E5: Total Paid | F5: Payment Method | G5: Notes
A6: 2024 | B6: January | C6: Monthly staff payroll | D6: 12 | E6: 407669 | F6: Bank Transfer
A7: 2024 | B7: February | C7: Monthly staff payroll | D7: 12 | E7: 406109 | F7: Bank Transfer
A8: 2024 | B8: March | C8: Monthly staff payroll | D8: 12 | E8: 401121 | F8: Bank Transfer
A9: 2024 | B9: April | C9: Monthly staff payroll | D9: 12 | E9: 411259 | F9: Bank Transfer
A10: 2024 | B10: May | C10: Monthly staff payroll | D10: 12 | E10: 411302 | F10: Bank Transfer
A11: 2024 | B11: June | C11: Monthly staff payroll | D11: 12 | E11: 407037 | F11: Bank Transfer
A12: 2024 | B12: July | C12: Monthly staff payroll | D12: 12 | E12: 412015 | F12: Bank Transfer
A13: 2024 | B13: August | C13: Monthly staff payroll | D13: 12 | E13: 403739 | F13: Bank Transfer
A14: 2024 | B14: September | C14: Monthly staff payroll | D14: 12 | E14: 397707 | F14: Bank Transfer
A15: 2024 | B15: October | C15: Monthly staff payroll | D15: 12 | E15: 408910 | F15: Bank Transfer
A16: 2024 | B16: November | C16: Monthly staff payroll | D16: 12 | E16: 397586 | F16: Bank Transfer
A17: 2024 | B17: December | C17: Monthly staff payroll | D17: 12 | E17: 409110 | F17: Bank Transfer

Sheet Budget
B2: Annual Budget
B3: Monthly targets — Variance = Budget minus Actual
B6: REVENUE BUDGET
B7: Category | C7: Jan | F7: Feb | I7: Mar | L7: Apr | O7: May | R7: Jun | U7: Jul | X7: Aug | AA7: Sep | AD7: Oct | AG7: Nov | AJ7: Dec | AM7: YEAR TOTAL
C8: Budget | D8: Actual | E8: Var | F8: Budget | G8: Actual | H8: Var | I8: Budget | J8: Actual | K8: Var | L8: Budget | M8: Actual | N8: Var | O8: Budget | P8: Actual | Q8: Var | R8: Budget | S8: Actual | T8: Var | U8: Budget | V8: Actual | W8: Var | X8: Budget | Y8: Actual | Z8: Var | AA8: Budget | AB8: Actual | AC8: Var | AD8: Budget | AE8: Actual | AF8: Var | AG8: Budget | AH8: Actual | AI8: Var | AJ8: Budget | AK8: Actual | AL8: Var | AM8: Budget | AN8: Actual | AO8: Var
B9: Room Revenue | C9: 3200000 | D9: =SUMPRODUCT((YEAR(Revenue_Log!A6:A5000)=Dashboard!$B$1)*(MONTH(Revenue_Log!A6:A5000)=1)*(Revenue_Log!D6:D5000="Room Revenue")*(Revenue_Log!H6:H5000)) | E9: =IFERROR(D9-C9,"—") | F9: 3000000 | G9: =SUMPRODUCT((YEAR(Revenue_Log!A6:A5000)=Dashboard!$B$1)*(MONTH(Revenue_Log!A6:A5000)=2)*(Revenue_Log!D6:D5000="Room Revenue")*(Revenue_Log!H6:H5000)) | H9: =IFERROR(G9-F9,"—") | I9: 2600000 | J9: =SUMPRODUCT((YEAR(Revenue_Log!A6:A5000)=Dashboard!$B$1)*(MONTH(Revenue_Log!A6:A5000)=3)*(Revenue_Log!D6:D5000="Room Revenue")*(Revenue_Log!H6:H5000)) | K9: =IFERROR(J9-I9,"—") | L9: 2400000 | M9: =SUMPRODUCT((YEAR(Revenue_Log!A6:A5000)=Dashboard!$B$1)*(MONTH(Revenue_Log!A6:A5000)=4)*(Revenue_Log!D6:D5000="Room Revenue")*(Revenue_Log!H6:H5000)) | N9: =IFERROR(M9-L9,"—") | O9: 2400000 | P9: =SUMPRODUCT((YEAR(Revenue_Log!A6:A5000)=Dashboard!$B$1)*(MONTH(Revenue_Log!A6:A5000)=5)*(Revenue_Log!D6:D5000="Room Revenue")*(Revenue_Log!H6:H5000)) | Q9: =IFERROR(P9-O9,"—") | R9: 1800000 | S9: =SUMPRODUCT((YEAR(Revenue_Log!A6:A5000)=Dashboard!$B$1)*(MONTH(Revenue_Log!A6:A5000)=6)*(Revenue_Log!D6:D5000="Room Revenue")*(Revenue_Log!H6:H5000)) | T9: =IFERROR(S9-R9,"—") | U9: 1600000 | V9: =SUMPRODUCT((YEAR(Revenue_Log!A6:A5000)=Dashboard!$B$1)*(MONTH(Revenue_Log!A6:A5000)=7)*(Revenue_Log!D6:D5000="Room Revenue")*(Revenue_Log!H6:H5000)) | W9: =IFERROR(V9-U9,"—") | X9: 1600000 | Y9: =SUMPRODUCT((YEAR(Revenue_Log!A6:A5000)=Dashboard!$B$1)*(MONTH(Revenue_Log!A6:A5000)=8)*(Revenue_Log!D6:D5000="Room Revenue")*(Revenue_Log!H6:H5000)) | Z9: =IFERROR(Y9-X9,"—") | AA9: 3200000 | AB9: =SUMPRODUCT((YEAR(Revenue_Log!A6:A5000)=Dashboard!$B$1)*(MONTH(Revenue_Log!A6:A5000)=9)*(Revenue_Log!D6:D5000="Room Revenue")*(Revenue_Log!H6:H5000)) | AC9: =IFERROR(AB9-AA9,"—") | AD9: 3200000 | AE9: =SUMPRODUCT((YEAR(Revenue_Log!A6:A5000)=Dashboard!$B$1)*(MONTH(Revenue_Log!A6:A5000)=10)*(Revenue_Log!D6:D5000="Room Revenue")*(Revenue_Log!H6:H5000)) | AF9: =IFERROR(AE9-AD9,"—") | AG9: 2800000 | AH9: =SUMPRODUCT((YEAR(Revenue_Log!A6:A5000)=Dashboard!$B$1)*(MONTH(Revenue_Log!A6:A5000)=11)*(Revenue_Log!D6:D5000="Room Revenue")*(Revenue_Log!H6:H5000)) | AI9: =IFERROR(AH9-AG9,"—") | AJ9: 2800000 | AK9: =SUMPRODUCT((YEAR(Revenue_Log!A6:A5000)=Dashboard!$B$1)*(MONTH(Revenue_Log!A6:A5000)=12)*(Revenue_Log!D6:D5000="Room Revenue")*(Revenue_Log!H6:H5000)) | AL9: =IFERROR(AK9-AJ9,"—") | AM9: =C9+F9+I9+L9+O9+R9+U9+X9+AA9+AD9+AG9+AJ9 | AN9: =D9+G9+J9+M9+P9+S9+V9+Y9+AB9+AE9+AH9+AK9 | AO9: =IFERROR(AN9-AM9,"—")
B10: Shop Rent | C10: 120000 | D10: =SUMPRODUCT((YEAR(Revenue_Log!A6:A5000)=Dashboard!$B$1)*(MONTH(Revenue_Log!A6:A5000)=1)*(Revenue_Log!D6:D5000="Shop Rent")*(Revenue_Log!H6:H5000)) | E10: =IFERROR(D10-C10,"—") | F10: 120000 | G10: =SUMPRODUCT((YEAR(Revenue_Log!A6:A5000)=Dashboard!$B$1)*(MONTH(Revenue_Log!A6:A5000)=2)*(Revenue_Log!D6:D5000="Shop Rent")*(Revenue_Log!H6:H5000)) | H10: =IFERROR(G10-F10,"—") | I10: 120000 | J10: =SUMPRODUCT((YEAR(Revenue_Log!A6:A5000)=Dashboard!$B$1)*(MONTH(Revenue_Log!A6:A5000)=3)*(Revenue_Log!D6:D5000="Shop Rent")*(Revenue_Log!H6:H5000)) | K10: =IFERROR(J10-I10,"—") | L10: 120000 | M10: =SUMPRODUCT((YEAR(Revenue_Log!A6:A5000)=Dashboard!$B$1)*(MONTH(Revenue_Log!A6:A5000)=4)*(Revenue_Log!D6:D5000="Shop Rent")*(Revenue_Log!H6:H5000)) | N10: =IFERROR(M10-L10,"—") | O10: 120000 | P10: =SUMPRODUCT((YEAR(Revenue_Log!A6:A5000)=Dashboard!$B$1)*(MONTH(Revenue_Log!A6:A5000)=5)*(Revenue_Log!D6:D5000="Shop Rent")*(Revenue_Log!H6:H5000)) | Q10: =IFERROR(P10-O10,"—") | R10: 120000 | S10: =SUMPRODUCT((YEAR(Revenue_Log!A6:A5000)=Dashboard!$B$1)*(MONTH(Revenue_Log!A6:A5000)=6)*(Revenue_Log!D6:D5000="Shop Rent")*(Revenue_Log!H6:H5000)) | T10: =IFERROR(S10-R10,"—") | U10: 120000 | V10: =SUMPRODUCT((YEAR(Revenue_Log!A6:A5000)=Dashboard!$B$1)*(MONTH(Revenue_Log!A6:A5000)=7)*(Revenue_Log!D6:D5000="Shop Rent")*(Revenue_Log!H6:H5000)) | W10: =IFERROR(V10-U10,"—") | X10: 120000 | Y10: =SUMPRODUCT((YEAR(Revenue_Log!A6:A5000)=Dashboard!$B$1)*(MONTH(Revenue_Log!A6:A5000)=8)*(Revenue_Log!D6:D5000="Shop Rent")*(Revenue_Log!H6:H5000)) | Z10: =IFERROR(Y10-X10,"—") | AA10: 120000 | AB10: =SUMPRODUCT((YEAR(Revenue_Log!A6:A5000)=Dashboard!$B$1)*(MONTH(Revenue_Log!A6:A5000)=9)*(Revenue_Log!D6:D5000="Shop Rent")*(Revenue_Log!H6:H5000)) | AC10: =IFERROR(AB10-AA10,"—") | AD10: 120000 | AE10: =SUMPRODUCT((YEAR(Revenue_Log!A6:A5000)=Dashboard!$B$1)*(MONTH(Revenue_Log!A6:A5000)=10)*(Revenue_Log!D6:D5000="Shop Rent")*(Revenue_Log!H6:H5000)) | AF10: =IFERROR(AE10-AD10,"—") | AG10: 120000 | AH10: =SUMPRODUCT((YEAR(Revenue_Log!A6:A5000)=Dashboard!$B$1)*(MONTH(Revenue_Log!A6:A5000)=11)*(Revenue_Log!D6:D5000="Shop Rent")*(Revenue_Log!H6:H5000)) | AI10: =IFERROR(AH10-AG10,"—") | AJ10: 120000 | AK10: =SUMPRODUCT((YEAR(Revenue_Log!A6:A5000)=Dashboard!$B$1)*(MONTH(Revenue_Log!A6:A5000)=12)*(Revenue_Log!D6:D5000="Shop Rent")*(Revenue_Log!H6:H5000)) | AL10: =IFERROR(AK10-AJ10,"—") | AM10: =C10+F10+I10+L10+O10+R10+U10+X10+AA10+AD10+AG10+AJ10 | AN10: =D10+G10+J10+M10+P10+S10+V10+Y10+AB10+AE10+AH10+AK10 | AO10: =IFERROR(AN10-AM10,"—")
B11: Caution Fee Income | C11: 75000 | D11: =SUMPRODUCT((YEAR(Revenue_Log!A6:A5000)=Dashboard!$B$1)*(MONTH(Revenue_Log!A6:A5000)=1)*(Revenue_Log!D6:D5000="Caution Fee Income")*(Revenue_Log!H6:H5000)) | E11: =IFERROR(D11-C11,"—") | F11: 50000 | G11: =SUMPRODUCT((YEAR(Revenue_Log!A6:A5000)=Dashboard!$B$1)*(MONTH(Revenue_Log!A6:A5000)=2)*(Revenue_Log!D6:D5000="Caution Fee Income")*(Revenue_Log!H6:H5000)) | H11: =IFERROR(G11-F11,"—") | I11: 50000 | J11: =SUMPRODUCT((YEAR(Revenue_Log!A6:A5000)=Dashboard!$B$1)*(MONTH(Revenue_Log!A6:A5000)=3)*(Revenue_Log!D6:D5000="Caution Fee Income")*(Revenue_Log!H6:H5000)) | K11: =IFERROR(J11-I11,"—") | L11: 50000 | M11: =SUMPRODUCT((YEAR(Revenue_Log!A6:A5000)=Dashboard!$B$1)*(MONTH(Revenue_Log!A6:A5000)=4)*(Revenue_Log!D6:D5000="Caution Fee Income")*(Revenue_Log!H6:H5000)) | N11: =IFERROR(M11-L11,"—") | O11: 50000 | P11: =SUMPRODUCT((YEAR(Revenue_Log!A6:A5000)=Dashboard!$B$1)*(MONTH(Revenue_Log!A6:A5000)=5)*(Revenue_Log!D6:D5000="Caution Fee Income")*(Revenue_Log!H6:H5000)) | Q11: =IFERROR(P11-O11,"—") | R11: 50000 | S11: =SUMPRODUCT((YEAR(Revenue_Log!A6:A5000)=Dashboard!$B$1)*(MONTH(Revenue_Log!A6:A5000)=6)*(Revenue_Log!D6:D5000="Caution Fee Income")*(Revenue_Log!H6:H5000)) | T11: =IFERROR(S11-R11,"—") | U11: 50000 | V11: =SUMPRODUCT((YEAR(Revenue_Log!A6:A5000)=Dashboard!$B$1)*(MONTH(Revenue_Log!A6:A5000)=7)*(Revenue_Log!D6:D5000="Caution Fee Income")*(Revenue_Log!H6:H5000)) | W11: =IFERROR(V11-U11,"—") | X11: 50000 | Y11: =SUMPRODUCT((YEAR(Revenue_Log!A6:A5000)=Dashboard!$B$1)*(MONTH(Revenue_Log!A6:A5000)=8)*(Revenue_Log!D6:D5000="Caution Fee Income")*(Revenue_Log!H6:H5000)) | Z11: =IFERROR(Y11-X11,"—") | AA11: 75000 | AB11: =SUMPRODUCT((YEAR(Revenue_Log!A6:A5000)=Dashboard!$B$1)*(MONTH(Revenue_Log!A6:A5000)=9)*(Revenue_Log!D6:D5000="Caution Fee Income")*(Revenue_Log!H6:H5000)) | AC11: =IFERROR(AB11-AA11,"—") | AD11: 75000 | AE11: =SUMPRODUCT((YEAR(Revenue_Log!A6:A5000)=Dashboard!$B$1)*(MONTH(Revenue_Log!A6:A5000)=10)*(Revenue_Log!D6:D5000="Caution Fee Income")*(Revenue_Log!H6:H5000)) | AF11: =IFERROR(AE11-AD11,"—") | AG11: 50000 | AH11: =SUMPRODUCT((YEAR(Revenue_Log!A6:A5000)=Dashboard!$B$1)*(MONTH(Revenue_Log!A6:A5000)=11)*(Revenue_Log!D6:D5000="Caution Fee Income")*(Revenue_Log!H6:H5000)) | AI11: =IFERROR(AH11-AG11,"—") | AJ11: 50000 | AK11: =SUMPRODUCT((YEAR(Revenue_Log!A6:A5000)=Dashboard!$B$1)*(MONTH(Revenue_Log!A6:A5000)=12)*(Revenue_Log!D6:D5000="Caution Fee Income")*(Revenue_Log!H6:H5000)) | AL11: =IFERROR(AK11-AJ11,"—") | AM11: =C11+F11+I11+L11+O11+R11+U11+X11+AA11+AD11+AG11+AJ11 | AN11: =D11+G11+J11+M11+P11+S11+V11+Y11+AB11+AE11+AH11+AK11 | AO11: =IFERROR(AN11-AM11,"—")
B12: Extra Charges | C12: 150000 | D12: =SUMPRODUCT((YEAR(Revenue_Log!A6:A5000)=Dashboard!$B$1)*(MONTH(Revenue_Log!A6:A5000)=1)*(Revenue_Log!D6:D5000="Extra Charges")*(Revenue_Log!H6:H5000)) | E12: =IFERROR(D12-C12,"—") | F12: 130000 | G12: =SUMPRODUCT((YEAR(Revenue_Log!A6:A5000)=Dashboard!$B$1)*(MONTH(Revenue_Log!A6:A5000)=2)*(Revenue_Log!D6:D5000="Extra Charges")*(Revenue_Log!H6:H5000)) | H12: =IFERROR(G12-F12,"—") | I12: 110000 | J12: =SUMPRODUCT((YEAR(Revenue_Log!A6:A5000)=Dashboard!$B$1)*(MONTH(Revenue_Log!A6:A5000)=3)*(Revenue_Log!D6:D5000="Extra Charges")*(Revenue_Log!H6:H5000)) | K12: =IFERROR(J12-I12,"—") | L12: 100000 | M12: =SUMPRODUCT((YEAR(Revenue_Log!A6:A5000)=Dashboard!$B$1)*(MONTH(Revenue_Log!A6:A5000)=4)*(Revenue_Log!D6:D5000="Extra Charges")*(Revenue_Log!H6:H5000)) | N12: =IFERROR(M12-L12,"—") | O12: 100000 | P12: =SUMPRODUCT((YEAR(Revenue_Log!A6:A5000)=Dashboard!$B$1)*(MONTH(Revenue_Log!A6:A5000)=5)*(Revenue_Log!D6:D5000="Extra Charges")*(Revenue_Log!H6:H5000)) | Q12: =IFERROR(P12-O12,"—") | R12: 80000 | S12: =SUMPRODUCT((YEAR(Revenue_Log!A6:A5000)=Dashboard!$B$1)*(MONTH(Revenue_Log!A6:A5000)=6)*(Revenue_Log!D6:D5000="Extra Charges")*(Revenue_Log!H6:H5000)) | T12: =IFERROR(S12-R12,"—") | U12: 70000 | V12: =SUMPRODUCT((YEAR(Revenue_Log!A6:A5000)=Dashboard!$B$1)*(MONTH(Revenue_Log!A6:A5000)=7)*(Revenue_Log!D6:D5000="Extra Charges")*(Revenue_Log!H6:H5000)) | W12: =IFERROR(V12-U12,"—") | X12: 70000 | Y12: =SUMPRODUCT((YEAR(Revenue_Log!A6:A5000)=Dashboard!$B$1)*(MONTH(Revenue_Log!A6:A5000)=8)*(Revenue_Log!D6:D5000="Extra Charges")*(Revenue_Log!H6:H5000)) | Z12: =IFERROR(Y12-X12,"—") | AA12: 150000 | AB12: =SUMPRODUCT((YEAR(Revenue_Log!A6:A5000)=Dashboard!$B$1)*(MONTH(Revenue_Log!A6:A5000)=9)*(Revenue_Log!D6:D5000="Extra Charges")*(Revenue_Log!H6:H5000)) | AC12: =IFERROR(AB12-AA12,"—") | AD12: 150000 | AE12: =SUMPRODUCT((YEAR(Revenue_Log!A6:A5000)=Dashboard!$B$1)*(MONTH(Revenue_Log!A6:A5000)=10)*(Revenue_Log!D6:D5000="Extra Charges")*(Revenue_Log!H6:H5000)) | AF12: =IFERROR(AE12-AD12,"—") | AG12: 110000 | AH12: =SUMPRODUCT((YEAR(Revenue_Log!A6:A5000)=Dashboard!$B$1)*(MONTH(Revenue_Log!A6:A5000)=11)*(Revenue_Log!D6:D5000="Extra Charges")*(Revenue_Log!H6:H5000)) | AI12: =IFERROR(AH12-AG12,"—") | AJ12: 110000 | AK12: =SUMPRODUCT((YEAR(Revenue_Log!A6:A5000)=Dashboard!$B$1)*(MONTH(Revenue_Log!A6:A5000)=12)*(Revenue_Log!D6:D5000="Extra Charges")*(Revenue_Log!H6:H5000)) | AL12: =IFERROR(AK12-AJ12,"—") | AM12: =C12+F12+I12+L12+O12+R12+U12+X12+AA12+AD12+AG12+AJ12 | AN12: =D12+G12+J12+M12+P12+S12+V12+Y12+AB12+AE12+AH12+AK12 | AO12: =IFERROR(AN12-AM12,"—")
B13: Form & Legal Fees | C13: 80000 | D13: =SUMPRODUCT((YEAR(Revenue_Log!A6:A5000)=Dashboard!$B$1)*(MONTH(Revenue_Log!A6:A5000)=1)*(Revenue_Log!D6:D5000="Form & Legal Fees")*(Revenue_Log!H6:H5000)) | E13: =IFERROR(D13-C13,"—") | F13: 60000 | G13: =SUMPRODUCT((YEAR(Revenue_Log!A6:A5000)=Dashboard!$B$1)*(MONTH(Revenue_Log!A6:A5000)=2)*(Revenue_Log!D6:D5000="Form & Legal Fees")*(Revenue_Log!H6:H5000)) | H13: =IFERROR(G13-F13,"—") | I13: 50000 | J13: =SUMPRODUCT((YEAR(Revenue_Log!A6:A5000)=Dashboard!$B$1)*(MONTH(Revenue_Log!A6:A5000)=3)*(Revenue_Log!D6:D5000="Form & Legal Fees")*(Revenue_Log!H6:H5000)) | K13: =IFERROR(J13-I13,"—") | L13: 45000 | M13: =SUMPRODUCT((YEAR(Revenue_Log!A6:A5000)=Dashboard!$B$1)*(MONTH(Revenue_Log!A6:A5000)=4)*(Revenue_Log!D6:D5000="Form & Legal Fees")*(Revenue_Log!H6:H5000)) | N13: =IFERROR(M13-L13,"—") | O13: 45000 | P13: =SUMPRODUCT((YEAR(Revenue_Log!A6:A5000)=Dashboard!$B$1)*(MONTH(Revenue_Log!A6:A5000)=5)*(Revenue_Log!D6:D5000="Form & Legal Fees")*(Revenue_Log!H6:H5000)) | Q13: =IFERROR(P13-O13,"—") | R13: 35000 | S13: =SUMPRODUCT((YEAR(Revenue_Log!A6:A5000)=Dashboard!$B$1)*(MONTH(Revenue_Log!A6:A5000)=6)*(Revenue_Log!D6:D5000="Form & Legal Fees")*(Revenue_Log!H6:H5000)) | T13: =IFERROR(S13-R13,"—") | U13: 30000 | V13: =SUMPRODUCT((YEAR(Revenue_Log!A6:A5000)=Dashboard!$B$1)*(MONTH(Revenue_Log!A6:A5000)=7)*(Revenue_Log!D6:D5000="Form & Legal Fees")*(Revenue_Log!H6:H5000)) | W13: =IFERROR(V13-U13,"—") | X13: 30000 | Y13: =SUMPRODUCT((YEAR(Revenue_Log!A6:A5000)=Dashboard!$B$1)*(MONTH(Revenue_Log!A6:A5000)=8)*(Revenue_Log!D6:D5000="Form & Legal Fees")*(Revenue_Log!H6:H5000)) | Z13: =IFERROR(Y13-X13,"—") | AA13: 80000 | AB13: =SUMPRODUCT((YEAR(Revenue_Log!A6:A5000)=Dashboard!$B$1)*(MONTH(Revenue_Log!A6:A5000)=9)*(Revenue_Log!D6:D5000="Form & Legal Fees")*(Revenue_Log!H6:H5000)) | AC13: =IFERROR(AB13-AA13,"—") | AD13: 80000 | AE13: =SUMPRODUCT((YEAR(Revenue_Log!A6:A5000)=Dashboard!$B$1)*(MONTH(Revenue_Log!A6:A5000)=10)*(Revenue_Log!D6:D5000="Form & Legal Fees")*(Revenue_Log!H6:H5000)) | AF13: =IFERROR(AE13-AD13,"—") | AG13: 60000 | AH13: =SUMPRODUCT((YEAR(Revenue_Log!A6:A5000)=Dashboard!$B$1)*(MONTH(Revenue_Log!A6:A5000)=11)*(Revenue_Log!D6:D5000="Form & Legal Fees")*(Revenue_Log!H6:H5000)) | AI13: =IFERROR(AH13-AG13,"—") | AJ13: 60000 | AK13: =SUMPRODUCT((YEAR(Revenue_Log!A6:A5000)=Dashboard!$B$1)*(MONTH(Revenue_Log!A6:A5000)=12)*(Revenue_Log!D6:D5000="Form & Legal Fees")*(Revenue_Log!H6:H5000)) | AL13: =IFERROR(AK13-AJ13,"—") | AM13: =C13+F13+I13+L13+O13+R13+U13+X13+AA13+AD13+AG13+AJ13 | AN13: =D13+G13+J13+M13+P13+S13+V13+Y13+AB13+AE13+AH13+AK13 | AO13: =IFERROR(AN13-AM13,"—")
B14: Other Income | C14: 0 | D14: =SUMPRODUCT((YEAR(Revenue_Log!A6:A5000)=Dashboard!$B$1)*(MONTH(Revenue_Log!A6:A5000)=1)*(Revenue_Log!D6:D5000="Other Income")*(Revenue_Log!H6:H5000)) | E14: =IFERROR(D14-C14,"—") | F14: 0 | G14: =SUMPRODUCT((YEAR(Revenue_Log!A6:A5000)=Dashboard!$B$1)*(MONTH(Revenue_Log!A6:A5000)=2)*(Revenue_Log!D6:D5000="Other Income")*(Revenue_Log!H6:H5000)) | H14: =IFERROR(G14-F14,"—") | I14: 0 | J14: =SUMPRODUCT((YEAR(Revenue_Log!A6:A5000)=Dashboard!$B$1)*(MONTH(Revenue_Log!A6:A5000)=3)*(Revenue_Log!D6:D5000="Other Income")*(Revenue_Log!H6:H5000)) | K14: =IFERROR(J14-I14,"—") | L14: 0 | M14: =SUMPRODUCT((YEAR(Revenue_Log!A6:A5000)=Dashboard!$B$1)*(MONTH(Revenue_Log!A6:A5000)=4)*(Revenue_Log!D6:D5000="Other Income")*(Revenue_Log!H6:H5000)) | N14: =IFERROR(M14-L14,"—") | O14: 0 | P14: =SUMPRODUCT((YEAR(Revenue_Log!A6:A5000)=Dashboard!$B$1)*(MONTH(Revenue_Log!A6:A5000)=5)*(Revenue_Log!D6:D5000="Other Income")*(Revenue_Log!H6:H5000)) | Q14: =IFERROR(P14-O14,"—") | R14: 0 | S14: =SUMPRODUCT((YEAR(Revenue_Log!A6:A5000)=Dashboard!$B$1)*(MONTH(Revenue_Log!A6:A5000)=6)*(Revenue_Log!D6:D5000="Other Income")*(Revenue_Log!H6:H5000)) | T14: =IFERROR(S14-R14,"—") | U14: 0 | V14: =SUMPRODUCT((YEAR(Revenue_Log!A6:A5000)=Dashboard!$B$1)*(MONTH(Revenue_Log!A6:A5000)=7)*(Revenue_Log!D6:D5000="Other Income")*(Revenue_Log!H6:H5000)) | W14: =IFERROR(V14-U14,"—") | X14: 0 | Y14: =SUMPRODUCT((YEAR(Revenue_Log!A6:A5000)=Dashboard!$B$1)*(MONTH(Revenue_Log!A6:A5000)=8)*(Revenue_Log!D6:D5000="Other Income")*(Revenue_Log!H6:H5000)) | Z14: =IFERROR(Y14-X14,"—") | AA14: 0 | AB14: =SUMPRODUCT((YEAR(Revenue_Log!A6:A5000)=Dashboard!$B$1)*(MONTH(Revenue_Log!A6:A5000)=9)*(Revenue_Log!D6:D5000="Other Income")*(Revenue_Log!H6:H5000)) | AC14: =IFERROR(AB14-AA14,"—") | AD14: 0 | AE14: =SUMPRODUCT((YEAR(Revenue_Log!A6:A5000)=Dashboard!$B$1)*(MONTH(Revenue_Log!A6:A5000)=10)*(Revenue_Log!D6:D5000="Other Income")*(Revenue_Log!H6:H5000)) | AF14: =IFERROR(AE14-AD14,"—") | AG14: 0 | AH14: =SUMPRODUCT((YEAR(Revenue_Log!A6:A5000)=Dashboard!$B$1)*(MONTH(Revenue_Log!A6:A5000)=11)*(Revenue_Log!D6:D5000="Other Income")*(Revenue_Log!H6:H5000)) | AI14: =IFERROR(AH14-AG14,"—") | AJ14: 0 | AK14: =SUMPRODUCT((YEAR(Revenue_Log!A6:A5000)=Dashboard!$B$1)*(MONTH(Revenue_Log!A6:A5000)=12)*(Revenue_Log!D6:D5000="Other Income")*(Revenue_Log!H6:H5000)) | AL14: =IFERROR(AK14-AJ14,"—") | AM14: =C14+F14+I14+L14+O14+R14+U14+X14+AA14+AD14+AG14+AJ14 | AN14: =D14+G14+J14+M14+P14+S14+V14+Y14+AB14+AE14+AH14+AK14 | AO14: =IFERROR(AN14-AM14,"—")
B15: TOTAL REVENUE | C15: =SUM(C9:C14) | D15: =SUM(D9:D14) | E15: =IFERROR(SUM(E9:E14),"—") | F15: =SUM(F9:F14) | G15: =SUM(G9:G14) | H15: =IFERROR(SUM(H9:H14),"—") | I15: =SUM(I9:I14) | J15: =SUM(J9:J14) | K15: =IFERROR(SUM(K9:K14),"—") | L15: =SUM(L9:L14) | M15: =SUM(M9:M14) | N15: =IFERROR(SUM(N9:N14),"—") | O15: =SUM(O9:O14) | P15: =SUM(P9:P14) | Q15: =IFERROR(SUM(Q9:Q14),"—") | R15: =SUM(R9:R14) | S15: =SUM(S9:S14) | T15: =IFERROR(SUM(T9:T14),"—") | U15: =SUM(U9:U14) | V15: =SUM(V9:V14) | W15: =IFERROR(SUM(W9:W14),"—") | X15: =SUM(X9:X14) | Y15: =SUM(Y9:Y14) | Z15: =IFERROR(SUM(Z9:Z14),"—") | AA15: =SUM(AA9:AA14) | AB15: =SUM(AB9:AB14) | AC15: =IFERROR(SUM(AC9:AC14),"—") | AD15: =SUM(AD9:AD14) | AE15: =SUM(AE9:AE14) | AF15: =IFERROR(SUM(AF9:AF14),"—") | AG15: =SUM(AG9:AG14) | AH15: =SUM(AH9:AH14) | AI15: =IFERROR(SUM(AI9:AI14),"—") | AJ15: =SUM(AJ9:AJ14) | AK15: =SUM(AK9:AK14) | AL15: =IFERROR(SUM(AL9:AL14),"—") | AM15: =SUM(AM9:AM14) | AN15: =SUM(AN9:AN14) | AO15: =IFERROR(SUM(AO9:AO14),"—")
B17: EXPENSE BUDGET
B18: Salaries | C18: 400000 | D18: =SUMPRODUCT((Staff_Salaries!A6:A5000=Dashboard!$B$1)*(Staff_Salaries!B6:B5000="January")*(Staff_Salaries!E6:E5000)) | E18: =IFERROR(C18-D18,"—") | F18: 400000 | G18: =SUMPRODUCT((Staff_Salaries!A6:A5000=Dashboard!$B$1)*(Staff_Salaries!B6:B5000="February")*(Staff_Salaries!E6:E5000)) | H18: =IFERROR(F18-G18,"—") | I18: 400000 | J18: =SUMPRODUCT((Staff_Salaries!A6:A5000=Dashboard!$B$1)*(Staff_Salaries!B6:B5000="March")*(Staff_Salaries!E6:E5000)) | K18: =IFERROR(I18-J18,"—") | L18: 400000 | M18: =SUMPRODUCT((Staff_Salaries!A6:A5000=Dashboard!$B$1)*(Staff_Salaries!B6:B5000="April")*(Staff_Salaries!E6:E5000)) | N18: =IFERROR(L18-M18,"—") | O18: 400000 | P18: =SUMPRODUCT((Staff_Salaries!A6:A5000=Dashboard!$B$1)*(Staff_Salaries!B6:B5000="May")*(Staff_Salaries!E6:E5000)) | Q18: =IFERROR(O18-P18,"—") | R18: 400000 | S18: =SUMPRODUCT((Staff_Salaries!A6:A5000=Dashboard!$B$1)*(Staff_Salaries!B6:B5000="June")*(Staff_Salaries!E6:E5000)) | T18: =IFERROR(R18-S18,"—") | U18: 400000 | V18: =SUMPRODUCT((Staff_Salaries!A6:A5000=Dashboard!$B$1)*(Staff_Salaries!B6:B5000="July")*(Staff_Salaries!E6:E5000)) | W18: =IFERROR(U18-V18,"—") | X18: 400000 | Y18: =SUMPRODUCT((Staff_Salaries!A6:A5000=Dashboard!$B$1)*(Staff_Salaries!B6:B5000="August")*(Staff_Salaries!E6:E5000)) | Z18: =IFERROR(X18-Y18,"—") | AA18: 400000 | AB18: =SUMPRODUCT((Staff_Salaries!A6:A5000=Dashboard!$B$1)*(Staff_Salaries!B6:B5000="September")*(Staff_Salaries!E6:E5000)) | AC18: =IFERROR(AA18-AB18,"—") | AD18: 400000 | AE18: =SUMPRODUCT((Staff_Salaries!A6:A5000=Dashboard!$B$1)*(Staff_Salaries!B6:B5000="October")*(Staff_Salaries!E6:E5000)) | AF18: =IFERROR(AD18-AE18,"—") | AG18: 400000 | AH18: =SUMPRODUCT((Staff_Salaries!A6:A5000=Dashboard!$B$1)*(Staff_Salaries!B6:B5000="November")*(Staff_Salaries!E6:E5000)) | AI18: =IFERROR(AG18-AH18,"—") | AJ18: 400000 | AK18: =SUMPRODUCT((Staff_Salaries!A6:A5000=Dashboard!$B$1)*(Staff_Salaries!B6:B5000="December")*(Staff_Salaries!E6:E5000)) | AL18: =IFERROR(AJ18-AK18,"—") | AM18: =C18+F18+I18+L18+O18+R18+U18+X18+AA18+AD18+AG18+AJ18 | AN18: =D18+G18+J18+M18+P18+S18+V18+Y18+AB18+AE18+AH18+AK18 | AO18: =IFERROR(AM18-AN18,"—")
B19: Construction | C19: 350000 | D19: =SUMPRODUCT((YEAR(Expenses_Log!A6:A5000)=Dashboard!$B$1)*(MONTH(Expenses_Log!A6:A5000)=1)*(Expenses_Log!C6:C5000="Construction")*(Expenses_Log!G6:G5000)) | E19: =IFERROR(C19-D19,"—") | F19: 300000 | G19: =SUMPRODUCT((YEAR(Expenses_Log!A6:A5000)=Dashboard!$B$1)*(MONTH(Expenses_Log!A6:A5000)=2)*(Expenses_Log!C6:C5000="Construction")*(Expenses_Log!G6:G5000)) | H19: =IFERROR(F19-G19,"—") | I19: 250000 | J19: =SUMPRODUCT((YEAR(Expenses_Log!A6:A5000)=Dashboard!$B$1)*(MONTH(Expenses_Log!A6:A5000)=3)*(Expenses_Log!C6:C5000="Construction")*(Expenses_Log!G6:G5000)) | K19: =IFERROR(I19-J19,"—") | L19: 200000 | M19: =SUMPRODUCT((YEAR(Expenses_Log!A6:A5000)=Dashboard!$B$1)*(MONTH(Expenses_Log!A6:A5000)=4)*(Expenses_Log!C6:C5000="Construction")*(Expenses_Log!G6:G5000)) | N19: =IFERROR(L19-M19,"—") | O19: 150000 | P19: =SUMPRODUCT((YEAR(Expenses_Log!A6:A5000)=Dashboard!$B$1)*(MONTH(Expenses_Log!A6:A5000)=5)*(Expenses_Log!C6:C5000="Construction")*(Expenses_Log!G6:G5000)) | Q19: =IFERROR(O19-P19,"—") | R19: 100000 | S19: =SUMPRODUCT((YEAR(Expenses_Log!A6:A5000)=Dashboard!$B$1)*(MONTH(Expenses_Log!A6:A5000)=6)*(Expenses_Log!C6:C5000="Construction")*(Expenses_Log!G6:G5000)) | T19: =IFERROR(R19-S19,"—") | U19: 0 | V19: =SUMPRODUCT((YEAR(Expenses_Log!A6:A5000)=Dashboard!$B$1)*(MONTH(Expenses_Log!A6:A5000)=7)*(Expenses_Log!C6:C5000="Construction")*(Expenses_Log!G6:G5000)) | W19: =IFERROR(U19-V19,"—") | X19: 0 | Y19: =SUMPRODUCT((YEAR(Expenses_Log!A6:A5000)=Dashboard!$B$1)*(MONTH(Expenses_Log!A6:A5000)=8)*(Expenses_Log!C6:C5000="Construction")*(Expenses_Log!G6:G5000)) | Z19: =IFERROR(X19-Y19,"—") | AA19: 0 | AB19: =SUMPRODUCT((YEAR(Expenses_Log!A6:A5000)=Dashboard!$B$1)*(MONTH(Expenses_Log!A6:A5000)=9)*(Expenses_Log!C6:C5000="Construction")*(Expenses_Log!G6:G5000)) | AC19: =IFERROR(AA19-AB19,"—") | AD19: 0 | AE19: =SUMPRODUCT((YEAR(Expenses_Log!A6:A5000)=Dashboard!$B$1)*(MONTH(Expenses_Log!A6:A5000)=10)*(Expenses_Log!C6:C5000="Construction")*(Expenses_Log!G6:G5000)) | AF19: =IFERROR(AD19-AE19,"—") | AG19: 0 | AH19: =SUMPRODUCT((YEAR(Expenses_Log!A6:A5000)=Dashboard!$B$1)*(MONTH(Expenses_Log!A6:A5000)=11)*(Expenses_Log!C6:C5000="Construction")*(Expenses_Log!G6:G5000)) | AI19: =IFERROR(AG19-AH19,"—") | AJ19: 0 | AK19: =SUMPRODUCT((YEAR(Expenses_Log!A6:A5000)=Dashboard!$B$1)*(MONTH(Expenses_Log!A6:A5000)=12)*(Expenses_Log!C6:C5000="Construction")*(Expenses_Log!G6:G5000)) | AL19: =IFERROR(AJ19-AK19,"—") | AM19: =C19+F19+I19+L19+O19+R19+U19+X19+AA19+AD19+AG19+AJ19 | AN19: =D19+G19+J19+M19+P19+S19+V19+Y19+AB19+AE19+AH19+AK19 | AO19: =IFERROR(AM19-AN19,"—")
B20: Maintenance | C20: 100000 | D20: =SUMPRODUCT((YEAR(Expenses_Log!A6:A5000)=Dashboard!$B$1)*(MONTH(Expenses_Log!A6:A5000)=1)*(Expenses_Log!C6:C5000="Maintenance")*(Expenses_Log!G6:G5000)) | E20: =IFERROR(C20-D20,"—") | F20: 90000 | G20: =SUMPRODUCT((YEAR(Expenses_Log!A6:A5000)=Dashboard!$B$1)*(MONTH(Expenses_Log!A6:A5000)=2)*(Expenses_Log!C6:C5000="Maintenance")*(Expenses_Log!G6:G5000)) | H20: =IFERROR(F20-G20,"—") | I20: 90000 | J20: =SUMPRODUCT((YEAR(Expenses_Log!A6:A5000)=Dashboard!$B$1)*(MONTH(Expenses_Log!A6:A5000)=3)*(Expenses_Log!C6:C5000="Maintenance")*(Expenses_Log!G6:G5000)) | K20: =IFERROR(I20-J20,"—") | L20: 80000 | M20: =SUMPRODUCT((YEAR(Expenses_Log!A6:A5000)=Dashboard!$B$1)*(MONTH(Expenses_Log!A6:A5000)=4)*(Expenses_Log!C6:C5000="Maintenance")*(Expenses_Log!G6:G5000)) | N20: =IFERROR(L20-M20,"—") | O20: 80000 | P20: =SUMPRODUCT((YEAR(Expenses_Log!A6:A5000)=Dashboard!$B$1)*(MONTH(Expenses_Log!A6:A5000)=5)*(Expenses_Log!C6:C5000="Maintenance")*(Expenses_Log!G6:G5000)) | Q20: =IFERROR(O20-P20,"—") | R20: 80000 | S20: =SUMPRODUCT((YEAR(Expenses_Log!A6:A5000)=Dashboard!$B$1)*(MONTH(Expenses_Log!A6:A5000)=6)*(Expenses_Log!C6:C5000="Maintenance")*(Expenses_Log!G6:G5000)) | T20: =IFERROR(R20-S20,"—") | U20: 80000 | V20: =SUMPRODUCT((YEAR(Expenses_Log!A6:A5000)=Dashboard!$B$1)*(MONTH(Expenses_Log!A6:A5000)=7)*(Expenses_Log!C6:C5000="Maintenance")*(Expenses_Log!G6:G5000)) | W20: =IFERROR(U20-V20,"—") | X20: 80000 | Y20: =SUMPRODUCT((YEAR(Expenses_Log!A6:A5000)=Dashboard!$B$1)*(MONTH(Expenses_Log!A6:A5000)=8)*(Expenses_Log!C6:C5000="Maintenance")*(Expenses_Log!G6:G5000)) | Z20: =IFERROR(X20-Y20,"—") | AA20: 100000 | AB20: =SUMPRODUCT((YEAR(Expenses_Log!A6:A5000)=Dashboard!$B$1)*(MONTH(Expenses_Log!A6:A5000)=9)*(Expenses_Log!C6:C5000="Maintenance")*(Expenses_Log!G6:G5000)) | AC20: =IFERROR(AA20-AB20,"—") | AD20: 100000 | AE20: =SUMPRODUCT((YEAR(Expenses_Log!A6:A5000)=Dashboard!$B$1)*(MONTH(Expenses_Log!A6:A5000)=10)*(Expenses_Log!C6:C5000="Maintenance")*(Expenses_Log!G6:G5000)) | AF20: =IFERROR(AD20-AE20,"—") | AG20: 90000 | AH20: =SUMPRODUCT((YEAR(Expenses_Log!A6:A5000)=Dashboard!$B$1)*(MONTH(Expenses_Log!A6:A5000)=11)*(Expenses_Log!C6:C5000="Maintenance")*(Expenses_Log!G6:G5000)) | AI20: =IFERROR(AG20-AH20,"—") | AJ20: 90000 | AK20: =SUMPRODUCT((YEAR(Expenses_Log!A6:A5000)=Dashboard!$B$1)*(MONTH(Expenses_Log!A6:A5000)=12)*(Expenses_Log!C6:C5000="Maintenance")*(Expenses_Log!G6:G5000)) | AL20: =IFERROR(AJ20-AK20,"—") | AM20: =C20+F20+I20+L20+O20+R20+U20+X20+AA20+AD20+AG20+AJ20 | AN20: =D20+G20+J20+M20+P20+S20+V20+Y20+AB20+AE20+AH20+AK20 | AO20: =IFERROR(AM20-AN20,"—")
B21: Utilities | C21: 130000 | D21: =SUMPRODUCT((YEAR(Expenses_Log!A6:A5000)=Dashboard!$B$1)*(MONTH(Expenses_Log!A6:A5000)=1)*(Expenses_Log!C6:C5000="Utilities")*(Expenses_Log!G6:G5000)) | E21: =IFERROR(C21-D21,"—") | F21: 120000 | G21: =SUMPRODUCT((YEAR(Expenses_Log!A6:A5000)=Dashboard!$B$1)*(MONTH(Expenses_Log!A6:A5000)=2)*(Expenses_Log!C6:C5000="Utilities")*(Expenses_Log!G6:G5000)) | H21: =IFERROR(F21-G21,"—") | I21: 110000 | J21: =SUMPRODUCT((YEAR(Expenses_Log!A6:A5000)=Dashboard!$B$1)*(MONTH(Expenses_Log!A6:A5000)=3)*(Expenses_Log!C6:C5000="Utilities")*(Expenses_Log!G6:G5000)) | K21: =IFERROR(I21-J21,"—") | L21: 110000 | M21: =SUMPRODUCT((YEAR(Expenses_Log!A6:A5000)=Dashboard!$B$1)*(MONTH(Expenses_Log!A6:A5000)=4)*(Expenses_Log!C6:C5000="Utilities")*(Expenses_Log!G6:G5000)) | N21: =IFERROR(L21-M21,"—") | O21: 110000 | P21: =SUMPRODUCT((YEAR(Expenses_Log!A6:A5000)=Dashboard!$B$1)*(MONTH(Expenses_Log!A6:A5000)=5)*(Expenses_Log!C6:C5000="Utilities")*(Expenses_Log!G6:G5000)) | Q21: =IFERROR(O21-P21,"—") | R21: 110000 | S21: =SUMPRODUCT((YEAR(Expenses_Log!A6:A5000)=Dashboard!$B$1)*(MONTH(Expenses_Log!A6:A5000)=6)*(Expenses_Log!C6:C5000="Utilities")*(Expenses_Log!G6:G5000)) | T21: =IFERROR(R21-S21,"—") | U21: 110000 | V21: =SUMPRODUCT((YEAR(Expenses_Log!A6:A5000)=Dashboard!$B$1)*(MONTH(Expenses_Log!A6:A5000)=7)*(Expenses_Log!C6:C5000="Utilities")*(Expenses_Log!G6:G5000)) | W21: =IFERROR(U21-V21,"—") | X21: 110000 | Y21: =SUMPRODUCT((YEAR(Expenses_Log!A6:A5000)=Dashboard!$B$1)*(MONTH(Expenses_Log!A6:A5000)=8)*(Expenses_Log!C6:C5000="Utilities")*(Expenses_Log!G6:G5000)) | Z21: =IFERROR(X21-Y21,"—") | AA21: 130000 | AB21: =SUMPRODUCT((YEAR(Expenses_Log!A6:A5000)=Dashboard!$B$1)*(MONTH(Expenses_Log!A6:A5000)=9)*(Expenses_Log!C6:C5000="Utilities")*(Expenses_Log!G6:G5000)) | AC21: =IFERROR(AA21-AB21,"—") | AD21: 130000 | AE21: =SUMPRODUCT((YEAR(Expenses_Log!A6:A5000)=Dashboard!$B$1)*(MONTH(Expenses_Log!A6:A5000)=10)*(Expenses_Log!C6:C5000="Utilities")*(Expenses_Log!G6:G5000)) | AF21: =IFERROR(AD21-AE21,"—") | AG21: 120000 | AH21: =SUMPRODUCT((YEAR(Expenses_Log!A6:A5000)=Dashboard!$B$1)*(MONTH(Expenses_Log!A6:A5000)=11)*(Expenses_Log!C6:C5000="Utilities")*(Expenses_Log!G6:G5000)) | AI21: =IFERROR(AG21-AH21,"—") | AJ21: 120000 | AK21: =SUMPRODUCT((YEAR(Expenses_Log!A6:A5000)=Dashboard!$B$1)*(MONTH(Expenses_Log!A6:A5000)=12)*(Expenses_Log!C6:C5000="Utilities")*(Expenses_Log!G6:G5000)) | AL21: =IFERROR(AJ21-AK21,"—") | AM21: =C21+F21+I21+L21+O21+R21+U21+X21+AA21+AD21+AG21+AJ21 | AN21: =D21+G21+J21+M21+P21+S21+V21+Y21+AB21+AE21+AH21+AK21 | AO21: =IFERROR(AM21-AN21,"—")
B22: Inventory | C22: 80000 | D22: =SUMPRODUCT((YEAR(Expenses_Log!A6:A5000)=Dashboard!$B$1)*(MONTH(Expenses_Log!A6:A5000)=1)*(Expenses_Log!C6:C5000="Inventory")*(Expenses_Log!G6:G5000)) | E22: =IFERROR(C22-D22,"—") | F22: 60000 | G22: =SUMPRODUCT((YEAR(Expenses_Log!A6:A5000)=Dashboard!$B$1)*(MONTH(Expenses_Log!A6:A5000)=2)*(Expenses_Log!C6:C5000="Inventory")*(Expenses_Log!G6:G5000)) | H22: =IFERROR(F22-G22,"—") | I22: 60000 | J22: =SUMPRODUCT((YEAR(Expenses_Log!A6:A5000)=Dashboard!$B$1)*(MONTH(Expenses_Log!A6:A5000)=3)*(Expenses_Log!C6:C5000="Inventory")*(Expenses_Log!G6:G5000)) | K22: =IFERROR(I22-J22,"—") | L22: 50000 | M22: =SUMPRODUCT((YEAR(Expenses_Log!A6:A5000)=Dashboard!$B$1)*(MONTH(Expenses_Log!A6:A5000)=4)*(Expenses_Log!C6:C5000="Inventory")*(Expenses_Log!G6:G5000)) | N22: =IFERROR(L22-M22,"—") | O22: 50000 | P22: =SUMPRODUCT((YEAR(Expenses_Log!A6:A5000)=Dashboard!$B$1)*(MONTH(Expenses_Log!A6:A5000)=5)*(Expenses_Log!C6:C5000="Inventory")*(Expenses_Log!G6:G5000)) | Q22: =IFERROR(O22-P22,"—") | R22: 50000 | S22: =SUMPRODUCT((YEAR(Expenses_Log!A6:A5000)=Dashboard!$B$1)*(MONTH(Expenses_Log!A6:A5000)=6)*(Expenses_Log!C6:C5000="Inventory")*(Expenses_Log!G6:G5000)) | T22: =IFERROR(R22-S22,"—") | U22: 50000 | V22: =SUMPRODUCT((YEAR(Expenses_Log!A6:A5000)=Dashboard!$B$1)*(MONTH(Expenses_Log!A6:A5000)=7)*(Expenses_Log!C6:C5000="Inventory")*(Expenses_Log!G6:G5000)) | W22: =IFERROR(U22-V22,"—") | X22: 50000 | Y22: =SUMPRODUCT((YEAR(Expenses_Log!A6:A5000)=Dashboard!$B$1)*(MONTH(Expenses_Log!A6:A5000)=8)*(Expenses_Log!C6:C5000="Inventory")*(Expenses_Log!G6:G5000)) | Z22: =IFERROR(X22-Y22,"—") | AA22: 80000 | AB22: =SUMPRODUCT((YEAR(Expenses_Log!A6:A5000)=Dashboard!$B$1)*(MONTH(Expenses_Log!A6:A5000)=9)*(Expenses_Log!C6:C5000="Inventory")*(Expenses_Log!G6:G5000)) | AC22: =IFERROR(AA22-AB22,"—") | AD22: 80000 | AE22: =SUMPRODUCT((YEAR(Expenses_Log!A6:A5000)=Dashboard!$B$1)*(MONTH(Expenses_Log!A6:A5000)=10)*(Expenses_Log!C6:C5000="Inventory")*(Expenses_Log!G6:G5000)) | AF22: =IFERROR(AD22-AE22,"—") | AG22: 60000 | AH22: =SUMPRODUCT((YEAR(Expenses_Log!A6:A5000)=Dashboard!$B$1)*(MONTH(Expenses_Log!A6:A5000)=11)*(Expenses_Log!C6:C5000="Inventory")*(Expenses_Log!G6:G5000)) | AI22: =IFERROR(AG22-AH22,"—") | AJ22: 60000 | AK22: =SUMPRODUCT((YEAR(Expenses_Log!A6:A5000)=Dashboard!$B$1)*(MONTH(Expenses_Log!A6:A5000)=12)*(Expenses_Log!C6:C5000="Inventory")*(Expenses_Log!G6:G5000)) | AL22: =IFERROR(AJ22-AK22,"—") | AM22: =C22+F22+I22+L22+O22+R22+U22+X22+AA22+AD22+AG22+AJ22 | AN22: =D22+G22+J22+M22+P22+S22+V22+Y22+AB22+AE22+AH22+AK22 | AO22: =IFERROR(AM22-AN22,"—")
B23: Administrative | C23: 40000 | D23: =SUMPRODUCT((YEAR(Expenses_Log!A6:A5000)=Dashboard!$B$1)*(MONTH(Expenses_Log!A6:A5000)=1)*(Expenses_Log!C6:C5000="Administrative")*(Expenses_Log!G6:G5000)) | E23: =IFERROR(C23-D23,"—") | F23: 30000 | G23: =SUMPRODUCT((YEAR(Expenses_Log!A6:A5000)=Dashboard!$B$1)*(MONTH(Expenses_Log!A6:A5000)=2)*(Expenses_Log!C6:C5000="Administrative")*(Expenses_Log!G6:G5000)) | H23: =IFERROR(F23-G23,"—") | I23: 30000 | J23: =SUMPRODUCT((YEAR(Expenses_Log!A6:A5000)=Dashboard!$B$1)*(MONTH(Expenses_Log!A6:A5000)=3)*(Expenses_Log!C6:C5000="Administrative")*(Expenses_Log!G6:G5000)) | K23: =IFERROR(I23-J23,"—") | L23: 25000 | M23: =SUMPRODUCT((YEAR(Expenses_Log!A6:A5000)=Dashboard!$B$1)*(MONTH(Expenses_Log!A6:A5000)=4)*(Expenses_Log!C6:C5000="Administrative")*(Expenses_Log!G6:G5000)) | N23: =IFERROR(L23-M23,"—") | O23: 25000 | P23: =SUMPRODUCT((YEAR(Expenses_Log!A6:A5000)=Dashboard!$B$1)*(MONTH(Expenses_Log!A6:A5000)=5)*(Expenses_Log!C6:C5000="Administrative")*(Expenses_Log!G6:G5000)) | Q23: =IFERROR(O23-P23,"—") | R23: 25000 | S23: =SUMPRODUCT((YEAR(Expenses_Log!A6:A5000)=Dashboard!$B$1)*(MONTH(Expenses_Log!A6:A5000)=6)*(Expenses_Log!C6:C5000="Administrative")*(Expenses_Log!G6:G5000)) | T23: =IFERROR(R23-S23,"—") | U23: 25000 | V23: =SUMPRODUCT((YEAR(Expenses_Log!A6:A5000)=Dashboard!$B$1)*(MONTH(Expenses_Log!A6:A5000)=7)*(Expenses_Log!C6:C5000="Administrative")*(Expenses_Log!G6:G5000)) | W23: =IFERROR(U23-V23,"—") | X23: 25000 | Y23: =SUMPRODUCT((YEAR(Expenses_Log!A6:A5000)=Dashboard!$B$1)*(MONTH(Expenses_Log!A6:A5000)=8)*(Expenses_Log!C6:C5000="Administrative")*(Expenses_Log!G6:G5000)) | Z23: =IFERROR(X23-Y23,"—") | AA23: 40000 | AB23: =SUMPRODUCT((YEAR(Expenses_Log!A6:A5000)=Dashboard!$B$1)*(MONTH(Expenses_Log!A6:A5000)=9)*(Expenses_Log!C6:C5000="Administrative")*(Expenses_Log!G6:G5000)) | AC23: =IFERROR(AA23-AB23,"—") | AD23: 40000 | AE23: =SUMPRODUCT((YEAR(Expenses_Log!A6:A5000)=Dashboard!$B$1)*(MONTH(Expenses_Log!A6:A5000)=10)*(Expenses_Log!C6:C5000="Administrative")*(Expenses_Log!G6:G5000)) | AF23: =IFERROR(AD23-AE23,"—") | AG23: 30000 | AH23: =SUMPRODUCT((YEAR(Expenses_Log!A6:A5000)=Dashboard!$B$1)*(MONTH(Expenses_Log!A6:A5000)=11)*(Expenses_Log!C6:C5000="Administrative")*(Expenses_Log!G6:G5000)) | AI23: =IFERROR(AG23-AH23,"—") | AJ23: 30000 | AK23: =SUMPRODUCT((YEAR(Expenses_Log!A6:A5000)=Dashboard!$B$1)*(MONTH(Expenses_Log!A6:A5000)=12)*(Expenses_Log!C6:C5000="Administrative")*(Expenses_Log!G6:G5000)) | AL23: =IFERROR(AJ23-AK23,"—") | AM23: =C23+F23+I23+L23+O23+R23+U23+X23+AA23+AD23+AG23+AJ23 | AN23: =D23+G23+J23+M23+P23+S23+V23+Y23+AB23+AE23+AH23+AK23 | AO23: =IFERROR(AM23-AN23,"—")
B24: Loans & Advances | C24: 200000 | D24: =SUMPRODUCT((YEAR(Expenses_Log!A6:A5000)=Dashboard!$B$1)*(MONTH(Expenses_Log!A6:A5000)=1)*(Expenses_Log!C6:C5000="Loans & Advances")*(Expenses_Log!G6:G5000)) | E24: =IFERROR(C24-D24,"—") | F24: 0 | G24: =SUMPRODUCT((YEAR(Expenses_Log!A6:A5000)=Dashboard!$B$1)*(MONTH(Expenses_Log!A6:A5000)=2)*(Expenses_Log!C6:C5000="Loans & Advances")*(Expenses_Log!G6:G5000)) | H24: =IFERROR(F24-G24,"—") | I24: 200000 | J24: =SUMPRODUCT((YEAR(Expenses_Log!A6:A5000)=Dashboard!$B$1)*(MONTH(Expenses_Log!A6:A5000)=3)*(Expenses_Log!C6:C5000="Loans & Advances")*(Expenses_Log!G6:G5000)) | K24: =IFERROR(I24-J24,"—") | L24: 0 | M24: =SUMPRODUCT((YEAR(Expenses_Log!A6:A5000)=Dashboard!$B$1)*(MONTH(Expenses_Log!A6:A5000)=4)*(Expenses_Log!C6:C5000="Loans & Advances")*(Expenses_Log!G6:G5000)) | N24: =IFERROR(L24-M24,"—") | O24: 200000 | P24: =SUMPRODUCT((YEAR(Expenses_Log!A6:A5000)=Dashboard!$B$1)*(MONTH(Expenses_Log!A6:A5000)=5)*(Expenses_Log!C6:C5000="Loans & Advances")*(Expenses_Log!G6:G5000)) | Q24: =IFERROR(O24-P24,"—") | R24: 0 | S24: =SUMPRODUCT((YEAR(Expenses_Log!A6:A5000)=Dashboard!$B$1)*(MONTH(Expenses_Log!A6:A5000)=6)*(Expenses_Log!C6:C5000="Loans & Advances")*(Expenses_Log!G6:G5000)) | T24: =IFERROR(R24-S24,"—") | U24: 200000 | V24: =SUMPRODUCT((YEAR(Expenses_Log!A6:A5000)=Dashboard!$B$1)*(MONTH(Expenses_Log!A6:A5000)=7)*(Expenses_Log!C6:C5000="Loans & Advances")*(Expenses_Log!G6:G5000)) | W24: =IFERROR(U24-V24,"—") | X24: 0 | Y24: =SUMPRODUCT((YEAR(Expenses_Log!A6:A5000)=Dashboard!$B$1)*(MONTH(Expenses_Log!A6:A5000)=8)*(Expenses_Log!C6:C5000="Loans & Advances")*(Expenses_Log!G6:G5000)) | Z24: =IFERROR(X24-Y24,"—") | AA24: 200000 | AB24: =SUMPRODUCT((YEAR(Expenses_Log!A6:A5000)=Dashboard!$B$1)*(MONTH(Expenses_Log!A6:A5000)=9)*(Expenses_Log!C6:C5000="Loans & Advances")*(Expenses_Log!G6:G5000)) | AC24: =IFERROR(AA24-AB24,"—") | AD24: 0 | AE24: =SUMPRODUCT((YEAR(Expenses_Log!A6:A5000)=Dashboard!$B$1)*(MONTH(Expenses_Log!A6:A5000)=10)*(Expenses_Log!C6:C5000="Loans & Advances")*(Expenses_Log!G6:G5000)) | AF24: =IFERROR(AD24-AE24,"—") | AG24: 200000 | AH24: =SUMPRODUCT((YEAR(Expenses_Log!A6:A5000)=Dashboard!$B$1)*(MONTH(Expenses_Log!A6:A5000)=11)*(Expenses_Log!C6:C5000="Loans & Advances")*(Expenses_Log!G6:G5000)) | AI24: =IFERROR(AG24-AH24,"—") | AJ24: 0 | AK24: =SUMPRODUCT((YEAR(Expenses_Log!A6:A5000)=Dashboard!$B$1)*(MONTH(Expenses_Log!A6:A5000)=12)*(Expenses_Log!C6:C5000="Loans & Advances")*(Expenses_Log!G6:G5000)) | AL24: =IFERROR(AJ24-AK24,"—") | AM24: =C24+F24+I24+L24+O24+R24+U24+X24+AA24+AD24+AG24+AJ24 | AN24: =D24+G24+J24+M24+P24+S24+V24+Y24+AB24+AE24+AH24+AK24 | AO24: =IFERROR(AM24-AN24,"—")
B25: Transportation | C25: 12000 | D25: =SUMPRODUCT((YEAR(Expenses_Log!A6:A5000)=Dashboard!$B$1)*(MONTH(Expenses_Log!A6:A5000)=1)*(Expenses_Log!C6:C5000="Transportation")*(Expenses_Log!G6:G5000)) | E25: =IFERROR(C25-D25,"—") | F25: 10000 | G25: =SUMPRODUCT((YEAR(Expenses_Log!A6:A5000)=Dashboard!$B$1)*(MONTH(Expenses_Log!A6:A5000)=2)*(Expenses_Log!C6:C5000="Transportation")*(Expenses_Log!G6:G5000)) | H25: =IFERROR(F25-G25,"—") | I25: 10000 | J25: =SUMPRODUCT((YEAR(Expenses_Log!A6:A5000)=Dashboard!$B$1)*(MONTH(Expenses_Log!A6:A5000)=3)*(Expenses_Log!C6:C5000="Transportation")*(Expenses_Log!G6:G5000)) | K25: =IFERROR(I25-J25,"—") | L25: 10000 | M25: =SUMPRODUCT((YEAR(Expenses_Log!A6:A5000)=Dashboard!$B$1)*(MONTH(Expenses_Log!A6:A5000)=4)*(Expenses_Log!C6:C5000="Transportation")*(Expenses_Log!G6:G5000)) | N25: =IFERROR(L25-M25,"—") | O25: 10000 | P25: =SUMPRODUCT((YEAR(Expenses_Log!A6:A5000)=Dashboard!$B$1)*(MONTH(Expenses_Log!A6:A5000)=5)*(Expenses_Log!C6:C5000="Transportation")*(Expenses_Log!G6:G5000)) | Q25: =IFERROR(O25-P25,"—") | R25: 10000 | S25: =SUMPRODUCT((YEAR(Expenses_Log!A6:A5000)=Dashboard!$B$1)*(MONTH(Expenses_Log!A6:A5000)=6)*(Expenses_Log!C6:C5000="Transportation")*(Expenses_Log!G6:G5000)) | T25: =IFERROR(R25-S25,"—") | U25: 10000 | V25: =SUMPRODUCT((YEAR(Expenses_Log!A6:A5000)=Dashboard!$B$1)*(MONTH(Expenses_Log!A6:A5000)=7)*(Expenses_Log!C6:C5000="Transportation")*(Expenses_Log!G6:G5000)) | W25: =IFERROR(U25-V25,"—") | X25: 10000 | Y25: =SUMPRODUCT((YEAR(Expenses_Log!A6:A5000)=Dashboard!$B$1)*(MONTH(Expenses_Log!A6:A5000)=8)*(Expenses_Log!C6:C5000="Transportation")*(Expenses_Log!G6:G5000)) | Z25: =IFERROR(X25-Y25,"—") | AA25: 12000 | AB25: =SUMPRODUCT((YEAR(Expenses_Log!A6:A5000)=Dashboard!$B$1)*(MONTH(Expenses_Log!A6:A5000)=9)*(Expenses_Log!C6:C5000="Transportation")*(Expenses_Log!G6:G5000)) | AC25: =IFERROR(AA25-AB25,"—") | AD25: 12000 | AE25: =SUMPRODUCT((YEAR(Expenses_Log!A6:A5000)=Dashboard!$B$1)*(MONTH(Expenses_Log!A6:A5000)=10)*(Expenses_Log!C6:C5000="Transportation")*(Expenses_Log!G6:G5000)) | AF25: =IFERROR(AD25-AE25,"—") | AG25: 10000 | AH25: =SUMPRODUCT((YEAR(Expenses_Log!A6:A5000)=Dashboard!$B$1)*(MONTH(Expenses_Log!A6:A5000)=11)*(Expenses_Log!C6:C5000="Transportation")*(Expenses_Log!G6:G5000)) | AI25: =IFERROR(AG25-AH25,"—") | AJ25: 10000 | AK25: =SUMPRODUCT((YEAR(Expenses_Log!A6:A5000)=Dashboard!$B$1)*(MONTH(Expenses_Log!A6:A5000)=12)*(Expenses_Log!C6:C5000="Transportation")*(Expenses_Log!G6:G5000)) | AL25: =IFERROR(AJ25-AK25,"—") | AM25: =C25+F25+I25+L25+O25+R25+U25+X25+AA25+AD25+AG25+AJ25 | AN25: =D25+G25+J25+M25+P25+S25+V25+Y25+AB25+AE25+AH25+AK25 | AO25: =IFERROR(AM25-AN25,"—")
B26: IT & Communications | C26: 15000 | D26: =SUMPRODUCT((YEAR(Expenses_Log!A6:A5000)=Dashboard!$B$1)*(MONTH(Expenses_Log!A6:A5000)=1)*(Expenses_Log!C6:C5000="IT & Communications")*(Expenses_Log!G6:G5000)) | E26: =IFERROR(C26-D26,"—") | F26: 12000 | G26: =SUMPRODUCT((YEAR(Expenses_Log!A6:A5000)=Dashboard!$B$1)*(MONTH(Expenses_Log!A6:A5000)=2)*(Expenses_Log!C6:C5000="IT & Communications")*(Expenses_Log!G6:G5000)) | H26: =IFERROR(F26-G26,"—") | I26: 12000 | J26: =SUMPRODUCT((YEAR(Expenses_Log!A6:A5000)=Dashboard!$B$1)*(MONTH(Expenses_Log!A6:A5000)=3)*(Expenses_Log!C6:C5000="IT & Communications")*(Expenses_Log!G6:G5000)) | K26: =IFERROR(I26-J26,"—") | L26: 10000 | M26: =SUMPRODUCT((YEAR(Expenses_Log!A6:A5000)=Dashboard!$B$1)*(MONTH(Expenses_Log!A6:A5000)=4)*(Expenses_Log!C6:C5000="IT & Communications")*(Expenses_Log!G6:G5000)) | N26: =IFERROR(L26-M26,"—") | O26: 10000 | P26: =SUMPRODUCT((YEAR(Expenses_Log!A6:A5000)=Dashboard!$B$1)*(MONTH(Expenses_Log!A6:A5000)=5)*(Expenses_Log!C6:C5000="IT & Communications")*(Expenses_Log!G6:G5000)) | Q26: =IFERROR(O26-P26,"—") | R26: 10000 | S26: =SUMPRODUCT((YEAR(Expenses_Log!A6:A5000)=Dashboard!$B$1)*(MONTH(Expenses_Log!A6:A5000)=6)*(Expenses_Log!C6:C5000="IT & Communications")*(Expenses_Log!G6:G5000)) | T26: =IFERROR(R26-S26,"—") | U26: 10000 | V26: =SUMPRODUCT((YEAR(Expenses_Log!A6:A5000)=Dashboard!$B$1)*(MONTH(Expenses_Log!A6:A5000)=7)*(Expenses_Log!C6:C5000="IT & Communications")*(Expenses_Log!G6:G5000)) | W26: =IFERROR(U26-V26,"—") | X26: 10000 | Y26: =SUMPRODUCT((YEAR(Expenses_Log!A6:A5000)=Dashboard!$B$1)*(MONTH(Expenses_Log!A6:A5000)=8)*(Expenses_Log!C6:C5000="IT & Communications")*(Expenses_Log!G6:G5000)) | Z26: =IFERROR(X26-Y26,"—") | AA26: 15000 | AB26: =SUMPRODUCT((YEAR(Expenses_Log!A6:A5000)=Dashboard!$B$1)*(MONTH(Expenses_Log!A6:A5000)=9)*(Expenses_Log!C6:C5000="IT & Communications")*(Expenses_Log!G6:G5000)) | AC26: =IFERROR(AA26-AB26,"—") | AD26: 15000 | AE26: =SUMPRODUCT((YEAR(Expenses_Log!A6:A5000)=Dashboard!$B$1)*(MONTH(Expenses_Log!A6:A5000)=10)*(Expenses_Log!C6:C5000="IT & Communications")*(Expenses_Log!G6:G5000)) | AF26: =IFERROR(AD26-AE26,"—") | AG26: 12000 | AH26: =SUMPRODUCT((YEAR(Expenses_Log!A6:A5000)=Dashboard!$B$1)*(MONTH(Expenses_Log!A6:A5000)=11)*(Expenses_Log!C6:C5000="IT & Communications")*(Expenses_Log!G6:G5000)) | AI26: =IFERROR(AG26-AH26,"—") | AJ26: 12000 | AK26: =SUMPRODUCT((YEAR(Expenses_Log!A6:A5000)=Dashboard!$B$1)*(MONTH(Expenses_Log!A6:A5000)=12)*(Expenses_Log!C6:C5000="IT & Communications")*(Expenses_Log!G6:G5000)) | AL26: =IFERROR(AJ26-AK26,"—") | AM26: =C26+F26+I26+L26+O26+R26+U26+X26+AA26+AD26+AG26+AJ26 | AN26: =D26+G26+J26+M26+P26+S26+V26+Y26+AB26+AE26+AH26+AK26 | AO26: =IFERROR(AM26-AN26,"—")
B27: Other | C27: 10000 | D27: =SUMPRODUCT((YEAR(Expenses_Log!A6:A5000)=Dashboard!$B$1)*(MONTH(Expenses_Log!A6:A5000)=1)*(Expenses_Log!C6:C5000="Other")*(Expenses_Log!G6:G5000)) | E27: =IFERROR(C27-D27,"—") | F27: 8000 | G27: =SUMPRODUCT((YEAR(Expenses_Log!A6:A5000)=Dashboard!$B$1)*(MONTH(Expenses_Log!A6:A5000)=2)*(Expenses_Log!C6:C5000="Other")*(Expenses_Log!G6:G5000)) | H27: =IFERROR(F27-G27,"—") | I27: 8000 | J27: =SUMPRODUCT((YEAR(Expenses_Log!A6:A5000)=Dashboard!$B$1)*(MONTH(Expenses_Log!A6:A5000)=3)*(Expenses_Log!C6:C5000="Other")*(Expenses_Log!G6:G5000)) | K27: =IFERROR(I27-J27,"—") | L27: 8000 | M27: =SUMPRODUCT((YEAR(Expenses_Log!A6:A5000)=Dashboard!$B$1)*(MONTH(Expenses_Log!A6:A5000)=4)*(Expenses_Log!C6:C5000="Other")*(Expenses_Log!G6:G5000)) | N27: =IFERROR(L27-M27,"—") | O27: 8000 | P27: =SUMPRODUCT((YEAR(Expenses_Log!A6:A5000)=Dashboard!$B$1)*(MONTH(Expenses_Log!A6:A5000)=5)*(Expenses_Log!C6:C5000="Other")*(Expenses_Log!G6:G5000)) | Q27: =IFERROR(O27-P27,"—") | R27: 8000 | S27: =SUMPRODUCT((YEAR(Expenses_Log!A6:A5000)=Dashboard!$B$1)*(MONTH(Expenses_Log!A6:A5000)=6)*(Expenses_Log!C6:C5000="Other")*(Expenses_Log!G6:G5000)) | T27: =IFERROR(R27-S27,"—") | U27: 8000 | V27: =SUMPRODUCT((YEAR(Expenses_Log!A6:A5000)=Dashboard!$B$1)*(MONTH(Expenses_Log!A6:A5000)=7)*(Expenses_Log!C6:C5000="Other")*(Expenses_Log!G6:G5000)) | W27: =IFERROR(U27-V27,"—") | X27: 8000 | Y27: =SUMPRODUCT((YEAR(Expenses_Log!A6:A5000)=Dashboard!$B$1)*(MONTH(Expenses_Log!A6:A5000)=8)*(Expenses_Log!C6:C5000="Other")*(Expenses_Log!G6:G5000)) | Z27: =IFERROR(X27-Y27,"—") | AA27: 10000 | AB27: =SUMPRODUCT((YEAR(Expenses_Log!A6:A5000)=Dashboard!$B$1)*(MONTH(Expenses_Log!A6:A5000)=9)*(Expenses_Log!C6:C5000="Other")*(Expenses_Log!G6:G5000)) | AC27: =IFERROR(AA27-AB27,"—") | AD27: 10000 | AE27: =SUMPRODUCT((YEAR(Expenses_Log!A6:A5000)=Dashboard!$B$1)*(MONTH(Expenses_Log!A6:A5000)=10)*(Expenses_Log!C6:C5000="Other")*(Expenses_Log!G6:G5000)) | AF27: =IFERROR(AD27-AE27,"—") | AG27: 8000 | AH27: =SUMPRODUCT((YEAR(Expenses_Log!A6:A5000)=Dashboard!$B$1)*(MONTH(Expenses_Log!A6:A5000)=11)*(Expenses_Log!C6:C5000="Other")*(Expenses_Log!G6:G5000)) | AI27: =IFERROR(AG27-AH27,"—") | AJ27: 8000 | AK27: =SUMPRODUCT((YEAR(Expenses_Log!A6:A5000)=Dashboard!$B$1)*(MONTH(Expenses_Log!A6:A5000)=12)*(Expenses_Log!C6:C5000="Other")*(Expenses_Log!G6:G5000)) | AL27: =IFERROR(AJ27-AK27,"—") | AM27: =C27+F27+I27+L27+O27+R27+U27+X27+AA27+AD27+AG27+AJ27 | AN27: =D27+G27+J27+M27+P27+S27+V27+Y27+AB27+AE27+AH27+AK27 | AO27: =IFERROR(AM27-AN27,"—")
B28: TOTAL EXPENSES | C28: =SUM(C18:C27) | D28: =SUM(D18:D27) | E28: =IFERROR(SUM(E18:E27),"—") | F28: =SUM(F18:F27) | G28: =SUM(G18:G27) | H28: =IFERROR(SUM(H18:H27),"—") | I28: =SUM(I18:I27) | J28: =SUM(J18:J27) | K28: =IFERROR(SUM(K18:K27),"—") | L28: =SUM(L18:L27) | M28: =SUM(M18:M27) | N28: =IFERROR(SUM(N18:N27),"—") | O28: =SUM(O18:O27) | P28: =SUM(P18:P27) | Q28: =IFERROR(SUM(Q18:Q27),"—") | R28: =SUM(R18:R27) | S28: =SUM(S18:S27) | T28: =IFERROR(SUM(T18:T27),"—") | U28: =SUM(U18:U27) | V28: =SUM(V18:V27) | W28: =IFERROR(SUM(W18:W27),"—") | X28: =SUM(X18:X27) | Y28: =SUM(Y18:Y27) | Z28: =IFERROR(SUM(Z18:Z27),"—") | AA28: =SUM(AA18:AA27) | AB28: =SUM(AB18:AB27) | AC28: =IFERROR(SUM(AC18:AC27),"—") | AD28: =SUM(AD18:AD27) | AE28: =SUM(AE18:AE27) | AF28: =IFERROR(SUM(AF18:AF27),"—") | AG28: =SUM(AG18:AG27) | AH28: =SUM(AH18:AH27) | AI28: =IFERROR(SUM(AI18:AI27),"—") | AJ28: =SUM(AJ18:AJ27) | AK28: =SUM(AK18:AK27) | AL28: =IFERROR(SUM(AL18:AL27),"—") | AM28: =SUM(AM18:AM27) | AN28: =SUM(AN18:AN27) | AO28: =IFERROR(SUM(AO18:AO27),"—")
B29: NET PROFIT | C29: =C15-C28 | D29: =D15-D28 | E29: =IFERROR(E15-E28,"—") | F29: =F15-F28 | G29: =G15-G28 | H29: =IFERROR(H15-H28,"—") | I29: =I15-I28 | J29: =J15-J28 | K29: =IFERROR(K15-K28,"—") | L29: =L15-L28 | M29: =M15-M28 | N29: =IFERROR(N15-N28,"—") | O29: =O15-O28 | P29: =P15-P28 | Q29: =IFERROR(Q15-Q28,"—") | R29: =R15-R28 | S29: =S15-S28 | T29: =IFERROR(T15-T28,"—") | U29: =U15-U28 | V29: =V15-V28 | W29: =IFERROR(W15-W28,"—") | X29: =X15-X28 | Y29: =Y15-Y28 | Z29: =IFERROR(Z15-Z28,"—") | AA29: =AA15-AA28 | AB29: =AB15-AB28 | AC29: =IFERROR(AC15-AC28,"—") | AD29: =AD15-AD28 | AE29: =AE15-AE28 | AF29: =IFERROR(AF15-AF28,"—") | AG29: =AG15-AG28 | AH29: =AH15-AH28 | AI29: =IFERROR(AI15-AI28,"—") | AJ29: =AJ15-AJ28 | AK29: =AK15-AK28 | AL29: =IFERROR(AL15-AL28,"—") | AM29: =AM15-AM28 | AN29: =AN15-AN28 | AO29: =IFERROR(AO15-AO28,"—")

Sheet Dashboard
A1: FY Year: | B1: 2024
E2: TALENTS APARTMENT
E3: ="Executive Dashboard | FY "&Dashboard!$B$1
B5: FILTER: | C5: All
B7: TOTAL REVENUE | E7: TOTAL EXPENSES | H7: NET PROFIT | K7: STAFF SALARIES | N7: MARGIN
B8: =IF(C5="All",SUMPRODUCT((YEAR(Revenue_Log!A6:A5000)=Dashboard!$B$1)*(Revenue_Log!H6:H5000)),SUMPRODUCT((YEAR(Revenue_Log!A6:A5000)=Dashboard!$B$1)*(Revenue_Log!B6:B5000=C5)*(Revenue_Log!H6:H5000))) | E8: =IFERROR(IF(C5="All",SUMPRODUCT((YEAR(Expenses_Log!A6:A5000)=Dashboard!$B$1)*(Expenses_Log!G6:G5000))+Staff_Salaries!E4,SUMPRODUCT((YEAR(Expenses_Log!A6:A5000)=Dashboard!$B$1)*(Expenses_Log!B6:B5000=C5)*(Expenses_Log!G6:G5000))+Staff_Salaries!E4),"—") | H8: =B8-E8 | K8: =Staff_Salaries!E4 | N8: =IFERROR(H8/B8,0)
B10: REVENUE & EXPENDITURE
C11: Jan | D11: Feb | E11: Mar | F11: Apr | G11: May | H11: Jun | I11: Jul | J11: Aug | K11: Sep | L11: Oct | M11: Nov | N11: Dec | O11: YTD
B12: REVENUE:
B13: Room Revenue | C13: =IF($C$5="All",SUMPRODUCT((MONTH(Revenue_Log!A6:A5000)=1)*(Revenue_Log!D6:D5000="Room Revenue")*(Revenue_Log!H6:H5000)),SUMPRODUCT((MONTH(Revenue_Log!A6:A5000)=1)*(Revenue_Log!D6:D5000="Room Revenue")*(Revenue_Log!B6:B5000=$C$5)*(Revenue_Log!H6:H5000))) | D13: =IF($C$5="All",SUMPRODUCT((MONTH(Revenue_Log!A6:A5000)=2)*(Revenue_Log!D6:D5000="Room Revenue")*(Revenue_Log!H6:H5000)),SUMPRODUCT((MONTH(Revenue_Log!A6:A5000)=2)*(Revenue_Log!D6:D5000="Room Revenue")*(Revenue_Log!B6:B5000=$C$5)*(Revenue_Log!H6:H5000))) | E13: =IF($C$5="All",SUMPRODUCT((MONTH(Revenue_Log!A6:A5000)=3)*(Revenue_Log!D6:D5000="Room Revenue")*(Revenue_Log!H6:H5000)),SUMPRODUCT((MONTH(Revenue_Log!A6:A5000)=3)*(Revenue_Log!D6:D5000="Room Revenue")*(Revenue_Log!B6:B5000=$C$5)*(Revenue_Log!H6:H5000))) | F13: =IF($C$5="All",SUMPRODUCT((MONTH(Revenue_Log!A6:A5000)=4)*(Revenue_Log!D6:D5000="Room Revenue")*(Revenue_Log!H6:H5000)),SUMPRODUCT((MONTH(Revenue_Log!A6:A5000)=4)*(Revenue_Log!D6:D5000="Room Revenue")*(Revenue_Log!B6:B5000=$C$5)*(Revenue_Log!H6:H5000))) | G13: =IF($C$5="All",SUMPRODUCT((MONTH(Revenue_Log!A6:A5000)=5)*(Revenue_Log!D6:D5000="Room Revenue")*(Revenue_Log!H6:H5000)),SUMPRODUCT((MONTH(Revenue_Log!A6:A5000)=5)*(Revenue_Log!D6:D5000="Room Revenue")*(Revenue_Log!B6:B5000=$C$5)*(Revenue_Log!H6:H5000))) | H13: =IF($C$5="All",SUMPRODUCT((MONTH(Revenue_Log!A6:A5000)=6)*(Revenue_Log!D6:D5000="Room Revenue")*(Revenue_Log!H6:H5000)),SUMPRODUCT((MONTH(Revenue_Log!A6:A5000)=6)*(Revenue_Log!D6:D5000="Room Revenue")*(Revenue_Log!B6:B5000=$C$5)*(Revenue_Log!H6:H5000))) | I13: =IF($C$5="All",SUMPRODUCT((MONTH(Revenue_Log!A6:A5000)=7)*(Revenue_Log!D6:D5000="Room Revenue")*(Revenue_Log!H6:H5000)),SUMPRODUCT((MONTH(Revenue_Log!A6:A5000)=7)*(Revenue_Log!D6:D5000="Room Revenue")*(Revenue_Log!B6:B5000=$C$5)*(Revenue_Log!H6:H5000))) | J13: =IF($C$5="All",SUMPRODUCT((MONTH(Revenue_Log!A6:A5000)=8)*(Revenue_Log!D6:D5000="Room Revenue")*(Revenue_Log!H6:H5000)),SUMPRODUCT((MONTH(Revenue_Log!A6:A5000)=8)*(Revenue_Log!D6:D5000="Room Revenue")*(Revenue_Log!B6:B5000=$C$5)*(Revenue_Log!H6:H5000))) | K13: =IF($C$5="All",SUMPRODUCT((MONTH(Revenue_Log!A6:A5000)=9)*(Revenue_Log!D6:D5000="Room Revenue")*(Revenue_Log!H6:H5000)),SUMPRODUCT((MONTH(Revenue_Log!A6:A5000)=9)*(Revenue_Log!D6:D5000="Room Revenue")*(Revenue_Log!B6:B5000=$C$5)*(Revenue_Log!H6:H5000))) | L13: =IF($C$5="All",SUMPRODUCT((MONTH(Revenue_Log!A6:A5000)=10)*(Revenue_Log!D6:D5000="Room Revenue")*(Revenue_Log!H6:H5000)),SUMPRODUCT((MONTH(Revenue_Log!A6:A5000)=10)*(Revenue_Log!D6:D5000="Room Revenue")*(Revenue_Log!B6:B5000=$C$5)*(Revenue_Log!H6:H5000))) | M13: =IF($C$5="All",SUMPRODUCT((MONTH(Revenue_Log!A6:A5000)=11)*(Revenue_Log!D6:D5000="Room Revenue")*(Revenue_Log!H6:H5000)),SUMPRODUCT((MONTH(Revenue_Log!A6:A5000)=11)*(Revenue_Log!D6:D5000="Room Revenue")*(Revenue_Log!B6:B5000=$C$5)*(Revenue_Log!H6:H5000))) | N13: =IF($C$5="All",SUMPRODUCT((MONTH(Revenue_Log!A6:A5000)=12)*(Revenue_Log!D6:D5000="Room Revenue")*(Revenue_Log!H6:H5000)),SUMPRODUCT((MONTH(Revenue_Log!A6:A5000)=12)*(Revenue_Log!D6:D5000="Room Revenue")*(Revenue_Log!B6:B5000=$C$5)*(Revenue_Log!H6:H5000))) | O13: =SUM(C13:N13)
B14: Shop Rent | C14: =IF($C$5="All",SUMPRODUCT((MONTH(Revenue_Log!A6:A5000)=1)*(Revenue_Log!D6:D5000="Shop Rent")*(Revenue_Log!H6:H5000)),SUMPRODUCT((MONTH(Revenue_Log!A6:A5000)=1)*(Revenue_Log!D6:D5000="Shop Rent")*(Revenue_Log!B6:B5000=$C$5)*(Revenue_Log!H6:H5000))) | D14: =IF($C$5="All",SUMPRODUCT((MONTH(Revenue_Log!A6:A5000)=2)*(Revenue_Log!D6:D5000="Shop Rent")*(Revenue_Log!H6:H5000)),SUMPRODUCT((MONTH(Revenue_Log!A6:A5000)=2)*(Revenue_Log!D6:D5000="Shop Rent")*(Revenue_Log!B6:B5000=$C$5)*(Revenue_Log!H6:H5000))) | E14: =IF($C$5="All",SUMPRODUCT((MONTH(Revenue_Log!A6:A5000)=3)*(Revenue_Log!D6:D5000="Shop Rent")*(Revenue_Log!H6:H5000)),SUMPRODUCT((MONTH(Revenue_Log!A6:A5000)=3)*(Revenue_Log!D6:D5000="Shop Rent")*(Revenue_Log!B6:B5000=$C$5)*(Revenue_Log!H6:H5000))) | F14: =IF($C$5="All",SUMPRODUCT((MONTH(Revenue_Log!A6:A5000)=4)*(Revenue_Log!D6:D5000="Shop Rent")*(Revenue_Log!H6:H5000)),SUMPRODUCT((MONTH(Revenue_Log!A6:A5000)=4)*(Revenue_Log!D6:D5000="Shop Rent")*(Revenue_Log!B6:B5000=$C$5)*(Revenue_Log!H6:H5000))) | G14: =IF($C$5="All",SUMPRODUCT((MONTH(Revenue_Log!A6:A5000)=5)*(Revenue_Log!D6:D5000="Shop Rent")*(Revenue_Log!H6:H5000)),SUMPRODUCT((MONTH(Revenue_Log!A6:A5000)=5)*(Revenue_Log!D6:D5000="Shop Rent")*(Revenue_Log!B6:B5000=$C$5)*(Revenue_Log!H6:H5000))) | H14: =IF($C$5="All",SUMPRODUCT((MONTH(Revenue_Log!A6:A5000)=6)*(Revenue_Log!D6:D5000="Shop Rent")*(Revenue_Log!H6:H5000)),SUMPRODUCT((MONTH(Revenue_Log!A6:A5000)=6)*(Revenue_Log!D6:D5000="Shop Rent")*(Revenue_Log!B6:B5000=$C$5)*(Revenue_Log!H6:H5000))) | I14: =IF($C$5="All",SUMPRODUCT((MONTH(Revenue_Log!A6:A5000)=7)*(Revenue_Log!D6:D5000="Shop Rent")*(Revenue_Log!H6:H5000)),SUMPRODUCT((MONTH(Revenue_Log!A6:A5000)=7)*(Revenue_Log!D6:D5000="Shop Rent")*(Revenue_Log!B6:B5000=$C$5)*(Revenue_Log!H6:H5000))) | J14: =IF($C$5="All",SUMPRODUCT((MONTH(Revenue_Log!A6:A5000)=8)*(Revenue_Log!D6:D5000="Shop Rent")*(Revenue_Log!H6:H5000)),SUMPRODUCT((MONTH(Revenue_Log!A6:A5000)=8)*(Revenue_Log!D6:D5000="Shop Rent")*(Revenue_Log!B6:B5000=$C$5)*(Revenue_Log!H6:H5000))) | K14: =IF($C$5="All",SUMPRODUCT((MONTH(Revenue_Log!A6:A5000)=9)*(Revenue_Log!D6:D5000="Shop Rent")*(Revenue_Log!H6:H5000)),SUMPRODUCT((MONTH(Revenue_Log!A6:A5000)=9)*(Revenue_Log!D6:D5000="Shop Rent")*(Revenue_Log!B6:B5000=$C$5)*(Revenue_Log!H6:H5000))) | L14: =IF($C$5="All",SUMPRODUCT((MONTH(Revenue_Log!A6:A5000)=10)*(Revenue_Log!D6:D5000="Shop Rent")*(Revenue_Log!H6:H5000)),SUMPRODUCT((MONTH(Revenue_Log!A6:A5000)=10)*(Revenue_Log!D6:D5000="Shop Rent")*(Revenue_Log!B6:B5000=$C$5)*(Revenue_Log!H6:H5000))) | M14: =IF($C$5="All",SUMPRODUCT((MONTH(Revenue_Log!A6:A5000)=11)*(Revenue_Log!D6:D5000="Shop Rent")*(Revenue_Log!H6:H5000)),SUMPRODUCT((MONTH(Revenue_Log!A6:A5000)=11)*(Revenue_Log!D6:D5000="Shop Rent")*(Revenue_Log!B6:B5000=$C$5)*(Revenue_Log!H6:H5000))) | N14: =IF($C$5="All",SUMPRODUCT((MONTH(Revenue_Log!A6:A5000)=12)*(Revenue_Log!D6:D5000="Shop Rent")*(Revenue_Log!H6:H5000)),SUMPRODUCT((MONTH(Revenue_Log!A6:A5000)=12)*(Revenue_Log!D6:D5000="Shop Rent")*(Revenue_Log!B6:B5000=$C$5)*(Revenue_Log!H6:H5000))) | O14: =SUM(C14:N14)
B15: Caution Fee Income | C15: =IF($C$5="All",SUMPRODUCT((MONTH(Revenue_Log!A6:A5000)=1)*(Revenue_Log!D6:D5000="Caution Fee Income")*(Revenue_Log!H6:H5000)),SUMPRODUCT((MONTH(Revenue_Log!A6:A5000)=1)*(Revenue_Log!D6:D5000="Caution Fee Income")*(Revenue_Log!B6:B5000=$C$5)*(Revenue_Log!H6:H5000))) | D15: =IF($C$5="All",SUMPRODUCT((MONTH(Revenue_Log!A6:A5000)=2)*(Revenue_Log!D6:D5000="Caution Fee Income")*(Revenue_Log!H6:H5000)),SUMPRODUCT((MONTH(Revenue_Log!A6:A5000)=2)*(Revenue_Log!D6:D5000="Caution Fee Income")*(Revenue_Log!B6:B5000=$C$5)*(Revenue_Log!H6:H5000))) | E15: =IF($C$5="All",SUMPRODUCT((MONTH(Revenue_Log!A6:A5000)=3)*(Revenue_Log!D6:D5000="Caution Fee Income")*(Revenue_Log!H6:H5000)),SUMPRODUCT((MONTH(Revenue_Log!A6:A5000)=3)*(Revenue_Log!D6:D5000="Caution Fee Income")*(Revenue_Log!B6:B5000=$C$5)*(Revenue_Log!H6:H5000))) | F15: =IF($C$5="All",SUMPRODUCT((MONTH(Revenue_Log!A6:A5000)=4)*(Revenue_Log!D6:D5000="Caution Fee Income")*(Revenue_Log!H6:H5000)),SUMPRODUCT((MONTH(Revenue_Log!A6:A5000)=4)*(Revenue_Log!D6:D5000="Caution Fee Income")*(Revenue_Log!B6:B5000=$C$5)*(Revenue_Log!H6:H5000))) | G15: =IF($C$5="All",SUMPRODUCT((MONTH(Revenue_Log!A6:A5000)=5)*(Revenue_Log!D6:D5000="Caution Fee Income")*(Revenue_Log!H6:H5000)),SUMPRODUCT((MONTH(Revenue_Log!A6:A5000)=5)*(Revenue_Log!D6:D5000="Caution Fee Income")*(Revenue_Log!B6:B5000=$C$5)*(Revenue_Log!H6:H5000))) | H15: =IF($C$5="All",SUMPRODUCT((MONTH(Revenue_Log!A6:A5000)=6)*(Revenue_Log!D6:D5000="Caution Fee Income")*(Revenue_Log!H6:H5000)),SUMPRODUCT((MONTH(Revenue_Log!A6:A5000)=6)*(Revenue_Log!D6:D5000="Caution Fee Income")*(Revenue_Log!B6:B5000=$C$5)*(Revenue_Log!H6:H5000))) | I15: =IF($C$5="All",SUMPRODUCT((MONTH(Revenue_Log!A6:A5000)=7)*(Revenue_Log!D6:D5000="Caution Fee Income")*(Revenue_Log!H6:H5000)),SUMPRODUCT((MONTH(Revenue_Log!A6:A5000)=7)*(Revenue_Log!D6:D5000="Caution Fee Income")*(Revenue_Log!B6:B5000=$C$5)*(Revenue_Log!H6:H5000))) | J15: =IF($C$5="All",SUMPRODUCT((MONTH(Revenue_Log!A6:A5000)=8)*(Revenue_Log!D6:D5000="Caution Fee Income")*(Revenue_Log!H6:H5000)),SUMPRODUCT((MONTH(Revenue_Log!A6:A5000)=8)*(Revenue_Log!D6:D5000="Caution Fee Income")*(Revenue_Log!B6:B5000=$C$5)*(Revenue_Log!H6:H5000))) | K15: =IF($C$5="All",SUMPRODUCT((MONTH(Revenue_Log!A6:A5000)=9)*(Revenue_Log!D6:D5000="Caution Fee Income")*(Revenue_Log!H6:H5000)),SUMPRODUCT((MONTH(Revenue_Log!A6:A5000)=9)*(Revenue_Log!D6:D5000="Caution Fee Income")*(Revenue_Log!B6:B5000=$C$5)*(Revenue_Log!H6:H5000))) | L15: =IF($C$5="All",SUMPRODUCT((MONTH(Revenue_Log!A6:A5000)=10)*(Revenue_Log!D6:D5000="Caution Fee Income")*(Revenue_Log!H6:H5000)),SUMPRODUCT((MONTH(Revenue_Log!A6:A5000)=10)*(Revenue_Log!D6:D5000="Caution Fee Income")*(Revenue_Log!B6:B5000=$C$5)*(Revenue_Log!H6:H5000))) | M15: =IF($C$5="All",SUMPRODUCT((MONTH(Revenue_Log!A6:A5000)=11)*(Revenue_Log!D6:D5000="Caution Fee Income")*(Revenue_Log!H6:H5000)),SUMPRODUCT((MONTH(Revenue_Log!A6:A5000)=11)*(Revenue_Log!D6:D5000="Caution Fee Income")*(Revenue_Log!B6:B5000=$C$5)*(Revenue_Log!H6:H5000))) | N15: =IF($C$5="All",SUMPRODUCT((MONTH(Revenue_Log!A6:A5000)=12)*(Revenue_Log!D6:D5000="Caution Fee Income")*(Revenue_Log!H6:H5000)),SUMPRODUCT((MONTH(Revenue_Log!A6:A5000)=12)*(Revenue_Log!D6:D5000="Caution Fee Income")*(Revenue_Log!B6:B5000=$C$5)*(Revenue_Log!H6:H5000))) | O15: =SUM(C15:N15)
B16: Extra Charges | C16: =IF($C$5="All",SUMPRODUCT((MONTH(Revenue_Log!A6:A5000)=1)*(Revenue_Log!D6:D5000="Extra Charges")*(Revenue_Log!H6:H5000)),SUMPRODUCT((MONTH(Revenue_Log!A6:A5000)=1)*(Revenue_Log!D6:D5000="Extra Charges")*(Revenue_Log!B6:B5000=$C$5)*(Revenue_Log!H6:H5000))) | D16: =IF($C$5="All",SUMPRODUCT((MONTH(Revenue_Log!A6:A5000)=2)*(Revenue_Log!D6:D5000="Extra Charges")*(Revenue_Log!H6:H5000)),SUMPRODUCT((MONTH(Revenue_Log!A6:A5000)=2)*(Revenue_Log!D6:D5000="Extra Charges")*(Revenue_Log!B6:B5000=$C$5)*(Revenue_Log!H6:H5000))) | E16: =IF($C$5="All",SUMPRODUCT((MONTH(Revenue_Log!A6:A5000)=3)*(Revenue_Log!D6:D5000="Extra Charges")*(Revenue_Log!H6:H5000)),SUMPRODUCT((MONTH(Revenue_Log!A6:A5000)=3)*(Revenue_Log!D6:D5000="Extra Charges")*(Revenue_Log!B6:B5000=$C$5)*(Revenue_Log!H6:H5000))) | F16: =IF($C$5="All",SUMPRODUCT((MONTH(Revenue_Log!A6:A5000)=4)*(Revenue_Log!D6:D5000="Extra Charges")*(Revenue_Log!H6:H5000)),SUMPRODUCT((MONTH(Revenue_Log!A6:A5000)=4)*(Revenue_Log!D6:D5000="Extra Charges")*(Revenue_Log!B6:B5000=$C$5)*(Revenue_Log!H6:H5000))) | G16: =IF($C$5="All",SUMPRODUCT((MONTH(Revenue_Log!A6:A5000)=5)*(Revenue_Log!D6:D5000="Extra Charges")*(Revenue_Log!H6:H5000)),SUMPRODUCT((MONTH(Revenue_Log!A6:A5000)=5)*(Revenue_Log!D6:D5000="Extra Charges")*(Revenue_Log!B6:B5000=$C$5)*(Revenue_Log!H6:H5000))) | H16: =IF($C$5="All",SUMPRODUCT((MONTH(Revenue_Log!A6:A5000)=6)*(Revenue_Log!D6:D5000="Extra Charges")*(Revenue_Log!H6:H5000)),SUMPRODUCT((MONTH(Revenue_Log!A6:A5000)=6)*(Revenue_Log!D6:D5000="Extra Charges")*(Revenue_Log!B6:B5000=$C$5)*(Revenue_Log!H6:H5000))) | I16: =IF($C$5="All",SUMPRODUCT((MONTH(Revenue_Log!A6:A5000)=7)*(Revenue_Log!D6:D5000="Extra Charges")*(Revenue_Log!H6:H5000)),SUMPRODUCT((MONTH(Revenue_Log!A6:A5000)=7)*(Revenue_Log!D6:D5000="Extra Charges")*(Revenue_Log!B6:B5000=$C$5)*(Revenue_Log!H6:H5000))) | J16: =IF($C$5="All",SUMPRODUCT((MONTH(Revenue_Log!A6:A5000)=8)*(Revenue_Log!D6:D5000="Extra Charges")*(Revenue_Log!H6:H5000)),SUMPRODUCT((MONTH(Revenue_Log!A6:A5000)=8)*(Revenue_Log!D6:D5000="Extra Charges")*(Revenue_Log!B6:B5000=$C$5)*(Revenue_Log!H6:H5000))) | K16: =IF($C$5="All",SUMPRODUCT((MONTH(Revenue_Log!A6:A5000)=9)*(Revenue_Log!D6:D5000="Extra Charges")*(Revenue_Log!H6:H5000)),SUMPRODUCT((MONTH(Revenue_Log!A6:A5000)=9)*(Revenue_Log!D6:D5000="Extra Charges")*(Revenue_Log!B6:B5000=$C$5)*(Revenue_Log!H6:H5000))) | L16: =IF($C$5="All",SUMPRODUCT((MONTH(Revenue_Log!A6:A5000)=10)*(Revenue_Log!D6:D5000="Extra Charges")*(Revenue_Log!H6:H5000)),SUMPRODUCT((MONTH(Revenue_Log!A6:A5000)=10)*(Revenue_Log!D6:D5000="Extra Charges")*(Revenue_Log!B6:B5000=$C$5)*(Revenue_Log!H6:H5000))) | M16: =IF($C$5="All",SUMPRODUCT((MONTH(Revenue_Log!A6:A5000)=11)*(Revenue_Log!D6:D5000="Extra Charges")*(Revenue_Log!H6:H5000)),SUMPRODUCT((MONTH(Revenue_Log!A6:A5000)=11)*(Revenue_Log!D6:D5000="Extra Charges")*(Revenue_Log!B6:B5000=$C$5)*(Revenue_Log!H6:H5000))) | N16: =IF($C$5="All",SUMPRODUCT((MONTH(Revenue_Log!A6:A5000)=12)*(Revenue_Log!D6:D5000="Extra Charges")*(Revenue_Log!H6:H5000)),SUMPRODUCT((MONTH(Revenue_Log!A6:A5000)=12)*(Revenue_Log!D6:D5000="Extra Charges")*(Revenue_Log!B6:B5000=$C$5)*(Revenue_Log!H6:H5000))) | O16: =SUM(C16:N16)
B17: Form & Legal Fees | C17: =IF($C$5="All",SUMPRODUCT((MONTH(Revenue_Log!A6:A5000)=1)*(Revenue_Log!D6:D5000="Form & Legal Fees")*(Revenue_Log!H6:H5000)),SUMPRODUCT((MONTH(Revenue_Log!A6:A5000)=1)*(Revenue_Log!D6:D5000="Form & Legal Fees")*(Revenue_Log!B6:B5000=$C$5)*(Revenue_Log!H6:H5000))) | D17: =IF($C$5="All",SUMPRODUCT((MONTH(Revenue_Log!A6:A5000)=2)*(Revenue_Log!D6:D5000="Form & Legal Fees")*(Revenue_Log!H6:H5000)),SUMPRODUCT((MONTH(Revenue_Log!A6:A5000)=2)*(Revenue_Log!D6:D5000="Form & Legal Fees")*(Revenue_Log!B6:B5000=$C$5)*(Revenue_Log!H6:H5000))) | E17: =IF($C$5="All",SUMPRODUCT((MONTH(Revenue_Log!A6:A5000)=3)*(Revenue_Log!D6:D5000="Form & Legal Fees")*(Revenue_Log!H6:H5000)),SUMPRODUCT((MONTH(Revenue_Log!A6:A5000)=3)*(Revenue_Log!D6:D5000="Form & Legal Fees")*(Revenue_Log!B6:B5000=$C$5)*(Revenue_Log!H6:H5000))) | F17: =IF($C$5="All",SUMPRODUCT((MONTH(Revenue_Log!A6:A5000)=4)*(Revenue_Log!D6:D5000="Form & Legal Fees")*(Revenue_Log!H6:H5000)),SUMPRODUCT((MONTH(Revenue_Log!A6:A5000)=4)*(Revenue_Log!D6:D5000="Form & Legal Fees")*(Revenue_Log!B6:B5000=$C$5)*(Revenue_Log!H6:H5000))) | G17: =IF($C$5="All",SUMPRODUCT((MONTH(Revenue_Log!A6:A5000)=5)*(Revenue_Log!D6:D5000="Form & Legal Fees")*(Revenue_Log!H6:H5000)),SUMPRODUCT((MONTH(Revenue_Log!A6:A5000)=5)*(Revenue_Log!D6:D5000="Form & Legal Fees")*(Revenue_Log!B6:B5000=$C$5)*(Revenue_Log!H6:H5000))) | H17: =IF($C$5="All",SUMPRODUCT((MONTH(Revenue_Log!A6:A5000)=6)*(Revenue_Log!D6:D5000="Form & Legal Fees")*(Revenue_Log!H6:H5000)),SUMPRODUCT((MONTH(Revenue_Log!A6:A5000)=6)*(Revenue_Log!D6:D5000="Form & Legal Fees")*(Revenue_Log!B6:B5000=$C$5)*(Revenue_Log!H6:H5000))) | I17: =IF($C$5="All",SUMPRODUCT((MONTH(Revenue_Log!A6:A5000)=7)*(Revenue_Log!D6:D5000="Form & Legal Fees")*(Revenue_Log!H6:H5000)),SUMPRODUCT((MONTH(Revenue_Log!A6:A5000)=7)*(Revenue_Log!D6:D5000="Form & Legal Fees")*(Revenue_Log!B6:B5000=$C$5)*(Revenue_Log!H6:H5000))) | J17: =IF($C$5="All",SUMPRODUCT((MONTH(Revenue_Log!A6:A5000)=8)*(Revenue_Log!D6:D5000="Form & Legal Fees")*(Revenue_Log!H6:H5000)),SUMPRODUCT((MONTH(Revenue_Log!A6:A5000)=8)*(Revenue_Log!D6:D5000="Form & Legal Fees")*(Revenue_Log!B6:B5000=$C$5)*(Revenue_Log!H6:H5000))) | K17: =IF($C$5="All",SUMPRODUCT((MONTH(Revenue_Log!A6:A5000)=9)*(Revenue_Log!D6:D5000="Form & Legal Fees")*(Revenue_Log!H6:H5000)),SUMPRODUCT((MONTH(Revenue_Log!A6:A5000)=9)*(Revenue_Log!D6:D5000="Form & Legal Fees")*(Revenue_Log!B6:B5000=$C$5)*(Revenue_Log!H6:H5000))) | L17: =IF($C$5="All",SUMPRODUCT((MONTH(Revenue_Log!A6:A5000)=10)*(Revenue_Log!D6:D5000="Form & Legal Fees")*(Revenue_Log!H6:H5000)),SUMPRODUCT((MONTH(Revenue_Log!A6:A5000)=10)*(Revenue_Log!D6:D5000="Form & Legal Fees")*(Revenue_Log!B6:B5000=$C$5)*(Revenue_Log!H6:H5000))) | M17: =IF($C$5="All",SUMPRODUCT((MONTH(Revenue_Log!A6:A5000)=11)*(Revenue_Log!D6:D5000="Form & Legal Fees")*(Revenue_Log!H6:H5000)),SUMPRODUCT((MONTH(Revenue_Log!A6:A5000)=11)*(Revenue_Log!D6:D5000="Form & Legal Fees")*(Revenue_Log!B6:B5000=$C$5)*(Revenue_Log!H6:H5000))) | N17: =IF($C$5="All",SUMPRODUCT((MONTH(Revenue_Log!A6:A5000)=12)*(Revenue_Log!D6:D5000="Form & Legal Fees")*(Revenue_Log!H6:H5000)),SUMPRODUCT((MONTH(Revenue_Log!A6:A5000)=12)*(Revenue_Log!D6:D5000="Form & Legal Fees")*(Revenue_Log!B6:B5000=$C$5)*(Revenue_Log!H6:H5000))) | O17: =SUM(C17:N17)
B18: Other Income | C18: =IF($C$5="All",SUMPRODUCT((MONTH(Revenue_Log!A6:A5000)=1)*(Revenue_Log!D6:D5000="Other Income")*(Revenue_Log!H6:H5000)),SUMPRODUCT((MONTH(Revenue_Log!A6:A5000)=1)*(Revenue_Log!D6:D5000="Other Income")*(Revenue_Log!B6:B5000=$C$5)*(Revenue_Log!H6:H5000))) | D18: =IF($C$5="All",SUMPRODUCT((MONTH(Revenue_Log!A6:A5000)=2)*(Revenue_Log!D6:D5000="Other Income")*(Revenue_Log!H6:H5000)),SUMPRODUCT((MONTH(Revenue_Log!A6:A5000)=2)*(Revenue_Log!D6:D5000="Other Income")*(Revenue_Log!B6:B5000=$C$5)*(Revenue_Log!H6:H5000))) | E18: =IF($C$5="All",SUMPRODUCT((MONTH(Revenue_Log!A6:A5000)=3)*(Revenue_Log!D6:D5000="Other Income")*(Revenue_Log!H6:H5000)),SUMPRODUCT((MONTH(Revenue_Log!A6:A5000)=3)*(Revenue_Log!D6:D5000="Other Income")*(Revenue_Log!B6:B5000=$C$5)*(Revenue_Log!H6:H5000))) | F18: =IF($C$5="All",SUMPRODUCT((MONTH(Revenue_Log!A6:A5000)=4)*(Revenue_Log!D6:D5000="Other Income")*(Revenue_Log!H6:H5000)),SUMPRODUCT((MONTH(Revenue_Log!A6:A5000)=4)*(Revenue_Log!D6:D5000="Other Income")*(Revenue_Log!B6:B5000=$C$5)*(Revenue_Log!H6:H5000))) | G18: =IF($C$5="All",SUMPRODUCT((MONTH(Revenue_Log!A6:A5000)=5)*(Revenue_Log!D6:D5000="Other Income")*(Revenue_Log!H6:H5000)),SUMPRODUCT((MONTH(Revenue_Log!A6:A5000)=5)*(Revenue_Log!D6:D5000="Other Income")*(Revenue_Log!B6:B5000=$C$5)*(Revenue_Log!H6:H5000))) | H18: =IF($C$5="All",SUMPRODUCT((MONTH(Revenue_Log!A6:A5000)=6)*(Revenue_Log!D6:D5000="Other Income")*(Revenue_Log!H6:H5000)),SUMPRODUCT((MONTH(Revenue_Log!A6:A5000)=6)*(Revenue_Log!D6:D5000="Other Income")*(Revenue_Log!B6:B5000=$C$5)*(Revenue_Log!H6:H5000))) | I18: =IF($C$5="All",SUMPRODUCT((MONTH(Revenue_Log!A6:A5000)=7)*(Revenue_Log!D6:D5000="Other Income")*(Revenue_Log!H6:H5000)),SUMPRODUCT((MONTH(Revenue_Log!A6:A5000)=7)*(Revenue_Log!D6:D5000="Other Income")*(Revenue_Log!B6:B5000=$C$5)*(Revenue_Log!H6:H5000))) | J18: =IF($C$5="All",SUMPRODUCT((MONTH(Revenue_Log!A6:A5000)=8)*(Revenue_Log!D6:D5000="Other Income")*(Revenue_Log!H6:H5000)),SUMPRODUCT((MONTH(Revenue_Log!A6:A5000)=8)*(Revenue_Log!D6:D5000="Other Income")*(Revenue_Log!B6:B5000=$C$5)*(Revenue_Log!H6:H5000))) | K18: =IF($C$5="All",SUMPRODUCT((MONTH(Revenue_Log!A6:A5000)=9)*(Revenue_Log!D6:D5000="Other Income")*(Revenue_Log!H6:H5000)),SUMPRODUCT((MONTH(Revenue_Log!A6:A5000)=9)*(Revenue_Log!D6:D5000="Other Income")*(Revenue_Log!B6:B5000=$C$5)*(Revenue_Log!H6:H5000))) | L18: =IF($C$5="All",SUMPRODUCT((MONTH(Revenue_Log!A6:A5000)=10)*(Revenue_Log!D6:D5000="Other Income")*(Revenue_Log!H6:H5000)),SUMPRODUCT((MONTH(Revenue_Log!A6:A5000)=10)*(Revenue_Log!D6:D5000="Other Income")*(Revenue_Log!B6:B5000=$C$5)*(Revenue_Log!H6:H5000))) | M18: =IF($C$5="All",SUMPRODUCT((MONTH(Revenue_Log!A6:A5000)=11)*(Revenue_Log!D6:D5000="Other Income")*(Revenue_Log!H6:H5000)),SUMPRODUCT((MONTH(Revenue_Log!A6:A5000)=11)*(Revenue_Log!D6:D5000="Other Income")*(Revenue_Log!B6:B5000=$C$5)*(Revenue_Log!H6:H5000))) | N18: =IF($C$5="All",SUMPRODUCT((MONTH(Revenue_Log!A6:A5000)=12)*(Revenue_Log!D6:D5000="Other Income")*(Revenue_Log!H6:H5000)),SUMPRODUCT((MONTH(Revenue_Log!A6:A5000)=12)*(Revenue_Log!D6:D5000="Other Income")*(Revenue_Log!B6:B5000=$C$5)*(Revenue_Log!H6:H5000))) | O18: =SUM(C18:N18)
B19: TOTAL REVENUE | C19: =SUM(C13:C18) | D19: =SUM(D13:D18) | E19: =SUM(E13:E18) | F19: =SUM(F13:F18) | G19: =SUM(G13:G18) | H19: =SUM(H13:H18) | I19: =SUM(I13:I18) | J19: =SUM(J13:J18) | ... O19: =SUM(O13:O18)
B20: EXPENDITURE:
B21: Salaries | C21: =SUMPRODUCT((Staff_Salaries!A6:A5000=Dashboard!$B$1)*(Staff_Salaries!B6:B5000="January")*(Staff_Salaries!E6:E5000)) | D21: =SUMPRODUCT((Staff_Salaries!A6:A5000=Dashboard!$B$1)*(Staff_Salaries!B6:B5000="February")*(Staff_Salaries!E6:E5000)) | E21: =SUMPRODUCT((Staff_Salaries!A6:A5000=Dashboard!$B$1)*(Staff_Salaries!B6:B5000="March")*(Staff_Salaries!E6:E5000)) | F21: =SUMPRODUCT((Staff_Salaries!A6:A5000=Dashboard!$B$1)*(Staff_Salaries!B6:B5000="April")*(Staff_Salaries!E6:E5000)) | G21: =SUMPRODUCT((Staff_Salaries!A6:A5000=Dashboard!$B$1)*(Staff_Salaries!B6:B5000="May")*(Staff_Salaries!E6:E5000)) | H21: =SUMPRODUCT((Staff_Salaries!A6:A5000=Dashboard!$B$1)*(Staff_Salaries!B6:B5000="June")*(Staff_Salaries!E6:E5000)) | I21: =SUMPRODUCT((Staff_Salaries!A6:A5000=Dashboard!$B$1)*(Staff_Salaries!B6:B5000="July")*(Staff_Salaries!E6:E5000)) | J21: =SUMPRODUCT((Staff_Salaries!A6:A5000=Dashboard!$B$1)*(Staff_Salaries!B6:B5000="August")*(Staff_Salaries!E6:E5000)) | K21: =SUMPRODUCT((Staff_Salaries!A6:A5000=Dashboard!$B$1)*(Staff_Salaries!B6:B5000="September")*(Staff_Salaries!E6:E5000)) | L21: =SUMPRODUCT((Staff_Salaries!A6:A5000=Dashboard!$B$1)*(Staff_Salaries!B6:B5000="October")*(Staff_Salaries!E6:E5000)) | M21: =SUMPRODUCT((Staff_Salaries!A6:A5000=Dashboard!$B$1)*(Staff_Salaries!B6:B5000="November")*(Staff_Salaries!E6:E5000)) | N21: =SUMPRODUCT((Staff_Salaries!A6:A5000=Dashboard!$B$1)*(Staff_Salaries!B6:B5000="December")*(Staff_Salaries!E6:E5000)) | O21: =SUM(C21:N21)
B22: Construction | C22: =IF($C$5="All",SUMPRODUCT((MONTH(Expenses_Log!A6:A5000)=1)*(Expenses_Log!C6:C5000="Construction")*(Expenses_Log!G6:G5000)),SUMPRODUCT((MONTH(Expenses_Log!A6:A5000)=1)*(Expenses_Log!C6:C5000="Construction")*(Expenses_Log!B6:B5000=$C$5)*(Expenses_Log!G6:G5000))) | D22: =IF($C$5="All",SUMPRODUCT((MONTH(Expenses_Log!A6:A5000)=2)*(Expenses_Log!C6:C5000="Construction")*(Expenses_Log!G6:G5000)),SUMPRODUCT((MONTH(Expenses_Log!A6:A5000)=2)*(Expenses_Log!C6:C5000="Construction")*(Expenses_Log!B6:B5000=$C$5)*(Expenses_Log!G6:G5000))) | E22: =IF($C$5="All",SUMPRODUCT((MONTH(Expenses_Log!A6:A5000)=3)*(Expenses_Log!C6:C5000="Construction")*(Expenses_Log!G6:G5000)),SUMPRODUCT((MONTH(Expenses_Log!A6:A5000)=3)*(Expenses_Log!C6:C5000="Construction")*(Expenses_Log!B6:B5000=$C$5)*(Expenses_Log!G6:G5000))) | F22: =IF($C$5="All",SUMPRODUCT((MONTH(Expenses_Log!A6:A5000)=4)*(Expenses_Log!C6:C5000="Construction")*(Expenses_Log!G6:G5000)),SUMPRODUCT((MONTH(Expenses_Log!A6:A5000)=4)*(Expenses_Log!C6:C5000="Construction")*(Expenses_Log!B6:B5000=$C$5)*(Expenses_Log!G6:G5000))) | G22: =IF($C$5="All",SUMPRODUCT((MONTH(Expenses_Log!A6:A5000)=5)*(Expenses_Log!C6:C5000="Construction")*(Expenses_Log!G6:G5000)),SUMPRODUCT((MONTH(Expenses_Log!A6:A5000)=5)*(Expenses_Log!C6:C5000="Construction")*(Expenses_Log!B6:B5000=$C$5)*(Expenses_Log!G6:G5000))) | H22: =IF($C$5="All",SUMPRODUCT((MONTH(Expenses_Log!A6:A5000)=6)*(Expenses_Log!C6:C5000="Construction")*(Expenses_Log!G6:G5000)),SUMPRODUCT((MONTH(Expenses_Log!A6:A5000)=6)*(Expenses_Log!C6:C5000="Construction")*(Expenses_Log!B6:B5000=$C$5)*(Expenses_Log!G6:G5000))) | I22: =IF($C$5="All",SUMPRODUCT((MONTH(Expenses_Log!A6:A5000)=7)*(Expenses_Log!C6:C5000="Construction")*(Expenses_Log!G6:G5000)),SUMPRODUCT((MONTH(Expenses_Log!A6:A5000)=7)*(Expenses_Log!C6:C5000="Construction")*(Expenses_Log!B6:B5000=$C$5)*(Expenses_Log!G6:G5000))) | J22: =IF($C$5="All",SUMPRODUCT((MONTH(Expenses_Log!A6:A5000)=8)*(Expenses_Log!C6:C5000="Construction")*(Expenses_Log!G6:G5000)),SUMPRODUCT((MONTH(Expenses_Log!A6:A5000)=8)*(Expenses_Log!C6:C5000="Construction")*(Expenses_Log!B6:B5000=$C$5)*(Expenses_Log!G6:G5000))) | K22: =IF($C$5="All",SUMPRODUCT((MONTH(Expenses_Log!A6:A5000)=9)*(Expenses_Log!C6:C5000="Construction")*(Expenses_Log!G6:G5000)),SUMPRODUCT((MONTH(Expenses_Log!A6:A5000)=9)*(Expenses_Log!C6:C5000="Construction")*(Expenses_Log!B6:B5000=$C$5)*(Expenses_Log!G6:G5000))) | L22: =IF($C$5="All",SUMPRODUCT((MONTH(Expenses_Log!A6:A5000)=10)*(Expenses_Log!C6:C5000="Construction")*(Expenses_Log!G6:G5000)),SUMPRODUCT((MONTH(Expenses_Log!A6:A5000)=10)*(Expenses_Log!C6:C5000="Construction")*(Expenses_Log!B6:B5000=$C$5)*(Expenses_Log!G6:G5000))) | M22: =IF($C$5="All",SUMPRODUCT((MONTH(Expenses_Log!A6:A5000)=11)*(Expenses_Log!C6:C5000="Construction")*(Expenses_Log!G6:G5000)),SUMPRODUCT((MONTH(Expenses_Log!A6:A5000)=11)*(Expenses_Log!C6:C5000="Construction")*(Expenses_Log!B6:B5000=$C$5)*(Expenses_Log!G6:G5000))) | N22: =IF($C$5="All",SUMPRODUCT((MONTH(Expenses_Log!A6:A5000)=12)*(Expenses_Log!C6:C5000="Construction")*(Expenses_Log!G6:G5000)),SUMPRODUCT((MONTH(Expenses_Log!A6:A5000)=12)*(Expenses_Log!C6:C5000="Construction")*(Expenses_Log!B6:B5000=$C$5)*(Expenses_Log!G6:G5000))) | O22: =SUM(C22:N22)
B23: Maintenance | C23: =IF($C$5="All",SUMPRODUCT((MONTH(Expenses_Log!A6:A5000)=1)*(Expenses_Log!C6:C5000="Maintenance")*(Expenses_Log!G6:G5000)),SUMPRODUCT((MONTH(Expenses_Log!A6:A5000)=1)*(Expenses_Log!C6:C5000="Maintenance")*(Expenses_Log!B6:B5000=$C$5)*(Expenses_Log!G6:G5000))) | D23: =IF($C$5="All",SUMPRODUCT((MONTH(Expenses_Log!A6:A5000)=2)*(Expenses_Log!C6:C5000="Maintenance")*(Expenses_Log!G6:G5000)),SUMPRODUCT((MONTH(Expenses_Log!A6:A5000)=2)*(Expenses_Log!C6:C5000="Maintenance")*(Expenses_Log!B6:B5000=$C$5)*(Expenses_Log!G6:G5000))) | E23: =IF($C$5="All",SUMPRODUCT((MONTH(Expenses_Log!A6:A5000)=3)*(Expenses_Log!C6:C5000="Maintenance")*(Expenses_Log!G6:G5000)),SUMPRODUCT((MONTH(Expenses_Log!A6:A5000)=3)*(Expenses_Log!C6:C5000="Maintenance")*(Expenses_Log!B6:B5000=$C$5)*(Expenses_Log!G6:G5000))) | F23: =IF($C$5="All",SUMPRODUCT((MONTH(Expenses_Log!A6:A5000)=4)*(Expenses_Log!C6:C5000="Maintenance")*(Expenses_Log!G6:G5000)),SUMPRODUCT((MONTH(Expenses_Log!A6:A5000)=4)*(Expenses_Log!C6:C5000="Maintenance")*(Expenses_Log!B6:B5000=$C$5)*(Expenses_Log!G6:G5000))) | G23: =IF($C$5="All",SUMPRODUCT((MONTH(Expenses_Log!A6:A5000)=5)*(Expenses_Log!C6:C5000="Maintenance")*(Expenses_Log!G6:G5000)),SUMPRODUCT((MONTH(Expenses_Log!A6:A5000)=5)*(Expenses_Log!C6:C5000="Maintenance")*(Expenses_Log!B6:B5000=$C$5)*(Expenses_Log!G6:G5000))) | H23: =IF($C$5="All",SUMPRODUCT((MONTH(Expenses_Log!A6:A5000)=6)*(Expenses_Log!C6:C5000="Maintenance")*(Expenses_Log!G6:G5000)),SUMPRODUCT((MONTH(Expenses_Log!A6:A5000)=6)*(Expenses_Log!C6:C5000="Maintenance")*(Expenses_Log!B6:B5000=$C$5)*(Expenses_Log!G6:G5000))) | I23: =IF($C$5="All",SUMPRODUCT((MONTH(Expenses_Log!A6:A5000)=7)*(Expenses_Log!C6:C5000="Maintenance")*(Expenses_Log!G6:G5000)),SUMPRODUCT((MONTH(Expenses_Log!A6:A5000)=7)*(Expenses_Log!C6:C5000="Maintenance")*(Expenses_Log!B6:B5000=$C$5)*(Expenses_Log!G6:G5000))) | J23: =IF($C$5="All",SUMPRODUCT((MONTH(Expenses_Log!A6:A5000)=8)*(Expenses_Log!C6:C5000="Maintenance")*(Expenses_Log!G6:G5000)),SUMPRODUCT((MONTH(Expenses_Log!A6:A5000)=8)*(Expenses_Log!C6:C5000="Maintenance")*(Expenses_Log!B6:B5000=$C$5)*(Expenses_Log!G6:G5000))) | K23: =IF($C$5="All",SUMPRODUCT((MONTH(Expenses_Log!A6:A5000)=9)*(Expenses_Log!C6:C5000="Maintenance")*(Expenses_Log!G6:G5000)),SUMPRODUCT((MONTH(Expenses_Log!A6:A5000)=9)*(Expenses_Log!C6:C5000="Maintenance")*(Expenses_Log!B6:B5000=$C$5)*(Expenses_Log!G6:G5000))) | L23: =IF($C$5="All",SUMPRODUCT((MONTH(Expenses_Log!A6:A5000)=10)*(Expenses_Log!C6:C5000="Maintenance")*(Expenses_Log!G6:G5000)),SUMPRODUCT((MONTH(Expenses_Log!A6:A5000)=10)*(Expenses_Log!C6:C5000="Maintenance")*(Expenses_Log!B6:B5000=$C$5)*(Expenses_Log!G6:G5000))) | M23: =IF($C$5="All",SUMPRODUCT((MONTH(Expenses_Log!A6:A5000)=11)*(Expenses_Log!C6:C5000="Maintenance")*(Expenses_Log!G6:G5000)),SUMPRODUCT((MONTH(Expenses_Log!A6:A5000)=11)*(Expenses_Log!C6:C5000="Maintenance")*(Expenses_Log!B6:B5000=$C$5)*(Expenses_Log!G6:G5000))) | N23: =IF($C$5="All",SUMPRODUCT((MONTH(Expenses_Log!A6:A5000)=12)*(Expenses_Log!C6:C5000="Maintenance")*(Expenses_Log!G6:G5000)),SUMPRODUCT((MONTH(Expenses_Log!A6:A5000)=12)*(Expenses_Log!C6:C5000="Maintenance")*(Expenses_Log!B6:B5000=$C$5)*(Expenses_Log!G6:G5000))) | O23: =SUM(C23:N23)
B24: Utilities | C24: =IF($C$5="All",SUMPRODUCT((MONTH(Expenses_Log!A6:A5000)=1)*(Expenses_Log!C6:C5000="Utilities")*(Expenses_Log!G6:G5000)),SUMPRODUCT((MONTH(Expenses_Log!A6:A5000)=1)*(Expenses_Log!C6:C5000="Utilities")*(Expenses_Log!B6:B5000=$C$5)*(Expenses_Log!G6:G5000))) | D24: =IF($C$5="All",SUMPRODUCT((MONTH(Expenses_Log!A6:A5000)=2)*(Expenses_Log!C6:C5000="Utilities")*(Expenses_Log!G6:G5000)),SUMPRODUCT((MONTH(Expenses_Log!A6:A5000)=2)*(Expenses_Log!C6:C5000="Utilities")*(Expenses_Log!B6:B5000=$C$5)*(Expenses_Log!G6:G5000))) | E24: =IF($C$5="All",SUMPRODUCT((MONTH(Expenses_Log!A6:A5000)=3)*(Expenses_Log!C6:C5000="Utilities")*(Expenses_Log!G6:G5000)),SUMPRODUCT((MONTH(Expenses_Log!A6:A5000)=3)*(Expenses_Log!C6:C5000="Utilities")*(Expenses_Log!B6:B5000=$C$5)*(Expenses_Log!G6:G5000))) | F24: =IF($C$5="All",SUMPRODUCT((MONTH(Expenses_Log!A6:A5000)=4)*(Expenses_Log!C6:C5000="Utilities")*(Expenses_Log!G6:G5000)),SUMPRODUCT((MONTH(Expenses_Log!A6:A5000)=4)*(Expenses_Log!C6:C5000="Utilities")*(Expenses_Log!B6:B5000=$C$5)*(Expenses_Log!G6:G5000))) | G24: =IF($C$5="All",SUMPRODUCT((MONTH(Expenses_Log!A6:A5000)=5)*(Expenses_Log!C6:C5000="Utilities")*(Expenses_Log!G6:G5000)),SUMPRODUCT((MONTH(Expenses_Log!A6:A5000)=5)*(Expenses_Log!C6:C5000="Utilities")*(Expenses_Log!B6:B5000=$C$5)*(Expenses_Log!G6:G5000))) | H24: =IF($C$5="All",SUMPRODUCT((MONTH(Expenses_Log!A6:A5000)=6)*(Expenses_Log!C6:C5000="Utilities")*(Expenses_Log!G6:G5000)),SUMPRODUCT((MONTH(Expenses_Log!A6:A5000)=6)*(Expenses_Log!C6:C5000="Utilities")*(Expenses_Log!B6:B5000=$C$5)*(Expenses_Log!G6:G5000))) | I24: =IF($C$5="All",SUMPRODUCT((MONTH(Expenses_Log!A6:A5000)=7)*(Expenses_Log!C6:C5000="Utilities")*(Expenses_Log!G6:G5000)),SUMPRODUCT((MONTH(Expenses_Log!A6:A5000)=7)*(Expenses_Log!C6:C5000="Utilities")*(Expenses_Log!B6:B5000=$C$5)*(Expenses_Log!G6:G5000))) | J24: =IF($C$5="All",SUMPRODUCT((MONTH(Expenses_Log!A6:A5000)=8)*(Expenses_Log!C6:C5000="Utilities")*(Expenses_Log!G6:G5000)),SUMPRODUCT((MONTH(Expenses_Log!A6:A5000)=8)*(Expenses_Log!C6:C5000="Utilities")*(Expenses_Log!B6:B5000=$C$5)*(Expenses_Log!G6:G5000))) | K24: =IF($C$5="All",SUMPRODUCT((MONTH(Expenses_Log!A6:A5000)=9)*(Expenses_Log!C6:C5000="Utilities")*(Expenses_Log!G6:G5000)),SUMPRODUCT((MONTH(Expenses_Log!A6:A5000)=9)*(Expenses_Log!C6:C5000="Utilities")*(Expenses_Log!B6:B5000=$C$5)*(Expenses_Log!G6:G5000))) | L24: =IF($C$5="All",SUMPRODUCT((MONTH(Expenses_Log!A6:A5000)=10)*(Expenses_Log!C6:C5000="Utilities")*(Expenses_Log!G6:G5000)),SUMPRODUCT((MONTH(Expenses_Log!A6:A5000)=10)*(Expenses_Log!C6:C5000="Utilities")*(Expenses_Log!B6:B5000=$C$5)*(Expenses_Log!G6:G5000))) | M24: =IF($C$5="All",SUMPRODUCT((MONTH(Expenses_Log!A6:A5000)=11)*(Expenses_Log!C6:C5000="Utilities")*(Expenses_Log!G6:G5000)),SUMPRODUCT((MONTH(Expenses_Log!A6:A5000)=11)*(Expenses_Log!C6:C5000="Utilities")*(Expenses_Log!B6:B5000=$C$5)*(Expenses_Log!G6:G5000))) | N24: =IF($C$5="All",SUMPRODUCT((MONTH(Expenses_Log!A6:A5000)=12)*(Expenses_Log!C6:C5000="Utilities")*(Expenses_Log!G6:G5000)),SUMPRODUCT((MONTH(Expenses_Log!A6:A5000)=12)*(Expenses_Log!C6:C5000="Utilities")*(Expenses_Log!B6:B5000=$C$5)*(Expenses_Log!G6:G5000))) | O24: =SUM(C24:N24)
B25: Inventory | C25: =IF($C$5="All",SUMPRODUCT((MONTH(Expenses_Log!A6:A5000)=1)*(Expenses_Log!C6:C5000="Inventory")*(Expenses_Log!G6:G5000)),SUMPRODUCT((MONTH(Expenses_Log!A6:A5000)=1)*(Expenses_Log!C6:C5000="Inventory")*(Expenses_Log!B6:B5000=$C$5)*(Expenses_Log!G6:G5000))) | D25: =IF($C$5="All",SUMPRODUCT((MONTH(Expenses_Log!A6:A5000)=2)*(Expenses_Log!C6:C5000="Inventory")*(Expenses_Log!G6:G5000)),SUMPRODUCT((MONTH(Expenses_Log!A6:A5000)=2)*(Expenses_Log!C6:C5000="Inventory")*(Expenses_Log!B6:B5000=$C$5)*(Expenses_Log!G6:G5000))) | E25: =IF($C$5="All",SUMPRODUCT((MONTH(Expenses_Log!A6:A5000)=3)*(Expenses_Log!C6:C5000="Inventory")*(Expenses_Log!G6:G5000)),SUMPRODUCT((MONTH(Expenses_Log!A6:A5000)=3)*(Expenses_Log!C6:C5000="Inventory")*(Expenses_Log!B6:B5000=$C$5)*(Expenses_Log!G6:G5000))) | F25: =IF($C$5="All",SUMPRODUCT((MONTH(Expenses_Log!A6:A5000)=4)*(Expenses_Log!C6:C5000="Inventory")*(Expenses_Log!G6:G5000)),SUMPRODUCT((MONTH(Expenses_Log!A6:A5000)=4)*(Expenses_Log!C6:C5000="Inventory")*(Expenses_Log!B6:B5000=$C$5)*(Expenses_Log!G6:G5000))) | G25: =IF($C$5="All",SUMPRODUCT((MONTH(Expenses_Log!A6:A5000)=5)*(Expenses_Log!C6:C5000="Inventory")*(Expenses_Log!G6:G5000)),SUMPRODUCT((MONTH(Expenses_Log!A6:A5000)=5)*(Expenses_Log!C6:C5000="Inventory")*(Expenses_Log!B6:B5000=$C$5)*(Expenses_Log!G6:G5000))) | H25: =IF($C$5="All",SUMPRODUCT((MONTH(Expenses_Log!A6:A5000)=6)*(Expenses_Log!C6:C5000="Inventory")*(Expenses_Log!G6:G5000)),SUMPRODUCT((MONTH(Expenses_Log!A6:A5000)=6)*(Expenses_Log!C6:C5000="Inventory")*(Expenses_Log!B6:B5000=$C$5)*(Expenses_Log!G6:G5000))) | I25: =IF($C$5="All",SUMPRODUCT((MONTH(Expenses_Log!A6:A5000)=7)*(Expenses_Log!C6:C5000="Inventory")*(Expenses_Log!G6:G5000)),SUMPRODUCT((MONTH(Expenses_Log!A6:A5000)=7)*(Expenses_Log!C6:C5000="Inventory")*(Expenses_Log!B6:B5000=$C$5)*(Expenses_Log!G6:G5000))) | J25: =IF($C$5="All",SUMPRODUCT((MONTH(Expenses_Log!A6:A5000)=8)*(Expenses_Log!C6:C5000="Inventory")*(Expenses_Log!G6:G5000)),SUMPRODUCT((MONTH(Expenses_Log!A6:A5000)=8)*(Expenses_Log!C6:C5000="Inventory")*(Expenses_Log!B6:B5000=$C$5)*(Expenses_Log!G6:G5000))) | K25: =IF($C$5="All",SUMPRODUCT((MONTH(Expenses_Log!A6:A5000)=9)*(Expenses_Log!C6:C5000="Inventory")*(Expenses_Log!G6:G5000)),SUMPRODUCT((MONTH(Expenses_Log!A6:A5000)=9)*(Expenses_Log!C6:C5000="Inventory")*(Expenses_Log!B6:B5000=$C$5)*(Expenses_Log!G6:G5000))) | L25: =IF($C$5="All",SUMPRODUCT((MONTH(Expenses_Log!A6:A5000)=10)*(Expenses_Log!C6:C5000="Inventory")*(Expenses_Log!G6:G5000)),SUMPRODUCT((MONTH(Expenses_Log!A6:A5000)=10)*(Expenses_Log!C6:C5000="Inventory")*(Expenses_Log!B6:B5000=$C$5)*(Expenses_Log!G6:G5000))) | M25: =IF($C$5="All",SUMPRODUCT((MONTH(Expenses_Log!A6:A5000)=11)*(Expenses_Log!C6:C5000="Inventory")*(Expenses_Log!G6:G5000)),SUMPRODUCT((MONTH(Expenses_Log!A6:A5000)=11)*(Expenses_Log!C6:C5000="Inventory")*(Expenses_Log!B6:B5000=$C$5)*(Expenses_Log!G6:G5000))) | N25: =IF($C$5="All",SUMPRODUCT((MONTH(Expenses_Log!A6:A5000)=12)*(Expenses_Log!C6:C5000="Inventory")*(Expenses_Log!G6:G5000)),SUMPRODUCT((MONTH(Expenses_Log!A6:A5000)=12)*(Expenses_Log!C6:C5000="Inventory")*(Expenses_Log!B6:B5000=$C$5)*(Expenses_Log!G6:G5000))) | O25: =SUM(C25:N25)
B26: Administrative | C26: =IF($C$5="All",SUMPRODUCT((MONTH(Expenses_Log!A6:A5000)=1)*(Expenses_Log!C6:C5000="Administrative")*(Expenses_Log!G6:G5000)),SUMPRODUCT((MONTH(Expenses_Log!A6:A5000)=1)*(Expenses_Log!C6:C5000="Administrative")*(Expenses_Log!B6:B5000=$C$5)*(Expenses_Log!G6:G5000))) | D26: =IF($C$5="All",SUMPRODUCT((MONTH(Expenses_Log!A6:A5000)=2)*(Expenses_Log!C6:C5000="Administrative")*(Expenses_Log!G6:G5000)),SUMPRODUCT((MONTH(Expenses_Log!A6:A5000)=2)*(Expenses_Log!C6:C5000="Administrative")*(Expenses_Log!B6:B5000=$C$5)*(Expenses_Log!G6:G5000))) | E26: =IF($C$5="All",SUMPRODUCT((MONTH(Expenses_Log!A6:A5000)=3)*(Expenses_Log!C6:C5000="Administrative")*(Expenses_Log!G6:G5000)),SUMPRODUCT((MONTH(Expenses_Log!A6:A5000)=3)*(Expenses_Log!C6:C5000="Administrative")*(Expenses_Log!B6:B5000=$C$5)*(Expenses_Log!G6:G5000))) | F26: =IF($C$5="All",SUMPRODUCT((MONTH(Expenses_Log!A6:A5000)=4)*(Expenses_Log!C6:C5000="Administrative")*(Expenses_Log!G6:G5000)),SUMPRODUCT((MONTH(Expenses_Log!A6:A5000)=4)*(Expenses_Log!C6:C5000="Administrative")*(Expenses_Log!B6:B5000=$C$5)*(Expenses_Log!G6:G5000))) | G26: =IF($C$5="All",SUMPRODUCT((MONTH(Expenses_Log!A6:A5000)=5)*(Expenses_Log!C6:C5000="Administrative")*(Expenses_Log!G6:G5000)),SUMPRODUCT((MONTH(Expenses_Log!A6:A5000)=5)*(Expenses_Log!C6:C5000="Administrative")*(Expenses_Log!B6:B5000=$C$5)*(Expenses_Log!G6:G5000))) | H26: =IF($C$5="All",SUMPRODUCT((MONTH(Expenses_Log!A6:A5000)=6)*(Expenses_Log!C6:C5000="Administrative")*(Expenses_Log!G6:G5000)),SUMPRODUCT((MONTH(Expenses_Log!A6:A5000)=6)*(Expenses_Log!C6:C5000="Administrative")*(Expenses_Log!B6:B5000=$C$5)*(Expenses_Log!G6:G5000))) | I26: =IF($C$5="All",SUMPRODUCT((MONTH(Expenses_Log!A6:A5000)=7)*(Expenses_Log!C6:C5000="Administrative")*(Expenses_Log!G6:G5000)),SUMPRODUCT((MONTH(Expenses_Log!A6:A5000)=7)*(Expenses_Log!C6:C5000="Administrative")*(Expenses_Log!B6:B5000=$C$5)*(Expenses_Log!G6:G5000))) | J26: =IF($C$5="All",SUMPRODUCT((MONTH(Expenses_Log!A6:A5000)=8)*(Expenses_Log!C6:C5000="Administrative")*(Expenses_Log!G6:G5000)),SUMPRODUCT((MONTH(Expenses_Log!A6:A5000)=8)*(Expenses_Log!C6:C5000="Administrative")*(Expenses_Log!B6:B5000=$C$5)*(Expenses_Log!G6:G5000))) | K26: =IF($C$5="All",SUMPRODUCT((MONTH(Expenses_Log!A6:A5000)=9)*(Expenses_Log!C6:C5000="Administrative")*(Expenses_Log!G6:G5000)),SUMPRODUCT((MONTH(Expenses_Log!A6:A5000)=9)*(Expenses_Log!C6:C5000="Administrative")*(Expenses_Log!B6:B5000=$C$5)*(Expenses_Log!G6:G5000))) | L26: =IF($C$5="All",SUMPRODUCT((MONTH(Expenses_Log!A6:A5000)=10)*(Expenses_Log!C6:C5000="Administrative")*(Expenses_Log!G6:G5000)),SUMPRODUCT((MONTH(Expenses_Log!A6:A5000)=10)*(Expenses_Log!C6:C5000="Administrative")*(Expenses_Log!B6:B5000=$C$5)*(Expenses_Log!G6:G5000))) | M26: =IF($C$5="All",SUMPRODUCT((MONTH(Expenses_Log!A6:A5000)=11)*(Expenses_Log!C6:C5000="Administrative")*(Expenses_Log!G6:G5000)),SUMPRODUCT((MONTH(Expenses_Log!A6:A5000)=11)*(Expenses_Log!C6:C5000="Administrative")*(Expenses_Log!B6:B5000=$C$5)*(Expenses_Log!G6:G5000))) | N26: =IF($C$5="All",SUMPRODUCT((MONTH(Expenses_Log!A6:A5000)=12)*(Expenses_Log!C6:C5000="Administrative")*(Expenses_Log!G6:G5000)),SUMPRODUCT((MONTH(Expenses_Log!A6:A5000)=12)*(Expenses_Log!C6:C5000="Administrative")*(Expenses_Log!B6:B5000=$C$5)*(Expenses_Log!G6:G5000))) | O26: =SUM(C26:N26)
B27: Loans & Advances | C27: =IF($C$5="All",SUMPRODUCT((MONTH(Expenses_Log!A6:A5000)=1)*(Expenses_Log!C6:C5000="Loans & Advances")*(Expenses_Log!G6:G5000)),SUMPRODUCT((MONTH(Expenses_Log!A6:A5000)=1)*(Expenses_Log!C6:C5000="Loans & Advances")*(Expenses_Log!B6:B5000=$C$5)*(Expenses_Log!G6:G5000))) | D27: =IF($C$5="All",SUMPRODUCT((MONTH(Expenses_Log!A6:A5000)=2)*(Expenses_Log!C6:C5000="Loans & Advances")*(Expenses_Log!G6:G5000)),SUMPRODUCT((MONTH(Expenses_Log!A6:A5000)=2)*(Expenses_Log!C6:C5000="Loans & Advances")*(Expenses_Log!B6:B5000=$C$5)*(Expenses_Log!G6:G5000))) | E27: =IF($C$5="All",SUMPRODUCT((MONTH(Expenses_Log!A6:A5000)=3)*(Expenses_Log!C6:C5000="Loans & Advances")*(Expenses_Log!G6:G5000)),SUMPRODUCT((MONTH(Expenses_Log!A6:A5000)=3)*(Expenses_Log!C6:C5000="Loans & Advances")*(Expenses_Log!B6:B5000=$C$5)*(Expenses_Log!G6:G5000))) | F27: =IF($C$5="All",SUMPRODUCT((MONTH(Expenses_Log!A6:A5000)=4)*(Expenses_Log!C6:C5000="Loans & Advances")*(Expenses_Log!G6:G5000)),SUMPRODUCT((MONTH(Expenses_Log!A6:A5000)=4)*(Expenses_Log!C6:C5000="Loans & Advances")*(Expenses_Log!B6:B5000=$C$5)*(Expenses_Log!G6:G5000))) | G27: =IF($C$5="All",SUMPRODUCT((MONTH(Expenses_Log!A6:A5000)=5)*(Expenses_Log!C6:C5000="Loans & Advances")*(Expenses_Log!G6:G5000)),SUMPRODUCT((MONTH(Expenses_Log!A6:A5000)=5)*(Expenses_Log!C6:C5000="Loans & Advances")*(Expenses_Log!B6:B5000=$C$5)*(Expenses_Log!G6:G5000))) | H27: =IF($C$5="All",SUMPRODUCT((MONTH(Expenses_Log!A6:A5000)=6)*(Expenses_Log!C6:C5000="Loans & Advances")*(Expenses_Log!G6:G5000)),SUMPRODUCT((MONTH(Expenses_Log!A6:A5000)=6)*(Expenses_Log!C6:C5000="Loans & Advances")*(Expenses_Log!B6:B5000=$C$5)*(Expenses_Log!G6:G5000))) | I27: =IF($C$5="All",SUMPRODUCT((MONTH(Expenses_Log!A6:A5000)=7)*(Expenses_Log!C6:C5000="Loans & Advances")*(Expenses_Log!G6:G5000)),SUMPRODUCT((MONTH(Expenses_Log!A6:A5000)=7)*(Expenses_Log!C6:C5000="Loans & Advances")*(Expenses_Log!B6:B5000=$C$5)*(Expenses_Log!G6:G5000))) | J27: =IF($C$5="All",SUMPRODUCT((MONTH(Expenses_Log!A6:A5000)=8)*(Expenses_Log!C6:C5000="Loans & Advances")*(Expenses_Log!G6:G5000)),SUMPRODUCT((MONTH(Expenses_Log!A6:A5000)=8)*(Expenses_Log!C6:C5000="Loans & Advances")*(Expenses_Log!B6:B5000=$C$5)*(Expenses_Log!G6:G5000))) | K27: =IF($C$5="All",SUMPRODUCT((MONTH(Expenses_Log!A6:A5000)=9)*(Expenses_Log!C6:C5000="Loans & Advances")*(Expenses_Log!G6:G5000)),SUMPRODUCT((MONTH(Expenses_Log!A6:A5000)=9)*(Expenses_Log!C6:C5000="Loans & Advances")*(Expenses_Log!B6:B5000=$C$5)*(Expenses_Log!G6:G5000))) | L27: =IF($C$5="All",SUMPRODUCT((MONTH(Expenses_Log!A6:A5000)=10)*(Expenses_Log!C6:C5000="Loans & Advances")*(Expenses_Log!G6:G5000)),SUMPRODUCT((MONTH(Expenses_Log!A6:A5000)=10)*(Expenses_Log!C6:C5000="Loans & Advances")*(Expenses_Log!B6:B5000=$C$5)*(Expenses_Log!G6:G5000))) | M27: =IF($C$5="All",SUMPRODUCT((MONTH(Expenses_Log!A6:A5000)=11)*(Expenses_Log!C6:C5000="Loans & Advances")*(Expenses_Log!G6:G5000)),SUMPRODUCT((MONTH(Expenses_Log!A6:A5000)=11)*(Expenses_Log!C6:C5000="Loans & Advances")*(Expenses_Log!B6:B5000=$C$5)*(Expenses_Log!G6:G5000))) | N27: =IF($C$5="All",SUMPRODUCT((MONTH(Expenses_Log!A6:A5000)=12)*(Expenses_Log!C6:C5000="Loans & Advances")*(Expenses_Log!G6:G5000)),SUMPRODUCT((MONTH(Expenses_Log!A6:A5000)=12)*(Expenses_Log!C6:C5000="Loans & Advances")*(Expenses_Log!B6:B5000=$C$5)*(Expenses_Log!G6:G5000))) | O27: =SUM(C27:N27)
B28: Transportation | C28: =IF($C$5="All",SUMPRODUCT((MONTH(Expenses_Log!A6:A5000)=1)*(Expenses_Log!C6:C5000="Transportation")*(Expenses_Log!G6:G5000)),SUMPRODUCT((MONTH(Expenses_Log!A6:A5000)=1)*(Expenses_Log!C6:C5000="Transportation")*(Expenses_Log!B6:B5000=$C$5)*(Expenses_Log!G6:G5000))) | D28: =IF($C$5="All",SUMPRODUCT((MONTH(Expenses_Log!A6:A5000)=2)*(Expenses_Log!C6:C5000="Transportation")*(Expenses_Log!G6:G5000)),SUMPRODUCT((MONTH(Expenses_Log!A6:A5000)=2)*(Expenses_Log!C6:C5000="Transportation")*(Expenses_Log!B6:B5000=$C$5)*(Expenses_Log!G6:G5000))) | E28: =IF($C$5="All",SUMPRODUCT((MONTH(Expenses_Log!A6:A5000)=3)*(Expenses_Log!C6:C5000="Transportation")*(Expenses_Log!G6:G5000)),SUMPRODUCT((MONTH(Expenses_Log!A6:A5000)=3)*(Expenses_Log!C6:C5000="Transportation")*(Expenses_Log!B6:B5000=$C$5)*(Expenses_Log!G6:G5000))) | F28: =IF($C$5="All",SUMPRODUCT((MONTH(Expenses_Log!A6:A5000)=4)*(Expenses_Log!C6:C5000="Transportation")*(Expenses_Log!G6:G5000)),SUMPRODUCT((MONTH(Expenses_Log!A6:A5000)=4)*(Expenses_Log!C6:C5000="Transportation")*(Expenses_Log!B6:B5000=$C$5)*(Expenses_Log!G6:G5000))) | G28: =IF($C$5="All",SUMPRODUCT((MONTH(Expenses_Log!A6:A5000)=5)*(Expenses_Log!C6:C5000="Transportation")*(Expenses_Log!G6:G5000)),SUMPRODUCT((MONTH(Expenses_Log!A6:A5000)=5)*(Expenses_Log!C6:C5000="Transportation")*(Expenses_Log!B6:B5000=$C$5)*(Expenses_Log!G6:G5000))) | H28: =IF($C$5="All",SUMPRODUCT((MONTH(Expenses_Log!A6:A5000)=6)*(Expenses_Log!C6:C5000="Transportation")*(Expenses_Log!G6:G5000)),SUMPRODUCT((MONTH(Expenses_Log!A6:A5000)=6)*(Expenses_Log!C6:C5000="Transportation")*(Expenses_Log!B6:B5000=$C$5)*(Expenses_Log!G6:G5000))) | I28: =IF($C$5="All",SUMPRODUCT((MONTH(Expenses_Log!A6:A5000)=7)*(Expenses_Log!C6:C5000="Transportation")*(Expenses_Log!G6:G5000)),SUMPRODUCT((MONTH(Expenses_Log!A6:A5000)=7)*(Expenses_Log!C6:C5000="Transportation")*(Expenses_Log!B6:B5000=$C$5)*(Expenses_Log!G6:G5000))) | J28: =IF($C$5="All",SUMPRODUCT((MONTH(Expenses_Log!A6:A5000)=8)*(Expenses_Log!C6:C5000="Transportation")*(Expenses_Log!G6:G5000)),SUMPRODUCT((MONTH(Expenses_Log!A6:A5000)=8)*(Expenses_Log!C6:C5000="Transportation")*(Expenses_Log!B6:B5000=$C$5)*(Expenses_Log!G6:G5000))) | K28: =IF($C$5="All",SUMPRODUCT((MONTH(Expenses_Log!A6:A5000)=9)*(Expenses_Log!C6:C5000="Transportation")*(Expenses_Log!G6:G5000)),SUMPRODUCT((MONTH(Expenses_Log!A6:A5000)=9)*(Expenses_Log!C6:C5000="Transportation")*(Expenses_Log!B6:B5000=$C$5)*(Expenses_Log!G6:G5000))) | L28: =IF($C$5="All",SUMPRODUCT((MONTH(Expenses_Log!A6:A5000)=10)*(Expenses_Log!C6:C5000="Transportation")*(Expenses_Log!G6:G5000)),SUMPRODUCT((MONTH(Expenses_Log!A6:A5000)=10)*(Expenses_Log!C6:C5000="Transportation")*(Expenses_Log!B6:B5000=$C$5)*(Expenses_Log!G6:G5000))) | M28: =IF($C$5="All",SUMPRODUCT((MONTH(Expenses_Log!A6:A5000)=11)*(Expenses_Log!C6:C5000="Transportation")*(Expenses_Log!G6:G5000)),SUMPRODUCT((MONTH(Expenses_Log!A6:A5000)=11)*(Expenses_Log!C6:C5000="Transportation")*(Expenses_Log!B6:B5000=$C$5)*(Expenses_Log!G6:G5000))) | N28: =IF($C$5="All",SUMPRODUCT((MONTH(Expenses_Log!A6:A5000)=12)*(Expenses_Log!C6:C5000="Transportation")*(Expenses_Log!G6:G5000)),SUMPRODUCT((MONTH(Expenses_Log!A6:A5000)=12)*(Expenses_Log!C6:C5000="Transportation")*(Expenses_Log!B6:B5000=$C$5)*(Expenses_Log!G6:G5000))) | O28: =SUM(C28:N28)
B29: IT & Communications | C29: =IF($C$5="All",SUMPRODUCT((MONTH(Expenses_Log!A6:A5000)=1)*(Expenses_Log!C6:C5000="IT & Communications")*(Expenses_Log!G6:G5000)),SUMPRODUCT((MONTH(Expenses_Log!A6:A5000)=1)*(Expenses_Log!C6:C5000="IT & Communications")*(Expenses_Log!B6:B5000=$C$5)*(Expenses_Log!G6:G5000))) | D29: =IF($C$5="All",SUMPRODUCT((MONTH(Expenses_Log!A6:A5000)=2)*(Expenses_Log!C6:C5000="IT & Communications")*(Expenses_Log!G6:G5000)),SUMPRODUCT((MONTH(Expenses_Log!A6:A5000)=2)*(Expenses_Log!C6:C5000="IT & Communications")*(Expenses_Log!B6:B5000=$C$5)*(Expenses_Log!G6:G5000))) | E29: =IF($C$5="All",SUMPRODUCT((MONTH(Expenses_Log!A6:A5000)=3)*(Expenses_Log!C6:C5000="IT & Communications")*(Expenses_Log!G6:G5000)),SUMPRODUCT((MONTH(Expenses_Log!A6:A5000)=3)*(Expenses_Log!C6:C5000="IT & Communications")*(Expenses_Log!B6:B5000=$C$5)*(Expenses_Log!G6:G5000))) | F29: =IF($C$5="All",SUMPRODUCT((MONTH(Expenses_Log!A6:A5000)=4)*(Expenses_Log!C6:C5000="IT & Communications")*(Expenses_Log!G6:G5000)),SUMPRODUCT((MONTH(Expenses_Log!A6:A5000)=4)*(Expenses_Log!C6:C5000="IT & Communications")*(Expenses_Log!B6:B5000=$C$5)*(Expenses_Log!G6:G5000))) | G29: =IF($C$5="All",SUMPRODUCT((MONTH(Expenses_Log!A6:A5000)=5)*(Expenses_Log!C6:C5000="IT & Communications")*(Expenses_Log!G6:G5000)),SUMPRODUCT((MONTH(Expenses_Log!A6:A5000)=5)*(Expenses_Log!C6:C5000="IT & Communications")*(Expenses_Log!B6:B5000=$C$5)*(Expenses_Log!G6:G5000))) | H29: =IF($C$5="All",SUMPRODUCT((MONTH(Expenses_Log!A6:A5000)=6)*(Expenses_Log!C6:C5000="IT & Communications")*(Expenses_Log!G6:G5000)),SUMPRODUCT((MONTH(Expenses_Log!A6:A5000)=6)*(Expenses_Log!C6:C5000="IT & Communications")*(Expenses_Log!B6:B5000=$C$5)*(Expenses_Log!G6:G5000))) | I29: =IF($C$5="All",SUMPRODUCT((MONTH(Expenses_Log!A6:A5000)=7)*(Expenses_Log!C6:C5000="IT & Communications")*(Expenses_Log!G6:G5000)),SUMPRODUCT((MONTH(Expenses_Log!A6:A5000)=7)*(Expenses_Log!C6:C5000="IT & Communications")*(Expenses_Log!B6:B5000=$C$5)*(Expenses_Log!G6:G5000))) | J29: =IF($C$5="All",SUMPRODUCT((MONTH(Expenses_Log!A6:A5000)=8)*(Expenses_Log!C6:C5000="IT & Communications")*(Expenses_Log!G6:G5000)),SUMPRODUCT((MONTH(Expenses_Log!A6:A5000)=8)*(Expenses_Log!C6:C5000="IT & Communications")*(Expenses_Log!B6:B5000=$C$5)*(Expenses_Log!G6:G5000))) | K29: =IF($C$5="All",SUMPRODUCT((MONTH(Expenses_Log!A6:A5000)=9)*(Expenses_Log!C6:C5000="IT & Communications")*(Expenses_Log!G6:G5000)),SUMPRODUCT((MONTH(Expenses_Log!A6:A5000)=9)*(Expenses_Log!C6:C5000="IT & Communications")*(Expenses_Log!B6:B5000=$C$5)*(Expenses_Log!G6:G5000))) | L29: =IF($C$5="All",SUMPRODUCT((MONTH(Expenses_Log!A6:A5000)=10)*(Expenses_Log!C6:C5000="IT & Communications")*(Expenses_Log!G6:G5000)),SUMPRODUCT((MONTH(Expenses_Log!A6:A5000)=10)*(Expenses_Log!C6:C5000="IT & Communications")*(Expenses_Log!B6:B5000=$C$5)*(Expenses_Log!G6:G5000))) | M29: =IF($C$5="All",SUMPRODUCT((MONTH(Expenses_Log!A6:A5000)=11)*(Expenses_Log!C6:C5000="IT & Communications")*(Expenses_Log!G6:G5000)),SUMPRODUCT((MONTH(Expenses_Log!A6:A5000)=11)*(Expenses_Log!C6:C5000="IT & Communications")*(Expenses_Log!B6:B5000=$C$5)*(Expenses_Log!G6:G5000))) | N29: =IF($C$5="All",SUMPRODUCT((MONTH(Expenses_Log!A6:A5000)=12)*(Expenses_Log!C6:C5000="IT & Communications")*(Expenses_Log!G6:G5000)),SUMPRODUCT((MONTH(Expenses_Log!A6:A5000)=12)*(Expenses_Log!C6:C5000="IT & Communications")*(Expenses_Log!B6:B5000=$C$5)*(Expenses_Log!G6:G5000))) | O29: =SUM(C29:N29)
B30: Other | C30: =IF($C$5="All",SUMPRODUCT((MONTH(Expenses_Log!A6:A5000)=1)*(Expenses_Log!C6:C5000="Other")*(Expenses_Log!G6:G5000)),SUMPRODUCT((MONTH(Expenses_Log!A6:A5000)=1)*(Expenses_Log!C6:C5000="Other")*(Expenses_Log!B6:B5000=$C$5)*(Expenses_Log!G6:G5000))) | D30: =IF($C$5="All",SUMPRODUCT((MONTH(Expenses_Log!A6:A5000)=2)*(Expenses_Log!C6:C5000="Other")*(Expenses_Log!G6:G5000)),SUMPRODUCT((MONTH(Expenses_Log!A6:A5000)=2)*(Expenses_Log!C6:C5000="Other")*(Expenses_Log!B6:B5000=$C$5)*(Expenses_Log!G6:G5000))) | E30: =IF($C$5="All",SUMPRODUCT((MONTH(Expenses_Log!A6:A5000)=3)*(Expenses_Log!C6:C5000="Other")*(Expenses_Log!G6:G5000)),SUMPRODUCT((MONTH(Expenses_Log!A6:A5000)=3)*(Expenses_Log!C6:C5000="Other")*(Expenses_Log!B6:B5000=$C$5)*(Expenses_Log!G6:G5000))) | F30: =IF($C$5="All",SUMPRODUCT((MONTH(Expenses_Log!A6:A5000)=4)*(Expenses_Log!C6:C5000="Other")*(Expenses_Log!G6:G5000)),SUMPRODUCT((MONTH(Expenses_Log!A6:A5000)=4)*(Expenses_Log!C6:C5000="Other")*(Expenses_Log!B6:B5000=$C$5)*(Expenses_Log!G6:G5000))) | G30: =IF($C$5="All",SUMPRODUCT((MONTH(Expenses_Log!A6:A5000)=5)*(Expenses_Log!C6:C5000="Other")*(Expenses_Log!G6:G5000)),SUMPRODUCT((MONTH(Expenses_Log!A6:A5000)=5)*(Expenses_Log!C6:C5000="Other")*(Expenses_Log!B6:B5000=$C$5)*(Expenses_Log!G6:G5000))) | H30: =IF($C$5="All",SUMPRODUCT((MONTH(Expenses_Log!A6:A5000)=6)*(Expenses_Log!C6:C5000="Other")*(Expenses_Log!G6:G5000)),SUMPRODUCT((MONTH(Expenses_Log!A6:A5000)=6)*(Expenses_Log!C6:C5000="Other")*(Expenses_Log!B6:B5000=$C$5)*(Expenses_Log!G6:G5000))) | I30: =IF($C$5="All",SUMPRODUCT((MONTH(Expenses_Log!A6:A5000)=7)*(Expenses_Log!C6:C5000="Other")*(Expenses_Log!G6:G5000)),SUMPRODUCT((MONTH(Expenses_Log!A6:A5000)=7)*(Expenses_Log!C6:C5000="Other")*(Expenses_Log!B6:B5000=$C$5)*(Expenses_Log!G6:G5000))) | J30: =IF($C$5="All",SUMPRODUCT((MONTH(Expenses_Log!A6:A5000)=8)*(Expenses_Log!C6:C5000="Other")*(Expenses_Log!G6:G5000)),SUMPRODUCT((MONTH(Expenses_Log!A6:A5000)=8)*(Expenses_Log!C6:C5000="Other")*(Expenses_Log!B6:B5000=$C$5)*(Expenses_Log!G6:G5000))) | K30: =IF($C$5="All",SUMPRODUCT((MONTH(Expenses_Log!A6:A5000)=9)*(Expenses_Log!C6:C5000="Other")*(Expenses_Log!G6:G5000)),SUMPRODUCT((MONTH(Expenses_Log!A6:A5000)=9)*(Expenses_Log!C6:C5000="Other")*(Expenses_Log!B6:B5000=$C$5)*(Expenses_Log!G6:G5000))) | L30: =IF($C$5="All",SUMPRODUCT((MONTH(Expenses_Log!A6:A5000)=10)*(Expenses_Log!C6:C5000="Other")*(Expenses_Log!G6:G5000)),SUMPRODUCT((MONTH(Expenses_Log!A6:A5000)=10)*(Expenses_Log!C6:C5000="Other")*(Expenses_Log!B6:B5000=$C$5)*(Expenses_Log!G6:G5000))) | M30: =IF($C$5="All",SUMPRODUCT((MONTH(Expenses_Log!A6:A5000)=11)*(Expenses_Log!C6:C5000="Other")*(Expenses_Log!G6:G5000)),SUMPRODUCT((MONTH(Expenses_Log!A6:A5000)=11)*(Expenses_Log!C6:C5000="Other")*(Expenses_Log!B6:B5000=$C$5)*(Expenses_Log!G6:G5000))) | N30: =IF($C$5="All",SUMPRODUCT((MONTH(Expenses_Log!A6:A5000)=12)*(Expenses_Log!C6:C5000="Other")*(Expenses_Log!G6:G5000)),SUMPRODUCT((MONTH(Expenses_Log!A6:A5000)=12)*(Expenses_Log!C6:C5000="Other")*(Expenses_Log!B6:B5000=$C$5)*(Expenses_Log!G6:G5000))) | O30: =SUM(C30:N30)
B31: TOTAL EXPENSES | C31: =SUM(C21:C30) | D31: =SUM(D21:D30) | E31: =SUM(E21:E30) | F31: =SUM(F21:F30) | G31: =SUM(G21:G30) | H31: =SUM(H21:H30) | I31: =SUM(I21:I30) | J31: =SUM(J21:J30) | ... O31: =SUM(O21:O30)
B32: NET PROFIT | C32: =C19-C31 | D32: =D19-D31 | E32: =E19-E31 | F32: =F19-F31 | G32: =G19-G31 | H32: =H19-H31 | I32: =I19-I31 | J32: =J19-J31 | ... O32: =O19-O31
B34: REVENUE BY LOCATION | F34: SALARY SUMMARY | J34: BUDGET STATUS
B35: =IF(Dropdown_Lists!$A$4<>"",Dropdown_Lists!$A$4,"") | C35: =IF(B35="","",SUMIF(Revenue_Log!B6:B5000,B35,Revenue_Log!H6:H5000)) | F35: Annual Payroll | G35: =Staff_Salaries!E4 | J35: Rev Variance | K35: =Budget!AN15-Budget!AM15
B36: =IF(Dropdown_Lists!$A$5<>"",Dropdown_Lists!$A$5,"") | C36: =IF(B36="","",SUMIF(Revenue_Log!B6:B5000,B36,Revenue_Log!H6:H5000)) | F36: Avg Monthly | G36: =IFERROR(Staff_Salaries!E4/COUNTA(Staff_Salaries!B6:B5000),0) | J36: Exp Variance | K36: =Budget!AM28-Budget!AN28
B37: TOTAL | C37: =SUMPRODUCT((YEAR(Revenue_Log!A6:A5000)=Dashboard!$B$1)*(Revenue_Log!H6:H5000))

Sheet Analysis
B2: Financial Analysis
B3: Interactive charts with location filter
B5: FILTER: | C5: All
B7: Monthly Data
C8: Jan | D8: Feb | E8: Mar | F8: Apr | G8: May | H8: Jun | I8: Jul | J8: Aug | K8: Sep | L8: Oct | M8: Nov | N8: Dec
B9: Revenue | C9: =IF($C$5="All",SUMPRODUCT((MONTH(Revenue_Log!A6:A5000)=1)*(Revenue_Log!H6:H5000)),SUMPRODUCT((MONTH(Revenue_Log!A6:A5000)=1)*(Revenue_Log!B6:B5000=$C$5)*(Revenue_Log!H6:H5000))) | D9: =IF($C$5="All",SUMPRODUCT((MONTH(Revenue_Log!A6:A5000)=2)*(Revenue_Log!H6:H5000)),SUMPRODUCT((MONTH(Revenue_Log!A6:A5000)=2)*(Revenue_Log!B6:B5000=$C$5)*(Revenue_Log!H6:H5000))) | E9: =IF($C$5="All",SUMPRODUCT((MONTH(Revenue_Log!A6:A5000)=3)*(Revenue_Log!H6:H5000)),SUMPRODUCT((MONTH(Revenue_Log!A6:A5000)=3)*(Revenue_Log!B6:B5000=$C$5)*(Revenue_Log!H6:H5000))) | F9: =IF($C$5="All",SUMPRODUCT((MONTH(Revenue_Log!A6:A5000)=4)*(Revenue_Log!H6:H5000)),SUMPRODUCT((MONTH(Revenue_Log!A6:A5000)=4)*(Revenue_Log!B6:B5000=$C$5)*(Revenue_Log!H6:H5000))) | G9: =IF($C$5="All",SUMPRODUCT((MONTH(Revenue_Log!A6:A5000)=5)*(Revenue_Log!H6:H5000)),SUMPRODUCT((MONTH(Revenue_Log!A6:A5000)=5)*(Revenue_Log!B6:B5000=$C$5)*(Revenue_Log!H6:H5000))) | H9: =IF($C$5="All",SUMPRODUCT((MONTH(Revenue_Log!A6:A5000)=6)*(Revenue_Log!H6:H5000)),SUMPRODUCT((MONTH(Revenue_Log!A6:A5000)=6)*(Revenue_Log!B6:B5000=$C$5)*(Revenue_Log!H6:H5000))) | I9: =IF($C$5="All",SUMPRODUCT((MONTH(Revenue_Log!A6:A5000)=7)*(Revenue_Log!H6:H5000)),SUMPRODUCT((MONTH(Revenue_Log!A6:A5000)=7)*(Revenue_Log!B6:B5000=$C$5)*(Revenue_Log!H6:H5000))) | J9: =IF($C$5="All",SUMPRODUCT((MONTH(Revenue_Log!A6:A5000)=8)*(Revenue_Log!H6:H5000)),SUMPRODUCT((MONTH(Revenue_Log!A6:A5000)=8)*(Revenue_Log!B6:B5000=$C$5)*(Revenue_Log!H6:H5000))) | K9: =IF($C$5="All",SUMPRODUCT((MONTH(Revenue_Log!A6:A5000)=9)*(Revenue_Log!H6:H5000)),SUMPRODUCT((MONTH(Revenue_Log!A6:A5000)=9)*(Revenue_Log!B6:B5000=$C$5)*(Revenue_Log!H6:H5000))) | L9: =IF($C$5="All",SUMPRODUCT((MONTH(Revenue_Log!A6:A5000)=10)*(Revenue_Log!H6:H5000)),SUMPRODUCT((MONTH(Revenue_Log!A6:A5000)=10)*(Revenue_Log!B6:B5000=$C$5)*(Revenue_Log!H6:H5000))) | M9: =IF($C$5="All",SUMPRODUCT((MONTH(Revenue_Log!A6:A5000)=11)*(Revenue_Log!H6:H5000)),SUMPRODUCT((MONTH(Revenue_Log!A6:A5000)=11)*(Revenue_Log!B6:B5000=$C$5)*(Revenue_Log!H6:H5000))) | N9: =IF($C$5="All",SUMPRODUCT((MONTH(Revenue_Log!A6:A5000)=12)*(Revenue_Log!H6:H5000)),SUMPRODUCT((MONTH(Revenue_Log!A6:A5000)=12)*(Revenue_Log!B6:B5000=$C$5)*(Revenue_Log!H6:H5000)))
B10: Expenses | C10: =IF($C$5="All",SUMPRODUCT((MONTH(Expenses_Log!A6:A5000)=1)*(Expenses_Log!G6:G5000)),SUMPRODUCT((MONTH(Expenses_Log!A6:A5000)=1)*(Expenses_Log!B6:B5000=$C$5)*(Expenses_Log!G6:G5000)))+SUMPRODUCT((Staff_Salaries!A6:A5000=Dashboard!$B$1)*(Staff_Salaries!B6:B5000="January")*(Staff_Salaries!E6:E5000)) | D10: =IF($C$5="All",SUMPRODUCT((MONTH(Expenses_Log!A6:A5000)=2)*(Expenses_Log!G6:G5000)),SUMPRODUCT((MONTH(Expenses_Log!A6:A5000)=2)*(Expenses_Log!B6:B5000=$C$5)*(Expenses_Log!G6:G5000)))+SUMPRODUCT((Staff_Salaries!A6:A5000=Dashboard!$B$1)*(Staff_Salaries!B6:B5000="February")*(Staff_Salaries!E6:E5000)) | E10: =IF($C$5="All",SUMPRODUCT((MONTH(Expenses_Log!A6:A5000)=3)*(Expenses_Log!G6:G5000)),SUMPRODUCT((MONTH(Expenses_Log!A6:A5000)=3)*(Expenses_Log!B6:B5000=$C$5)*(Expenses_Log!G6:G5000)))+SUMPRODUCT((Staff_Salaries!A6:A5000=Dashboard!$B$1)*(Staff_Salaries!B6:B5000="March")*(Staff_Salaries!E6:E5000)) | F10: =IF($C$5="All",SUMPRODUCT((MONTH(Expenses_Log!A6:A5000)=4)*(Expenses_Log!G6:G5000)),SUMPRODUCT((MONTH(Expenses_Log!A6:A5000)=4)*(Expenses_Log!B6:B5000=$C$5)*(Expenses_Log!G6:G5000)))+SUMPRODUCT((Staff_Salaries!A6:A5000=Dashboard!$B$1)*(Staff_Salaries!B6:B5000="April")*(Staff_Salaries!E6:E5000)) | G10: =IF($C$5="All",SUMPRODUCT((MONTH(Expenses_Log!A6:A5000)=5)*(Expenses_Log!G6:G5000)),SUMPRODUCT((MONTH(Expenses_Log!A6:A5000)=5)*(Expenses_Log!B6:B5000=$C$5)*(Expenses_Log!G6:G5000)))+SUMPRODUCT((Staff_Salaries!A6:A5000=Dashboard!$B$1)*(Staff_Salaries!B6:B5000="May")*(Staff_Salaries!E6:E5000)) | H10: =IF($C$5="All",SUMPRODUCT((MONTH(Expenses_Log!A6:A5000)=6)*(Expenses_Log!G6:G5000)),SUMPRODUCT((MONTH(Expenses_Log!A6:A5000)=6)*(Expenses_Log!B6:B5000=$C$5)*(Expenses_Log!G6:G5000)))+SUMPRODUCT((Staff_Salaries!A6:A5000=Dashboard!$B$1)*(Staff_Salaries!B6:B5000="June")*(Staff_Salaries!E6:E5000)) | I10: =IF($C$5="All",SUMPRODUCT((MONTH(Expenses_Log!A6:A5000)=7)*(Expenses_Log!G6:G5000)),SUMPRODUCT((MONTH(Expenses_Log!A6:A5000)=7)*(Expenses_Log!B6:B5000=$C$5)*(Expenses_Log!G6:G5000)))+SUMPRODUCT((Staff_Salaries!A6:A5000=Dashboard!$B$1)*(Staff_Salaries!B6:B5000="July")*(Staff_Salaries!E6:E5000)) | J10: =IF($C$5="All",SUMPRODUCT((MONTH(Expenses_Log!A6:A5000)=8)*(Expenses_Log!G6:G5000)),SUMPRODUCT((MONTH(Expenses_Log!A6:A5000)=8)*(Expenses_Log!B6:B5000=$C$5)*(Expenses_Log!G6:G5000)))+SUMPRODUCT((Staff_Salaries!A6:A5000=Dashboard!$B$1)*(Staff_Salaries!B6:B5000="August")*(Staff_Salaries!E6:E5000)) | K10: =IF($C$5="All",SUMPRODUCT((MONTH(Expenses_Log!A6:A5000)=9)*(Expenses_Log!G6:G5000)),SUMPRODUCT((MONTH(Expenses_Log!A6:A5000)=9)*(Expenses_Log!B6:B5000=$C$5)*(Expenses_Log!G6:G5000)))+SUMPRODUCT((Staff_Salaries!A6:A5000=Dashboard!$B$1)*(Staff_Salaries!B6:B5000="September")*(Staff_Salaries!E6:E5000)) | L10: =IF($C$5="All",SUMPRODUCT((MONTH(Expenses_Log!A6:A5000)=10)*(Expenses_Log!G6:G5000)),SUMPRODUCT((MONTH(Expenses_Log!A6:A5000)=10)*(Expenses_Log!B6:B5000=$C$5)*(Expenses_Log!G6:G5000)))+SUMPRODUCT((Staff_Salaries!A6:A5000=Dashboard!$B$1)*(Staff_Salaries!B6:B5000="October")*(Staff_Salaries!E6:E5000)) | M10: =IF($C$5="All",SUMPRODUCT((MONTH(Expenses_Log!A6:A5000)=11)*(Expenses_Log!G6:G5000)),SUMPRODUCT((MONTH(Expenses_Log!A6:A5000)=11)*(Expenses_Log!B6:B5000=$C$5)*(Expenses_Log!G6:G5000)))+SUMPRODUCT((Staff_Salaries!A6:A5000=Dashboard!$B$1)*(Staff_Salaries!B6:B5000="November")*(Staff_Salaries!E6:E5000)) | N10: =IF($C$5="All",SUMPRODUCT((MONTH(Expenses_Log!A6:A5000)=12)*(Expenses_Log!G6:G5000)),SUMPRODUCT((MONTH(Expenses_Log!A6:A5000)=12)*(Expenses_Log!B6:B5000=$C$5)*(Expenses_Log!G6:G5000)))+SUMPRODUCT((Staff_Salaries!A6:A5000=Dashboard!$B$1)*(Staff_Salaries!B6:B5000="December")*(Staff_Salaries!E6:E5000))
B11: Net Profit | C11: =C9-C10 | D11: =D9-D10 | E11: =E9-E10 | F11: =F9-F10 | G11: =G9-G10 | H11: =H9-H10 | I11: =I9-I10 | J11: =J9-J10 | ... N11: =N9-N10
B12: Staff Salary | C12: =SUMPRODUCT((Staff_Salaries!A6:A5000=Dashboard!$B$1)*(Staff_Salaries!B6:B5000="January")*(Staff_Salaries!E6:E5000)) | D12: =SUMPRODUCT((Staff_Salaries!A6:A5000=Dashboard!$B$1)*(Staff_Salaries!B6:B5000="February")*(Staff_Salaries!E6:E5000)) | E12: =SUMPRODUCT((Staff_Salaries!A6:A5000=Dashboard!$B$1)*(Staff_Salaries!B6:B5000="March")*(Staff_Salaries!E6:E5000)) | F12: =SUMPRODUCT((Staff_Salaries!A6:A5000=Dashboard!$B$1)*(Staff_Salaries!B6:B5000="April")*(Staff_Salaries!E6:E5000)) | G12: =SUMPRODUCT((Staff_Salaries!A6:A5000=Dashboard!$B$1)*(Staff_Salaries!B6:B5000="May")*(Staff_Salaries!E6:E5000)) | H12: =SUMPRODUCT((Staff_Salaries!A6:A5000=Dashboard!$B$1)*(Staff_Salaries!B6:B5000="June")*(Staff_Salaries!E6:E5000)) | I12: =SUMPRODUCT((Staff_Salaries!A6:A5000=Dashboard!$B$1)*(Staff_Salaries!B6:B5000="July")*(Staff_Salaries!E6:E5000)) | J12: =SUMPRODUCT((Staff_Salaries!A6:A5000=Dashboard!$B$1)*(Staff_Salaries!B6:B5000="August")*(Staff_Salaries!E6:E5000)) | K12: =SUMPRODUCT((Staff_Salaries!A6:A5000=Dashboard!$B$1)*(Staff_Salaries!B6:B5000="September")*(Staff_Salaries!E6:E5000)) | L12: =SUMPRODUCT((Staff_Salaries!A6:A5000=Dashboard!$B$1)*(Staff_Salaries!B6:B5000="October")*(Staff_Salaries!E6:E5000)) | M12: =SUMPRODUCT((Staff_Salaries!A6:A5000=Dashboard!$B$1)*(Staff_Salaries!B6:B5000="November")*(Staff_Salaries!E6:E5000)) | N12: =SUMPRODUCT((Staff_Salaries!A6:A5000=Dashboard!$B$1)*(Staff_Salaries!B6:B5000="December")*(Staff_Salaries!E6:E5000))
B13: Budget Rev | C13: =Budget!C15 | D13: =Budget!F15 | E13: =Budget!I15 | F13: =Budget!L15 | G13: =Budget!O15 | H13: =Budget!R15 | I13: =Budget!U15 | J13: =Budget!X15 | K13: =Budget!AA15 | L13: =Budget!AD15 | M13: =Budget!AG15 | N13: =Budget!AJ15
B14: Budget Exp | C14: =Budget!C28 | D14: =Budget!F28 | E14: =Budget!I28 | F14: =Budget!L28 | G14: =Budget!O28 | H14: =Budget!R28 | I14: =Budget!U28 | J14: =Budget!X28 | K14: =Budget!AA28 | L14: =Budget!AD28 | M14: =Budget!AG28 | N14: =Budget!AJ28
B17: REVENUE BY LOCATION
B18: =IF(Dropdown_Lists!$A$4<>"",Dropdown_Lists!$A$4,"") | C18: =IF(B18="","",SUMIF(Revenue_Log!B6:B5000,B18,Revenue_Log!H6:H5000))
B19: =IF(Dropdown_Lists!$A$5<>"",Dropdown_Lists!$A$5,"") | C19: =IF(B19="","",SUMIF(Revenue_Log!B6:B5000,B19,Revenue_Log!H6:H5000))
B20: TOTAL | C20: =SUMPRODUCT((YEAR(Revenue_Log!A6:A5000)=Dashboard!$B$1)*(Revenue_Log!H6:H5000))
B22: Expenses by Category
B23: Salaries | C23: =Staff_Salaries!E4
B24: Construction | C24: =IF($C$5="All",SUMIF(Expenses_Log!C6:C5000,"Construction",Expenses_Log!G6:G5000),SUMPRODUCT((Expenses_Log!C6:C5000="Construction")*(Expenses_Log!B6:B5000=$C$5)*(Expenses_Log!G6:G5000)))
B25: Maintenance | C25: =IF($C$5="All",SUMIF(Expenses_Log!C6:C5000,"Maintenance",Expenses_Log!G6:G5000),SUMPRODUCT((Expenses_Log!C6:C5000="Maintenance")*(Expenses_Log!B6:B5000=$C$5)*(Expenses_Log!G6:G5000)))
B26: Utilities | C26: =IF($C$5="All",SUMIF(Expenses_Log!C6:C5000,"Utilities",Expenses_Log!G6:G5000),SUMPRODUCT((Expenses_Log!C6:C5000="Utilities")*(Expenses_Log!B6:B5000=$C$5)*(Expenses_Log!G6:G5000)))
B27: Inventory | C27: =IF($C$5="All",SUMIF(Expenses_Log!C6:C5000,"Inventory",Expenses_Log!G6:G5000),SUMPRODUCT((Expenses_Log!C6:C5000="Inventory")*(Expenses_Log!B6:B5000=$C$5)*(Expenses_Log!G6:G5000)))
B28: Administrative | C28: =IF($C$5="All",SUMIF(Expenses_Log!C6:C5000,"Administrative",Expenses_Log!G6:G5000),SUMPRODUCT((Expenses_Log!C6:C5000="Administrative")*(Expenses_Log!B6:B5000=$C$5)*(Expenses_Log!G6:G5000)))
B29: Loans & Advances | C29: =IF($C$5="All",SUMIF(Expenses_Log!C6:C5000,"Loans & Advances",Expenses_Log!G6:G5000),SUMPRODUCT((Expenses_Log!C6:C5000="Loans & Advances")*(Expenses_Log!B6:B5000=$C$5)*(Expenses_Log!G6:G5000)))
B30: Transportation | C30: =IF($C$5="All",SUMIF(Expenses_Log!C6:C5000,"Transportation",Expenses_Log!G6:G5000),SUMPRODUCT((Expenses_Log!C6:C5000="Transportation")*(Expenses_Log!B6:B5000=$C$5)*(Expenses_Log!G6:G5000)))
B31: IT & Communications | C31: =IF($C$5="All",SUMIF(Expenses_Log!C6:C5000,"IT & Communications",Expenses_Log!G6:G5000),SUMPRODUCT((Expenses_Log!C6:C5000="IT & Communications")*(Expenses_Log!B6:B5000=$C$5)*(Expenses_Log!G6:G5000)))
B32: Other | C32: =IF($C$5="All",SUMIF(Expenses_Log!C6:C5000,"Other",Expenses_Log!G6:G5000),SUMPRODUCT((Expenses_Log!C6:C5000="Other")*(Expenses_Log!B6:B5000=$C$5)*(Expenses_Log!G6:G5000)))

Sheet General_Ledger
B2: General Ledger
B3: Double-entry records
A5: Date | B5: Location | C5: Txn Ref | D5: Acct Code | E5: Account Name | F5: Description | G5: Debit | H5: Credit | I5: Balance | J5: Bank Ref / Notes
A6: 45299 | B6: Agbowo | C6: R0001 | D6: 1010 | E6: Bank Account | F6: Received: Booking - Anooore 1 | G6: 196558 | H6: 0 | I6: =IFERROR(SUMIF(A$6:A6,"<>""",G$6:G6)-SUMIF(A$6:A6,"<>""",H$6:H6),"")
A7: 45299 | B7: Agbowo | C7: R0001 | D7: 4000 | E7: Room Revenue | F7: Booking - Anooore 1 | G7: 0 | H7: 196558 | I7: =IFERROR(SUMIF(A$6:A7,"<>""",G$6:G7)-SUMIF(A$6:A7,"<>""",H$6:H7),"")
A8: 45299 | B8: Agbowo | C8: R0002 | D8: 1010 | E8: Bank Account | F8: Received: TV rental | G8: 10000 | H8: 0 | I8: =IFERROR(SUMIF(A$6:A8,"<>""",G$6:G8)-SUMIF(A$6:A8,"<>""",H$6:H8),"")
A9: 45299 | B9: Agbowo | C9: R0002 | D9: 4030 | E9: Extra Charges | F9: TV rental | G9: 0 | H9: 10000 | I9: =IFERROR(SUMIF(A$6:A9,"<>""",G$6:G9)-SUMIF(A$6:A9,"<>""",H$6:H9),"")
A10: 45308 | B10: Agbowo | C10: R0003 | D10: 1010 | E10: Bank Account | F10: Received: Booking - Vine 1 | G10: 176948 | H10: 0 | I10: =IFERROR(SUMIF(A$6:A10,"<>""",G$6:G10)-SUMIF(A$6:A10,"<>""",H$6:H10),"")
A11: 45308 | B11: Agbowo | C11: R0003 | D11: 4000 | E11: Room Revenue | F11: Booking - Vine 1 | G11: 0 | H11: 176948 | I11: =IFERROR(SUMIF(A$6:A11,"<>""",G$6:G11)-SUMIF(A$6:A11,"<>""",H$6:H11),"")
A12: 45310 | B12: Agbowo | C12: R0004 | D12: 1010 | E12: Bank Account | F12: Received: Booking - Vine 2 | G12: 354033 | H12: 0 | I12: =IFERROR(SUMIF(A$6:A12,"<>""",G$6:G12)-SUMIF(A$6:A12,"<>""",H$6:H12),"")
A13: 45310 | B13: Agbowo | C13: R0004 | D13: 4000 | E13: Room Revenue | F13: Booking - Vine 2 | G13: 0 | H13: 354033 | I13: =IFERROR(SUMIF(A$6:A13,"<>""",G$6:G13)-SUMIF(A$6:A13,"<>""",H$6:H13),"")
A14: 45310 | B14: Agbowo | C14: R0005 | D14: 1010 | E14: Bank Account | F14: Received: Registration form fee | G14: 5000 | H14: 0 | I14: =IFERROR(SUMIF(A$6:A14,"<>""",G$6:G14)-SUMIF(A$6:A14,"<>""",H$6:H14),"")
A15: 45310 | B15: Agbowo | C15: R0005 | D15: 4040 | E15: Form & Legal Fees | F15: Registration form fee | G15: 0 | H15: 5000 | I15: =IFERROR(SUMIF(A$6:A15,"<>""",G$6:G15)-SUMIF(A$6:A15,"<>""",H$6:H15),"")
A16: 45298 | B16: Agbowo | C16: R0006 | D16: 1010 | E16: Bank Account | F16: Received: Booking - Provision Shop | G16: 298616 | H16: 0 | I16: =IFERROR(SUMIF(A$6:A16,"<>""",G$6:G16)-SUMIF(A$6:A16,"<>""",H$6:H16),"")
A17: 45298 | B17: Agbowo | C17: R0006 | D17: 4000 | E17: Room Revenue | F17: Booking - Provision Shop | G17: 0 | H17: 298616 | I17: =IFERROR(SUMIF(A$6:A17,"<>""",G$6:G17)-SUMIF(A$6:A17,"<>""",H$6:H17),"")
... A35: 45302 | B35: UI | C35: R0015 | D35: 4030 | E35: Extra Charges | F35: Generator surcharge | G35: 0 | H35: 10000 | I35: =IFERROR(SUMIF(A$6:A35,"<>""",G$6:G35)-SUMIF(A$6:A35,"<>""",H$6:H35),"")
I36: =IFERROR(SUMIF(A$6:A36,"<>""",G$6:G36)-SUMIF(A$6:A36,"<>""",H$6:H36),"")
I37: =IFERROR(SUMIF(A$6:A37,"<>""",G$6:G37)-SUMIF(A$6:A37,"<>""",H$6:H37),"")
I38: =IFERROR(SUMIF(A$6:A38,"<>""",G$6:G38)-SUMIF(A$6:A38,"<>""",H$6:H38),"")
I39: =IFERROR(SUMIF(A$6:A39,"<>""",G$6:G39)-SUMIF(A$6:A39,"<>""",H$6:H39),"")
I40: =IFERROR(SUMIF(A$6:A40,"<>""",G$6:G40)-SUMIF(A$6:A40,"<>""",H$6:H40),"")
I41: =IFERROR(SUMIF(A$6:A41,"<>""",G$6:G41)-SUMIF(A$6:A41,"<>""",H$6:H41),"")
I42: =IFERROR(SUMIF(A$6:A42,"<>""",G$6:G42)-SUMIF(A$6:A42,"<>""",H$6:H42),"")
I43: =IFERROR(SUMIF(A$6:A43,"<>""",G$6:G43)-SUMIF(A$6:A43,"<>""",H$6:H43),"")
I44: =IFERROR(SUMIF(A$6:A44,"<>""",G$6:G44)-SUMIF(A$6:A44,"<>""",H$6:H44),"")
I45: =IFERROR(SUMIF(A$6:A45,"<>""",G$6:G45)-SUMIF(A$6:A45,"<>""",H$6:H45),"")
I46: =IFERROR(SUMIF(A$6:A46,"<>""",G$6:G46)-SUMIF(A$6:A46,"<>""",H$6:H46),"")
I47: =IFERROR(SUMIF(A$6:A47,"<>""",G$6:G47)-SUMIF(A$6:A47,"<>""",H$6:H47),"")
... I5000: =IFERROR(SUMIF(A$6:A5000,"<>""",G$6:G5000)-SUMIF(A$6:A5000,"<>""",H$6:H5000),"")

Sheet Profit_Loss
B2: Profit & Loss Statement
B3: ="FY "&Dashboard!$B$1
D5: Actual | E5: Budget
B6: REVENUE
C7: Room Revenue | D7: =SUMPRODUCT((YEAR(Revenue_Log!A6:A5000)=Dashboard!$B$1)*(Revenue_Log!D6:D5000="Room Revenue")*(Revenue_Log!H6:H5000)) | E7: =Budget!AM9
C8: Shop Rent | D8: =SUMPRODUCT((YEAR(Revenue_Log!A6:A5000)=Dashboard!$B$1)*(Revenue_Log!D6:D5000="Shop Rent")*(Revenue_Log!H6:H5000)) | E8: =Budget!AM10
C9: Caution Fee Income | D9: =SUMPRODUCT((YEAR(Revenue_Log!A6:A5000)=Dashboard!$B$1)*(Revenue_Log!D6:D5000="Caution Fee Income")*(Revenue_Log!H6:H5000)) | E9: =Budget!AM11
C10: Extra Charges | D10: =SUMPRODUCT((YEAR(Revenue_Log!A6:A5000)=Dashboard!$B$1)*(Revenue_Log!D6:D5000="Extra Charges")*(Revenue_Log!H6:H5000)) | E10: =Budget!AM12
C11: Form & Legal Fees | D11: =SUMPRODUCT((YEAR(Revenue_Log!A6:A5000)=Dashboard!$B$1)*(Revenue_Log!D6:D5000="Form & Legal Fees")*(Revenue_Log!H6:H5000)) | E11: =Budget!AM13
C12: Other Income | D12: =SUMPRODUCT((YEAR(Revenue_Log!A6:A5000)=Dashboard!$B$1)*(Revenue_Log!D6:D5000="Other Income")*(Revenue_Log!H6:H5000)) | E12: =Budget!AM14
B13: TOTAL REVENUE | D13: =SUM(D7:D12) | E13: =SUM(E7:E12)
B15: EXPENSES
C16: Salaries | D16: =Staff_Salaries!E4 | E16: =Budget!AM18
C17: Construction | D17: =SUMPRODUCT((YEAR(Expenses_Log!A6:A5000)=Dashboard!$B$1)*(Expenses_Log!C6:C5000="Construction")*(Expenses_Log!G6:G5000)) | E17: =Budget!AM19
C18: Maintenance | D18: =SUMPRODUCT((YEAR(Expenses_Log!A6:A5000)=Dashboard!$B$1)*(Expenses_Log!C6:C5000="Maintenance")*(Expenses_Log!G6:G5000)) | E18: =Budget!AM20
C19: Utilities | D19: =SUMPRODUCT((YEAR(Expenses_Log!A6:A5000)=Dashboard!$B$1)*(Expenses_Log!C6:C5000="Utilities")*(Expenses_Log!G6:G5000)) | E19: =Budget!AM21
C20: Inventory | D20: =SUMPRODUCT((YEAR(Expenses_Log!A6:A5000)=Dashboard!$B$1)*(Expenses_Log!C6:C5000="Inventory")*(Expenses_Log!G6:G5000)) | E20: =Budget!AM22
C21: Administrative | D21: =SUMPRODUCT((YEAR(Expenses_Log!A6:A5000)=Dashboard!$B$1)*(Expenses_Log!C6:C5000="Administrative")*(Expenses_Log!G6:G5000)) | E21: =Budget!AM23
C22: Loans & Advances | D22: =SUMPRODUCT((YEAR(Expenses_Log!A6:A5000)=Dashboard!$B$1)*(Expenses_Log!C6:C5000="Loans & Advances")*(Expenses_Log!G6:G5000)) | E22: =Budget!AM24
C23: Transportation | D23: =SUMPRODUCT((YEAR(Expenses_Log!A6:A5000)=Dashboard!$B$1)*(Expenses_Log!C6:C5000="Transportation")*(Expenses_Log!G6:G5000)) | E23: =Budget!AM25
C24: IT & Communications | D24: =SUMPRODUCT((YEAR(Expenses_Log!A6:A5000)=Dashboard!$B$1)*(Expenses_Log!C6:C5000="IT & Communications")*(Expenses_Log!G6:G5000)) | E24: =Budget!AM26
C25: Other | D25: =SUMPRODUCT((YEAR(Expenses_Log!A6:A5000)=Dashboard!$B$1)*(Expenses_Log!C6:C5000="Other")*(Expenses_Log!G6:G5000)) | E25: =Budget!AM27
B26: TOTAL EXPENSES | D26: =SUM(D16:D25) | E26: =SUM(E16:E25)
B28: NET PROFIT / (LOSS) | D28: =D13-D26 | E28: =E13-E26

Sheet Cash_Flow
B2: Cash Flow Statement
B3: ="FY "&Dashboard!$B$1
B6: OPERATING
C7: Cash from revenue | D7: =SUMPRODUCT((YEAR(Revenue_Log!A6:A5000)=Dashboard!$B$1)*(Revenue_Log!H6:H5000))
C8: Cash paid (expenses) | D8: =-(SUMPRODUCT((YEAR(Expenses_Log!A6:A5000)=Dashboard!$B$1)*(Expenses_Log!G6:G5000)))
C9: Cash paid (salaries) | D9: =-Staff_Salaries!E4
B10: Net Operating | D10: =SUM(D7:D9)
B12: INVESTING
C13: Capital expenditures | D13: =-(SUMPRODUCT((YEAR(Expenses_Log!A6:A5000)=Dashboard!$B$1)*(Expenses_Log!C6:C5000="Construction")*(Expenses_Log!G6:G5000)))
B15: FINANCING
C16: Owner contributions | D16: 0
C17: Loan repayments | D17: =-(SUMPRODUCT((YEAR(Expenses_Log!A6:A5000)=Dashboard!$B$1)*(Expenses_Log!C6:C5000="Loans & Advances")*(Expenses_Log!G6:G5000)))
B19: NET CASH CHANGE | D19: =IFERROR(D10,0)+IFERROR(D13,0)+IFERROR(D16,0)+IFERROR(D17,0)

Sheet Balance_Sheet
B2: Balance Sheet
B3: ="As at Dec 31, "&Dashboard!$B$1
B6: ASSETS
B7: Current Assets
C8: Cash & Bank | D8: =Cash_Flow!D19
C9: Accounts Receivable | D9: =0
C10: Inventory | D10: =0
B11: Total Current | D11: =SUM(D8:D10)
C12: Fixed Assets | D12: 0
B13: TOTAL ASSETS | D13: =D11+D12
B15: LIABILITIES
C16: Accounts Payable | D16: 0
C17: Salaries Payable | D17: 0
C18: Loans Payable | D18: 0
C19: Caution Deposits | D19: 0
B20: Total Liabilities | D20: =SUM(D16:D19)
B22: EQUITY
C23: Owner Capital | D23: 0
C24: Retained Earnings | D24: =Profit_Loss!D28
B25: Total Equity | D25: =D23+D24
B27: TOTAL L+E | D27: =D20+D25
B28: Check (=0): | D28: =D13-D27

Sheet Trial_Balance
B2: Trial Balance
B3: FY 2024
B5: Code | C5: Account | D5: Type | E5: Debit | F5: Credit
B6: 1010 | C6: Bank | D6: Asset | E6: =IFERROR(SUMIF(General_Ledger!D6:D5000,"1010",General_Ledger!G6:G5000),0) | F6: =IFERROR(SUMIF(General_Ledger!D6:D5000,"1010",General_Ledger!H6:H5000),0)
B7: 1100 | C7: AR | D7: Asset | E7: =IFERROR(SUMIF(General_Ledger!D6:D5000,"1100",General_Ledger!G6:G5000),0) | F7: =IFERROR(SUMIF(General_Ledger!D6:D5000,"1100",General_Ledger!H6:H5000),0)
B8: 2000 | C8: AP | D8: Liability | E8: =IFERROR(SUMIF(General_Ledger!D6:D5000,"2000",General_Ledger!G6:G5000),0) | F8: =IFERROR(SUMIF(General_Ledger!D6:D5000,"2000",General_Ledger!H6:H5000),0)
B9: 2200 | C9: Loans | D9: Liability | E9: =IFERROR(SUMIF(General_Ledger!D6:D5000,"2200",General_Ledger!G6:G5000),0) | F9: =IFERROR(SUMIF(General_Ledger!D6:D5000,"2200",General_Ledger!H6:H5000),0)
B10: 3000 | C10: Equity | D10: Equity | E10: =IFERROR(SUMIF(General_Ledger!D6:D5000,"3000",General_Ledger!G6:G5000),0) | F10: =IFERROR(SUMIF(General_Ledger!D6:D5000,"3000",General_Ledger!H6:H5000),0)
B11: 4000 | C11: Room Rev | D11: Revenue | E11: =IFERROR(SUMIF(General_Ledger!D6:D5000,"4000",General_Ledger!G6:G5000),0) | F11: =IFERROR(SUMIF(General_Ledger!D6:D5000,"4000",General_Ledger!H6:H5000),0)
B12: 4010 | C12: Shop Rent | D12: Revenue | E12: =IFERROR(SUMIF(General_Ledger!D6:D5000,"4010",General_Ledger!G6:G5000),0) | F12: =IFERROR(SUMIF(General_Ledger!D6:D5000,"4010",General_Ledger!H6:H5000),0)
B13: 4030 | C13: Extras | D13: Revenue | E13: =IFERROR(SUMIF(General_Ledger!D6:D5000,"4030",General_Ledger!G6:G5000),0) | F13: =IFERROR(SUMIF(General_Ledger!D6:D5000,"4030",General_Ledger!H6:H5000),0)
B14: 5000 | C14: Salaries | D14: Expense | E14: =IFERROR(SUMIF(General_Ledger!D6:D5000,"5000",General_Ledger!G6:G5000),0) | F14: =IFERROR(SUMIF(General_Ledger!D6:D5000,"5000",General_Ledger!H6:H5000),0)
B15: 5010 | C15: Construction | D15: Expense | E15: =IFERROR(SUMIF(General_Ledger!D6:D5000,"5010",General_Ledger!G6:G5000),0) | F15: =IFERROR(SUMIF(General_Ledger!D6:D5000,"5010",General_Ledger!H6:H5000),0)
B16: 5020 | C16: Maintenance | D16: Expense | E16: =IFERROR(SUMIF(General_Ledger!D6:D5000,"5020",General_Ledger!G6:G5000),0) | F16: =IFERROR(SUMIF(General_Ledger!D6:D5000,"5020",General_Ledger!H6:H5000),0)
B17: 5030 | C17: Utilities | D17: Expense | E17: =IFERROR(SUMIF(General_Ledger!D6:D5000,"5030",General_Ledger!G6:G5000),0) | F17: =IFERROR(SUMIF(General_Ledger!D6:D5000,"5030",General_Ledger!H6:H5000),0)
B18: 5080 | C18: IT | D18: Expense | E18: =IFERROR(SUMIF(General_Ledger!D6:D5000,"5080",General_Ledger!G6:G5000),0) | F18: =IFERROR(SUMIF(General_Ledger!D6:D5000,"5080",General_Ledger!H6:H5000),0)
B19: 5090 | C19: Other | D19: Expense | E19: =IFERROR(SUMIF(General_Ledger!D6:D5000,"5090",General_Ledger!G6:G5000),0) | F19: =IFERROR(SUMIF(General_Ledger!D6:D5000,"5090",General_Ledger!H6:H5000),0)
C21: TOTALS | E21: =SUM(E6:E19) | F21: =SUM(F6:F19)
C22: DIFF | E22: =E21-F21

Sheet Chart_of_Accounts
B2: Chart of Accounts
B5: Code | C5: Account | D5: Type | E5: Bal | F5: Description
B6: 1000 | C6: Cash | D6: Asset | E6: Dr | F6: Cash on hand
B7: 1010 | C7: Bank Account | D7: Asset | E7: Dr | F7: Bank
B8: 1100 | C8: Accounts Receivable | D8: Asset | E8: Dr | F8: Owed by guests
B9: 1200 | C9: Inventory | D9: Asset | E9: Dr | F9: Supplies
B10: 1300 | C10: Fixed Assets | D10: Asset | E10: Dr | F10: Property/equip
B11: 2000 | C11: Accounts Payable | D11: Liability | E11: Cr | F11: Owed to vendors
B12: 2100 | C12: Salaries Payable | D12: Liability | E12: Cr | F12: Staff owed
B13: 2200 | C13: Loans Payable | D13: Liability | E13: Cr | F13: Loans
B14: 2300 | C14: Caution Deposits | D14: Liability | E14: Cr | F14: Guest deposits
B15: 3000 | C15: Owner Equity | D15: Equity | E15: Cr | F15: Capital
B16: 3100 | C16: Retained Earnings | D16: Equity | E16: Cr | F16: Profits
... B32: 5090 | C32: Other | D32: Expense | E32: Dr | F32: Misc

Sheet Dropdown_Lists
A1: MASTER REFERENCE — DO NOT EDIT. All dropdowns reference this sheet. Add new items below the headers only.
A2: Locations | B2: Unit Names | C2: Revenue Accounts | D2: Expense Categories | E2: Payment Methods | F2: Departments | G2: Months | H2: Staff Status
A3: All
A4: Agbowo | B4: Anooore 1 | C4: Room Revenue | D4: Salaries | E4: Cash | F4: Admin | G4: January | H4: Active
A5: UI | B5: Anooore 2 | C5: Shop Rent | D5: Construction | E5: Bank Transfer | F5: Maintenance | G5: February | H5: Non Active
B6: Anooore X | C6: Caution Fee Income | D6: Maintenance | E6: POS | F6: Project | G6: March
B7: Scholar | C7: Extra Charges | D7: Utilities | E7: Mobile Transfer | F7: Inventory | G7: April
B8: Scholar 2 | C8: Form & Legal Fees | D8: Inventory | E8: Cheque | F8: IT | G8: May
B9: Vine | C9: Other Income | D9: Administrative | F9: Accounts | G9: June
B10: Vine 1 | D10: Loans & Advances | G10: July
B11: Vine 2 | D11: Transportation | G11: August
B12: Vine Special | D12: IT & Communications | G12: September
B13: VINE X | D13: Other | G13: October
B14: Kollege | G14: November
B15: Premier | G15: December
B16: Provision Shop
B17: Salon
B18: Business Centre

Sheet Employee_Data
B2: Employee Records
B3: Staff payroll rates & contact info
B5: ID | C5: Name | D5: Designation | E5: Gender | F5: Phone | G5: Email | H5: Monthly Salary | I5: Status
B6: E001 | C6: Kingsley Chinedu Osuji | D6: Project Manager | F6: N/A | G6: N/A | H6: 60000 | I6: Active
B7: E002 | C7: Olapeju Omolayo Daniel | D7: Student Rel. Mgr | F7: N/A | G7: N/A | H7: 60000 | I7: Active
B8: E003 | C8: Sola A Dada | D8: Maintenance Officer | F8: N/A | G8: N/A | H8: 50000 | I8: Active
B9: E004 | C9: Salahudeen Fashiat Adeola | D9: Housekeeper | F9: N/A | G9: N/A | H9: 25000 | I9: Active
B10: E005 | C10: Oshobukola Bose Deborah | D10: Housekeeper | F10: N/A | G10: N/A | H10: 25000 | I10: Active
B11: E006 | C11: Abidemi Testimony Busari | D11: Front Desk | F11: N/A | G11: N/A | H11: 30000 | I11: Active
B12: E007 | C12: Oseni Bello Eniola | D12: Front Desk | F12: N/A | G12: N/A | H12: 30000 | I12: Active
B13: E008 | C13: Alaka Daniel Olayiwola | D13: Porter | F13: N/A | G13: N/A | H13: 20000 | I13: Active
B14: E009 | C14: Olajide Afolabi Nureen | D14: Cleaner | F14: N/A | G14: N/A | H14: 20000 | I14: Active
B15: E010 | C15: Security Guard 1 | D15: Security | F15: N/A | G15: N/A | H15: 25000 | I15: Active
B16: E011 | C16: Security Guard 2 | D16: Security | F16: N/A | G16: N/A | H16: 25000 | I16: Active
B17: E012 | C17: Eze David Chidi | D17: Electrician | F17: N/A | G17: N/A | H17: 30000 | I17: Active
C18: MONTHLY PAYROLL TOTAL | H18: =SUMIF(I6:I5000,"Active",H6:H5000)
